Workbook

Sheet Start Here
B2: Start here
B3: 10 minutes to set up. Works with any currency.
B5: 1. My Debts: one row per debt. Fill the blue columns. Only Name, Balance, APR and Minimum payment are needed.
B6: • Optional columns can stay blank: blank = no fee, no lock, no promo, not behind. The maths still works.
B7: • Early payoff rule: if your contract charges a fee for paying early, pick 'Allowed with a fee' and enter the fee and when it ends.
B8: The sheet compares the fee with the interest you'd save. If the fee costs more, extra payments wait until the fee ends.
B9: • Locked until a date: no extra goes in until that date (minimums still get paid).
B10: • Not sure: minimums only, until you ask your lender and change the rule.
B11: • 0% / promo deals: enter the promo end date and the APR after it. Deferred interest = Yes if back-interest is added when you don't clear it in time.
B12: 2. Plan: enter how much you can put toward all debts each month, the start month, and any one-time extra.
B13: 3. Plan: pick a payoff order and compare all four. Smart is CheckMaybe's default:
B14: behind-on-payments first → deferred-interest deadlines → highest APR (or, if minimums take 35%+ of income, the debt that frees up the most monthly money).
... B21: Example rows are made up. Replace or clear them.

Sheet Plan
B2: Debt Payoff Planner
B3: Set your budget here, list your debts on My Debts. Blue headers = you fill in.
B4: SETTING | C4: VALUE | H4: YOUR CHOSEN ORDER
B5: Money for debts each month | C5: 1500 | D5: Total you can put toward ALL debts each month, minimums included. | H5: DEBT-FREE | I5: =INDEX(C15:F15,Plan!$K$5) | K5: =MATCH($C$9,{"Smart (CheckMaybe order)","Avalanche (highest APR first)","Snowball (smallest balance first)","Cash-flow (free up monthly money first)"},0)
B6: Plan starts | C6: 46327 | D6: First month of the plan. Use the 1st of the month. | H6: MONTHS TO GO | I6: =INDEX(C16:F16,Plan!$K$5) | K6: =SUMPRODUCT(('My Debts'!$D$7:$D$18>0)*N(+'My Debts'!$F$7:$F$18))
B7: One-time extra (optional) | C7: 0 | D7: A bonus, tax refund or savings you'll throw at debt once. Leave 0 if none. | H7: INTEREST YOU'LL PAY | I7: =INDEX(C17:F17,Plan!$K$5) | K7: =AND(N($C$10)>0,$K$6/MAX(1,N($C$10))>=0.35)
B8: …in plan month # | C8: 1 | D8: Which month the one-time extra goes in (1 = first month). | H8: EARLY-PAYOFF FEES | I8: =INDEX(C18:F18,Plan!$K$5) | K8: =COUNTIFS('My Debts'!$D$7:$D$18,">0")
B9: Payoff order | C9: Smart (CheckMaybe order) | D9: Smart is the default. Compare all four on the right. | H9: MINIMUMS ONLY: INTEREST | I9: =IF(COUNT('My Debts'!$P$7:$P$18)=0,"",SUM('My Debts'!$P$7:$P$18))
B10: Monthly take-home income (optional) | C10: 3800 | D10: Used only to spot money pressure: if minimums take 35%+ of income, Smart frees up monthly money first. | H10: YOU SAVE VS MINIMUMS ONLY | I10: =IF(OR(I9="",NOT(ISNUMBER(I7))),"",MAX(0,I9-I7-I8))
H11: Minimums-only ignores debts that minimums never clear.
B13: COMPARE THE FOUR ORDERS | H13: TOTAL LEFT, FIRST 10 YEARS
C14: SMART | D14: AVALANCHE | E14: SNOWBALL | F14: CASH-FLOW
B15: Debt-free | C15: ='Calc Smart'!$B$5 | D15: ='Calc Avalanche'!$B$5 | E15: ='Calc Snowball'!$B$5 | F15: ='Calc Cashflow'!$B$5
B16: Months to debt-free | C16: ='Calc Smart'!$B$6 | D16: ='Calc Avalanche'!$B$6 | E16: ='Calc Snowball'!$B$6 | F16: ='Calc Cashflow'!$B$6
B17: Total interest | C17: ='Calc Smart'!$B$7 | D17: ='Calc Avalanche'!$B$7 | E17: ='Calc Snowball'!$B$7 | F17: ='Calc Cashflow'!$B$7
B18: Early-payoff fees paid | C18: ='Calc Smart'!$B$8 | D18: ='Calc Avalanche'!$B$8 | E18: ='Calc Snowball'!$B$8 | F18: ='Calc Cashflow'!$B$8
B19: Interest + fees | C19: ='Calc Smart'!$B$7+'Calc Smart'!$B$8 | D19: ='Calc Avalanche'!$B$7+'Calc Avalanche'!$B$8 | E19: ='Calc Snowball'!$B$7+'Calc Snowball'!$B$8 | F19: ='Calc Cashflow'!$B$7+'Calc Cashflow'!$B$8
B20: First debt cleared | C20: ='Calc Smart'!$B$9 | D20: ='Calc Avalanche'!$B$9 | E20: ='Calc Snowball'!$B$9 | F20: ='Calc Cashflow'!$B$9
B21: Green = best in that row. If a month shows "-", that plan doesn't finish within 30 years: raise the monthly amount.
B23: CHECKS
B24: =IF(Plan!$C$5<Plan!$K$6,"⚠ Your monthly amount is less than your minimum payments ("&TEXT(Plan!$K$6,"#,##0")&"). The plan assumes you still pay every minimum.","✓ Monthly amount covers all minimums ("&TEXT(Plan!$K$6,"#,##0")&"). Extra each month: "&TEXT(Plan!$C$5-Plan!$K$6,"#,##0"))
B25: =IF(COUNTIF('My Debts'!$Q$7:$Q$18,"Minimum doesn't cover interest*")>0,"⚠ At least one minimum payment doesn't cover its interest: that debt grows unless you pay more.","✓ Every minimum payment covers its interest.")
B26: =IF(COUNTIF('My Debts'!$Q$7:$Q$18,"Ask your lender*")+COUNTIF('My Debts'!$Q$7:$Q$18,"Locked*")+COUNTIF('My Debts'!$Q$7:$Q$18,"Wait*")>0,"ℹ Some debts get minimums only until they unlock (see My Debts › Early payoff check).","✓ No locked or uncertain debts.")
B27: =IF(Plan!$K$7,"ℹ Minimums take 35%+ of your income: Smart frees up monthly money first, then switches to highest APR.","ℹ Smart: behind-on-payments first, then 0%-promo deadlines, then highest APR.")
B28: =IF(COUNTIF('My Debts'!$AE$7:$AE$18,TRUE)>0,"⚠ A deferred-interest debt is cleared after its promo ends in this order: back-interest would be added (not in these totals). Smart avoids this when it can.","✓ No deferred-interest deadline missed in this order.")
B29: YOUR PAYOFF ORDER (CHOSEN)
B30: # | C30: DEBT | D30: BALANCE | E30: APR | F30: PAID OFF | G30: WHY / NOTE
B31: =IF(1<=Plan!$K$8,1,"") | C31: =IFERROR(INDEX('My Debts'!$B$7:$B$18,MATCH(1,'My Debts'!$S$7:$S$18,0)),"") | D31: =IFERROR(INDEX('My Debts'!$D$7:$D$18,MATCH(1,'My Debts'!$S$7:$S$18,0)),"") | E31: =IFERROR(INDEX('My Debts'!$E$7:$E$18,MATCH(1,'My Debts'!$S$7:$S$18,0)),"") | F31: =IFERROR(INDEX('My Debts'!$T$7:$T$18,MATCH(1,'My Debts'!$S$7:$S$18,0)),"") | G31: =IFERROR(INDEX('My Debts'!$V$7:$V$18,MATCH(1,'My Debts'!$S$7:$S$18,0)),"")
B32: =IF(2<=Plan!$K$8,2,"") | C32: =IFERROR(INDEX('My Debts'!$B$7:$B$18,MATCH(2,'My Debts'!$S$7:$S$18,0)),"") | D32: =IFERROR(INDEX('My Debts'!$D$7:$D$18,MATCH(2,'My Debts'!$S$7:$S$18,0)),"") | E32: =IFERROR(INDEX('My Debts'!$E$7:$E$18,MATCH(2,'My Debts'!$S$7:$S$18,0)),"") | F32: =IFERROR(INDEX('My Debts'!$T$7:$T$18,MATCH(2,'My Debts'!$S$7:$S$18,0)),"") | G32: =IFERROR(INDEX('My Debts'!$V$7:$V$18,MATCH(2,'My Debts'!$S$7:$S$18,0)),"")
B33: =IF(3<=Plan!$K$8,3,"") | C33: =IFERROR(INDEX('My Debts'!$B$7:$B$18,MATCH(3,'My Debts'!$S$7:$S$18,0)),"") | D33: =IFERROR(INDEX('My Debts'!$D$7:$D$18,MATCH(3,'My Debts'!$S$7:$S$18,0)),"") | E33: =IFERROR(INDEX('My Debts'!$E$7:$E$18,MATCH(3,'My Debts'!$S$7:$S$18,0)),"") | F33: =IFERROR(INDEX('My Debts'!$T$7:$T$18,MATCH(3,'My Debts'!$S$7:$S$18,0)),"") | G33: =IFERROR(INDEX('My Debts'!$V$7:$V$18,MATCH(3,'My Debts'!$S$7:$S$18,0)),"")
B34: =IF(4<=Plan!$K$8,4,"") | C34: =IFERROR(INDEX('My Debts'!$B$7:$B$18,MATCH(4,'My Debts'!$S$7:$S$18,0)),"") | D34: =IFERROR(INDEX('My Debts'!$D$7:$D$18,MATCH(4,'My Debts'!$S$7:$S$18,0)),"") | E34: =IFERROR(INDEX('My Debts'!$E$7:$E$18,MATCH(4,'My Debts'!$S$7:$S$18,0)),"") | F34: =IFERROR(INDEX('My Debts'!$T$7:$T$18,MATCH(4,'My Debts'!$S$7:$S$18,0)),"") | G34: =IFERROR(INDEX('My Debts'!$V$7:$V$18,MATCH(4,'My Debts'!$S$7:$S$18,0)),"")
B35: =IF(5<=Plan!$K$8,5,"") | C35: =IFERROR(INDEX('My Debts'!$B$7:$B$18,MATCH(5,'My Debts'!$S$7:$S$18,0)),"") | D35: =IFERROR(INDEX('My Debts'!$D$7:$D$18,MATCH(5,'My Debts'!$S$7:$S$18,0)),"") | E35: =IFERROR(INDEX('My Debts'!$E$7:$E$18,MATCH(5,'My Debts'!$S$7:$S$18,0)),"") | F35: =IFERROR(INDEX('My Debts'!$T$7:$T$18,MATCH(5,'My Debts'!$S$7:$S$18,0)),"") | G35: =IFERROR(INDEX('My Debts'!$V$7:$V$18,MATCH(5,'My Debts'!$S$7:$S$18,0)),"")
B36: =IF(6<=Plan!$K$8,6,"") | C36: =IFERROR(INDEX('My Debts'!$B$7:$B$18,MATCH(6,'My Debts'!$S$7:$S$18,0)),"") | D36: =IFERROR(INDEX('My Debts'!$D$7:$D$18,MATCH(6,'My Debts'!$S$7:$S$18,0)),"") | E36: =IFERROR(INDEX('My Debts'!$E$7:$E$18,MATCH(6,'My Debts'!$S$7:$S$18,0)),"") | F36: =IFERROR(INDEX('My Debts'!$T$7:$T$18,MATCH(6,'My Debts'!$S$7:$S$18,0)),"") | G36: =IFERROR(INDEX('My Debts'!$V$7:$V$18,MATCH(6,'My Debts'!$S$7:$S$18,0)),"")
B37: =IF(7<=Plan!$K$8,7,"") | C37: =IFERROR(INDEX('My Debts'!$B$7:$B$18,MATCH(7,'My Debts'!$S$7:$S$18,0)),"") | D37: =IFERROR(INDEX('My Debts'!$D$7:$D$18,MATCH(7,'My Debts'!$S$7:$S$18,0)),"") | E37: =IFERROR(INDEX('My Debts'!$E$7:$E$18,MATCH(7,'My Debts'!$S$7:$S$18,0)),"") | F37: =IFERROR(INDEX('My Debts'!$T$7:$T$18,MATCH(7,'My Debts'!$S$7:$S$18,0)),"") | G37: =IFERROR(INDEX('My Debts'!$V$7:$V$18,MATCH(7,'My Debts'!$S$7:$S$18,0)),"")
B38: =IF(8<=Plan!$K$8,8,"") | C38: =IFERROR(INDEX('My Debts'!$B$7:$B$18,MATCH(8,'My Debts'!$S$7:$S$18,0)),"") | D38: =IFERROR(INDEX('My Debts'!$D$7:$D$18,MATCH(8,'My Debts'!$S$7:$S$18,0)),"") | E38: =IFERROR(INDEX('My Debts'!$E$7:$E$18,MATCH(8,'My Debts'!$S$7:$S$18,0)),"") | F38: =IFERROR(INDEX('My Debts'!$T$7:$T$18,MATCH(8,'My Debts'!$S$7:$S$18,0)),"") | G38: =IFERROR(INDEX('My Debts'!$V$7:$V$18,MATCH(8,'My Debts'!$S$7:$S$18,0)),"")
B39: =IF(9<=Plan!$K$8,9,"") | C39: =IFERROR(INDEX('My Debts'!$B$7:$B$18,MATCH(9,'My Debts'!$S$7:$S$18,0)),"") | D39: =IFERROR(INDEX('My Debts'!$D$7:$D$18,MATCH(9,'My Debts'!$S$7:$S$18,0)),"") | E39: =IFERROR(INDEX('My Debts'!$E$7:$E$18,MATCH(9,'My Debts'!$S$7:$S$18,0)),"") | F39: =IFERROR(INDEX('My Debts'!$T$7:$T$18,MATCH(9,'My Debts'!$S$7:$S$18,0)),"") | G39: =IFERROR(INDEX('My Debts'!$V$7:$V$18,MATCH(9,'My Debts'!$S$7:$S$18,0)),"")
B40: =IF(10<=Plan!$K$8,10,"") | C40: =IFERROR(INDEX('My Debts'!$B$7:$B$18,MATCH(10,'My Debts'!$S$7:$S$18,0)),"") | D40: =IFERROR(INDEX('My Debts'!$D$7:$D$18,MATCH(10,'My Debts'!$S$7:$S$18,0)),"") | E40: =IFERROR(INDEX('My Debts'!$E$7:$E$18,MATCH(10,'My Debts'!$S$7:$S$18,0)),"") | F40: =IFERROR(INDEX('My Debts'!$T$7:$T$18,MATCH(10,'My Debts'!$S$7:$S$18,0)),"") | G40: =IFERROR(INDEX('My Debts'!$V$7:$V$18,MATCH(10,'My Debts'!$S$7:$S$18,0)),"")
B41: =IF(11<=Plan!$K$8,11,"") | C41: =IFERROR(INDEX('My Debts'!$B$7:$B$18,MATCH(11,'My Debts'!$S$7:$S$18,0)),"") | D41: =IFERROR(INDEX('My Debts'!$D$7:$D$18,MATCH(11,'My Debts'!$S$7:$S$18,0)),"") | E41: =IFERROR(INDEX('My Debts'!$E$7:$E$18,MATCH(11,'My Debts'!$S$7:$S$18,0)),"") | F41: =IFERROR(INDEX('My Debts'!$T$7:$T$18,MATCH(11,'My Debts'!$S$7:$S$18,0)),"") | G41: =IFERROR(INDEX('My Debts'!$V$7:$V$18,MATCH(11,'My Debts'!$S$7:$S$18,0)),"")
B42: =IF(12<=Plan!$K$8,12,"") | C42: =IFERROR(INDEX('My Debts'!$B$7:$B$18,MATCH(12,'My Debts'!$S$7:$S$18,0)),"") | D42: =IFERROR(INDEX('My Debts'!$D$7:$D$18,MATCH(12,'My Debts'!$S$7:$S$18,0)),"") | E42: =IFERROR(INDEX('My Debts'!$E$7:$E$18,MATCH(12,'My Debts'!$S$7:$S$18,0)),"") | F42: =IFERROR(INDEX('My Debts'!$T$7:$T$18,MATCH(12,'My Debts'!$S$7:$S$18,0)),"") | G42: =IFERROR(INDEX('My Debts'!$V$7:$V$18,MATCH(12,'My Debts'!$S$7:$S$18,0)),"")
B44: Estimates only, not financial advice. Interest is worked out monthly at APR÷12; your lender's method, fees and rules are the final word. Example debts are made up: replace them with yours.
H45: INTEREST + FEES BY ORDER

Sheet My Debts
B2: My Debts
B3: One row per debt. Blue = you fill in (blank is fine for optional ones). Orange = calculated.
B4: Any currency works: just use the same one everywhere. APR as a percent (24.99%).
B6: DEBT NAME | C6: TYPE | D6: BALANCE NOW | E6: APR | F6: MINIMUM MONTHLY PAYMENT | G6: BEHIND ON PAYMENTS? | H6: EARLY PAYOFF RULE | I6: FEE TO PAY OFF EARLY | J6: FEE / LOCK ENDS | K6: 0% / PROMO RATE ENDS | L6: APR AFTER PROMO | M6: DEFERRED INTEREST? | N6: NOTES | O6: INTEREST THIS MONTH | P6: INTEREST IF MINIMUMS ONLY | Q6: EARLY PAYOFF CHECK | R6: EXTRA CAN START | S6: ORDER # | T6: PAID OFF | V6: WHY / NOTE
B7: Store card (sample) | C7: Store card | D7: 1200 | E7: 0 | F7: 60 | G7: No | H7: Allowed, no fee | K7: 46508 | L7: 0.2999 | M7: Yes | N7: 0% until May | O7: =IF(AND(ISNUMBER($D7),$D7>0),$D7*N(+$E7)/12,"") | P7: =IF(NOT(AND(ISNUMBER($D7),$D7>0)),"",IF(N(+$F7)<=0,"No minimum",IF(N(+$F7)<=$D7*N(+$E7)/12,"Never at minimum",IF(N(+$E7)=0,0,N(+$F7)*NPER(N(+$E7)/12,-N(+$F7),$D7)-$D7)))) | Q7: =IF(NOT(AND(ISNUMBER($D7),$D7>0)),"",IF(AND(N(+$F7)>0,N(+$F7)<=$D7*N(+$E7)/12),"Minimum doesn't cover interest: pay more here",IF(N(+$F7)<=0,"Add the minimum payment",IF($H7="Not sure - ask lender","Ask your lender before paying extra",IF($H7="Locked until a date",IF(N(+$J7)=0,"Locked: add the unlock date","Locked until "&CHOOSE(MONTH($J7),"Jan","Feb","Mar","Apr","May","Jun","Jul","Aug","Sep","Oct","Nov","Dec")&" "&YEAR($J7)),IF($H7="Allowed with a fee",IF(N(+$I7)=0,"Add the fee amount (blank = no fee)",IF(NOT(ISNUMBER($P7)),"Fee is worth paying: minimums never clear this",IF(N(+$I7)<$P7,"Worth it: saves about "&TEXT($P7-$I7,"#,##0")&" after the fee","Wait: the fee is more than the interest you'd save"&IF(N(+$J7)>0," (until "&CHOOSE(MONTH($J7),"Jan","Feb","Mar","Apr","May","Jun","Jul","Aug","Sep","Oct","Nov","Dec")&" "&YEAR($J7)&")","")))),"OK to pay early")))))) | R7: =IF($U7="","",IF($U7<=Plan!$C$6,"Now",IF($U7>=DATE(2199,12,1),"Not yet",CHOOSE(MONTH($U7),"Jan","Feb","Mar","Apr","May","Jun","Jul","Aug","Sep","Oct","Nov","Dec")&" "&YEAR($U7)))) | S7: =IF(AND(ISNUMBER($D7),$D7>0),CHOOSE(Plan!$K$5,AA7,AB7,AC7,AD7),"") | T7: =IF(AND(ISNUMBER($D7),$D7>0),CHOOSE(Plan!$K$5,'Calc Smart'!C$10,'Calc Avalanche'!C$10,'Calc Snowball'!C$10,'Calc Cashflow'!C$10),"") | U7: =IF(NOT(AND(ISNUMBER($D7),$D7>0)),"",IF($H7="Not sure - ask lender",DATE(2199,12,1),IF($H7="Locked until a date",IF(N(+$J7)=0,DATE(2199,12,1),$J7),IF(AND($H7="Allowed with a fee",N(+$I7)>0,ISNUMBER($P7),N(+$I7)>=N(+$P7)),IF(N(+$J7)=0,DATE(2199,12,1),$J7),DATE(1900,1,1))))) | V7: =IF(NOT(AND(ISNUMBER($D7),$D7>0)),"",IF($AE7,"⚠ Cleared after the promo ends ("&CHOOSE(MONTH($K7),"Jan","Feb","Mar","Apr","May","Jun","Jul","Aug","Sep","Oct","Nov","Dec")&" "&YEAR($K7)&"): back-interest likely, not counted here. Try Smart.",IF($G7="Yes","Behind on payments: deal with this first",IF(AND($M7="Yes",N(+$K7)>Plan!$C$6),"Deferred interest: clear by "&CHOOSE(MONTH($K7),"Jan","Feb","Mar","Apr","May","Jun","Jul","Aug","Sep","Oct","Nov","Dec")&" "&YEAR($K7)&" or back-interest is added",IF($U7>Plan!$C$6,$Q7,CHOOSE(Plan!$K$5,IF(Plan!$K$7,"Frees up monthly money fastest","Highest APR among the rest"),"APR "&TEXT(N(+$E7),"0.0%"),"Balance "&TEXT($D7,"#,##0"),"Frees "&TEXT(N(+$F7),"#,##0")&"/month when cleared")))))) | W7: =IF(AND(ISNUMBER($D7),$D7>0),1000-N(+$E7)*100+ROW()/1000000,"") | X7: =IF(AND(ISNUMBER($D7),$D7>0),$D7+ROW()/1000000,"") | Y7: =IF(AND(ISNUMBER($D7),$D7>0),1000-IF(N(+$F7)>0,N(+$F7)/$D7,0)*100+ROW()/1000000,"") | Z7: =IF(AND(ISNUMBER($D7),$D7>0),IF($G7="Yes",0,IF(AND($M7="Yes",N(+$K7)>Plan!$C$6),1,2))*1000000+IF(IF($G7="Yes",0,IF(AND($M7="Yes",N(+$K7)>Plan!$C$6),1,2))=0,1000-IF(N(+$F7)>0,N(+$F7)/$D7,0)*100+ROW()/1000000,IF(IF($G7="Yes",0,IF(AND($M7="Yes",N(+$K7)>Plan!$C$6),1,2))=1,N(+$K7)/100,IF(Plan!$K$7,1000-IF(N(+$F7)>0,N(+$F7)/$D7,0)*100+ROW()/1000000,1000-N(+$E7)*100+ROW()/1000000))),"") | AA7: =IF(Z7="","",COUNTIF(Z$7:Z$18,"<"&Z7)+1) | AB7: =IF(W7="","",COUNTIF(W$7:W$18,"<"&W7)+1) | AC7: =IF(X7="","",COUNTIF(X$7:X$18,"<"&X7)+1) | AD7: =IF(Y7="","",COUNTIF(Y$7:Y$18,"<"&Y7)+1) | AE7: =AND(AND(ISNUMBER($D7),$D7>0),$M7="Yes",N(+$K7)>0,ISNUMBER($T7),N(+$T7)>=N(+$K7))
B8: Credit card (sample) | C8: Credit card | D8: 4800 | E8: 0.2449 | F8: 120 | G8: No | H8: Allowed, no fee | O8: =IF(AND(ISNUMBER($D8),$D8>0),$D8*N(+$E8)/12,"") | P8: =IF(NOT(AND(ISNUMBER($D8),$D8>0)),"",IF(N(+$F8)<=0,"No minimum",IF(N(+$F8)<=$D8*N(+$E8)/12,"Never at minimum",IF(N(+$E8)=0,0,N(+$F8)*NPER(N(+$E8)/12,-N(+$F8),$D8)-$D8)))) | Q8: =IF(NOT(AND(ISNUMBER($D8),$D8>0)),"",IF(AND(N(+$F8)>0,N(+$F8)<=$D8*N(+$E8)/12),"Minimum doesn't cover interest: pay more here",IF(N(+$F8)<=0,"Add the minimum payment",IF($H8="Not sure - ask lender","Ask your lender before paying extra",IF($H8="Locked until a date",IF(N(+$J8)=0,"Locked: add the unlock date","Locked until "&CHOOSE(MONTH($J8),"Jan","Feb","Mar","Apr","May","Jun","Jul","Aug","Sep","Oct","Nov","Dec")&" "&YEAR($J8)),IF($H8="Allowed with a fee",IF(N(+$I8)=0,"Add the fee amount (blank = no fee)",IF(NOT(ISNUMBER($P8)),"Fee is worth paying: minimums never clear this",IF(N(+$I8)<$P8,"Worth it: saves about "&TEXT($P8-$I8,"#,##0")&" after the fee","Wait: the fee is more than the interest you'd save"&IF(N(+$J8)>0," (until "&CHOOSE(MONTH($J8),"Jan","Feb","Mar","Apr","May","Jun","Jul","Aug","Sep","Oct","Nov","Dec")&" "&YEAR($J8)&")","")))),"OK to pay early")))))) | R8: =IF($U8="","",IF($U8<=Plan!$C$6,"Now",IF($U8>=DATE(2199,12,1),"Not yet",CHOOSE(MONTH($U8),"Jan","Feb","Mar","Apr","May","Jun","Jul","Aug","Sep","Oct","Nov","Dec")&" "&YEAR($U8)))) | S8: =IF(AND(ISNUMBER($D8),$D8>0),CHOOSE(Plan!$K$5,AA8,AB8,AC8,AD8),"") | T8: =IF(AND(ISNUMBER($D8),$D8>0),CHOOSE(Plan!$K$5,'Calc Smart'!D$10,'Calc Avalanche'!D$10,'Calc Snowball'!D$10,'Calc Cashflow'!D$10),"") | U8: =IF(NOT(AND(ISNUMBER($D8),$D8>0)),"",IF($H8="Not sure - ask lender",DATE(2199,12,1),IF($H8="Locked until a date",IF(N(+$J8)=0,DATE(2199,12,1),$J8),IF(AND($H8="Allowed with a fee",N(+$I8)>0,ISNUMBER($P8),N(+$I8)>=N(+$P8)),IF(N(+$J8)=0,DATE(2199,12,1),$J8),DATE(1900,1,1))))) | V8: =IF(NOT(AND(ISNUMBER($D8),$D8>0)),"",IF($AE8,"⚠ Cleared after the promo ends ("&CHOOSE(MONTH($K8),"Jan","Feb","Mar","Apr","May","Jun","Jul","Aug","Sep","Oct","Nov","Dec")&" "&YEAR($K8)&"): back-interest likely, not counted here. Try Smart.",IF($G8="Yes","Behind on payments: deal with this first",IF(AND($M8="Yes",N(+$K8)>Plan!$C$6),"Deferred interest: clear by "&CHOOSE(MONTH($K8),"Jan","Feb","Mar","Apr","May","Jun","Jul","Aug","Sep","Oct","Nov","Dec")&" "&YEAR($K8)&" or back-interest is added",IF($U8>Plan!$C$6,$Q8,CHOOSE(Plan!$K$5,IF(Plan!$K$7,"Frees up monthly money fastest","Highest APR among the rest"),"APR "&TEXT(N(+$E8),"0.0%"),"Balance "&TEXT($D8,"#,##0"),"Frees "&TEXT(N(+$F8),"#,##0")&"/month when cleared")))))) | W8: =IF(AND(ISNUMBER($D8),$D8>0),1000-N(+$E8)*100+ROW()/1000000,"") | X8: =IF(AND(ISNUMBER($D8),$D8>0),$D8+ROW()/1000000,"") | Y8: =IF(AND(ISNUMBER($D8),$D8>0),1000-IF(N(+$F8)>0,N(+$F8)/$D8,0)*100+ROW()/1000000,"") | Z8: =IF(AND(ISNUMBER($D8),$D8>0),IF($G8="Yes",0,IF(AND($M8="Yes",N(+$K8)>Plan!$C$6),1,2))*1000000+IF(IF($G8="Yes",0,IF(AND($M8="Yes",N(+$K8)>Plan!$C$6),1,2))=0,1000-IF(N(+$F8)>0,N(+$F8)/$D8,0)*100+ROW()/1000000,IF(IF($G8="Yes",0,IF(AND($M8="Yes",N(+$K8)>Plan!$C$6),1,2))=1,N(+$K8)/100,IF(Plan!$K$7,1000-IF(N(+$F8)>0,N(+$F8)/$D8,0)*100+ROW()/1000000,1000-N(+$E8)*100+ROW()/1000000))),"") | AA8: =IF(Z8="","",COUNTIF(Z$7:Z$18,"<"&Z8)+1) | AB8: =IF(W8="","",COUNTIF(W$7:W$18,"<"&W8)+1) | AC8: =IF(X8="","",COUNTIF(X$7:X$18,"<"&X8)+1) | AD8: =IF(Y8="","",COUNTIF(Y$7:Y$18,"<"&Y8)+1) | AE8: =AND(AND(ISNUMBER($D8),$D8>0),$M8="Yes",N(+$K8)>0,ISNUMBER($T8),N(+$T8)>=N(+$K8))
B9: Car loan (sample) | C9: Car loan | D9: 9500 | E9: 0.089 | F9: 310 | G9: No | H9: Allowed with a fee | I9: 400 | J9: 46600 | N9: fee until Aug 2027 | O9: =IF(AND(ISNUMBER($D9),$D9>0),$D9*N(+$E9)/12,"") | P9: =IF(NOT(AND(ISNUMBER($D9),$D9>0)),"",IF(N(+$F9)<=0,"No minimum",IF(N(+$F9)<=$D9*N(+$E9)/12,"Never at minimum",IF(N(+$E9)=0,0,N(+$F9)*NPER(N(+$E9)/12,-N(+$F9),$D9)-$D9)))) | Q9: =IF(NOT(AND(ISNUMBER($D9),$D9>0)),"",IF(AND(N(+$F9)>0,N(+$F9)<=$D9*N(+$E9)/12),"Minimum doesn't cover interest: pay more here",IF(N(+$F9)<=0,"Add the minimum payment",IF($H9="Not sure - ask lender","Ask your lender before paying extra",IF($H9="Locked until a date",IF(N(+$J9)=0,"Locked: add the unlock date","Locked until "&CHOOSE(MONTH($J9),"Jan","Feb","Mar","Apr","May","Jun","Jul","Aug","Sep","Oct","Nov","Dec")&" "&YEAR($J9)),IF($H9="Allowed with a fee",IF(N(+$I9)=0,"Add the fee amount (blank = no fee)",IF(NOT(ISNUMBER($P9)),"Fee is worth paying: minimums never clear this",IF(N(+$I9)<$P9,"Worth it: saves about "&TEXT($P9-$I9,"#,##0")&" after the fee","Wait: the fee is more than the interest you'd save"&IF(N(+$J9)>0," (until "&CHOOSE(MONTH($J9),"Jan","Feb","Mar","Apr","May","Jun","Jul","Aug","Sep","Oct","Nov","Dec")&" "&YEAR($J9)&")","")))),"OK to pay early")))))) | R9: =IF($U9="","",IF($U9<=Plan!$C$6,"Now",IF($U9>=DATE(2199,12,1),"Not yet",CHOOSE(MONTH($U9),"Jan","Feb","Mar","Apr","May","Jun","Jul","Aug","Sep","Oct","Nov","Dec")&" "&YEAR($U9)))) | S9: =IF(AND(ISNUMBER($D9),$D9>0),CHOOSE(Plan!$K$5,AA9,AB9,AC9,AD9),"") | T9: =IF(AND(ISNUMBER($D9),$D9>0),CHOOSE(Plan!$K$5,'Calc Smart'!E$10,'Calc Avalanche'!E$10,'Calc Snowball'!E$10,'Calc Cashflow'!E$10),"") | U9: =IF(NOT(AND(ISNUMBER($D9),$D9>0)),"",IF($H9="Not sure - ask lender",DATE(2199,12,1),IF($H9="Locked until a date",IF(N(+$J9)=0,DATE(2199,12,1),$J9),IF(AND($H9="Allowed with a fee",N(+$I9)>0,ISNUMBER($P9),N(+$I9)>=N(+$P9)),IF(N(+$J9)=0,DATE(2199,12,1),$J9),DATE(1900,1,1))))) | V9: =IF(NOT(AND(ISNUMBER($D9),$D9>0)),"",IF($AE9,"⚠ Cleared after the promo ends ("&CHOOSE(MONTH($K9),"Jan","Feb","Mar","Apr","May","Jun","Jul","Aug","Sep","Oct","Nov","Dec")&" "&YEAR($K9)&"): back-interest likely, not counted here. Try Smart.",IF($G9="Yes","Behind on payments: deal with this first",IF(AND($M9="Yes",N(+$K9)>Plan!$C$6),"Deferred interest: clear by "&CHOOSE(MONTH($K9),"Jan","Feb","Mar","Apr","May","Jun","Jul","Aug","Sep","Oct","Nov","Dec")&" "&YEAR($K9)&" or back-interest is added",IF($U9>Plan!$C$6,$Q9,CHOOSE(Plan!$K$5,IF(Plan!$K$7,"Frees up monthly money fastest","Highest APR among the rest"),"APR "&TEXT(N(+$E9),"0.0%"),"Balance "&TEXT($D9,"#,##0"),"Frees "&TEXT(N(+$F9),"#,##0")&"/month when cleared")))))) | W9: =IF(AND(ISNUMBER($D9),$D9>0),1000-N(+$E9)*100+ROW()/1000000,"") | X9: =IF(AND(ISNUMBER($D9),$D9>0),$D9+ROW()/1000000,"") | Y9: =IF(AND(ISNUMBER($D9),$D9>0),1000-IF(N(+$F9)>0,N(+$F9)/$D9,0)*100+ROW()/1000000,"") | Z9: =IF(AND(ISNUMBER($D9),$D9>0),IF($G9="Yes",0,IF(AND($M9="Yes",N(+$K9)>Plan!$C$6),1,2))*1000000+IF(IF($G9="Yes",0,IF(AND($M9="Yes",N(+$K9)>Plan!$C$6),1,2))=0,1000-IF(N(+$F9)>0,N(+$F9)/$D9,0)*100+ROW()/1000000,IF(IF($G9="Yes",0,IF(AND($M9="Yes",N(+$K9)>Plan!$C$6),1,2))=1,N(+$K9)/100,IF(Plan!$K$7,1000-IF(N(+$F9)>0,N(+$F9)/$D9,0)*100+ROW()/1000000,1000-N(+$E9)*100+ROW()/1000000))),"") | AA9: =IF(Z9="","",COUNTIF(Z$7:Z$18,"<"&Z9)+1) | AB9: =IF(W9="","",COUNTIF(W$7:W$18,"<"&W9)+1) | AC9: =IF(X9="","",COUNTIF(X$7:X$18,"<"&X9)+1) | AD9: =IF(Y9="","",COUNTIF(Y$7:Y$18,"<"&Y9)+1) | AE9: =AND(AND(ISNUMBER($D9),$D9>0),$M9="Yes",N(+$K9)>0,ISNUMBER($T9),N(+$T9)>=N(+$K9))
B10: Personal loan (sample) | C10: Personal loan | D10: 3000 | E10: 0.159 | F10: 140 | G10: No | H10: Not sure - ask lender | N10: call lender | O10: =IF(AND(ISNUMBER($D10),$D10>0),$D10*N(+$E10)/12,"") | P10: =IF(NOT(AND(ISNUMBER($D10),$D10>0)),"",IF(N(+$F10)<=0,"No minimum",IF(N(+$F10)<=$D10*N(+$E10)/12,"Never at minimum",IF(N(+$E10)=0,0,N(+$F10)*NPER(N(+$E10)/12,-N(+$F10),$D10)-$D10)))) | Q10: =IF(NOT(AND(ISNUMBER($D10),$D10>0)),"",IF(AND(N(+$F10)>0,N(+$F10)<=$D10*N(+$E10)/12),"Minimum doesn't cover interest: pay more here",IF(N(+$F10)<=0,"Add the minimum payment",IF($H10="Not sure - ask lender","Ask your lender before paying extra",IF($H10="Locked until a date",IF(N(+$J10)=0,"Locked: add the unlock date","Locked until "&CHOOSE(MONTH($J10),"Jan","Feb","Mar","Apr","May","Jun","Jul","Aug","Sep","Oct","Nov","Dec")&" "&YEAR($J10)),IF($H10="Allowed with a fee",IF(N(+$I10)=0,"Add the fee amount (blank = no fee)",IF(NOT(ISNUMBER($P10)),"Fee is worth paying: minimums never clear this",IF(N(+$I10)<$P10,"Worth it: saves about "&TEXT($P10-$I10,"#,##0")&" after the fee","Wait: the fee is more than the interest you'd save"&IF(N(+$J10)>0," (until "&CHOOSE(MONTH($J10),"Jan","Feb","Mar","Apr","May","Jun","Jul","Aug","Sep","Oct","Nov","Dec")&" "&YEAR($J10)&")","")))),"OK to pay early")))))) | R10: =IF($U10="","",IF($U10<=Plan!$C$6,"Now",IF($U10>=DATE(2199,12,1),"Not yet",CHOOSE(MONTH($U10),"Jan","Feb","Mar","Apr","May","Jun","Jul","Aug","Sep","Oct","Nov","Dec")&" "&YEAR($U10)))) | S10: =IF(AND(ISNUMBER($D10),$D10>0),CHOOSE(Plan!$K$5,AA10,AB10,AC10,AD10),"") | T10: =IF(AND(ISNUMBER($D10),$D10>0),CHOOSE(Plan!$K$5,'Calc Smart'!F$10,'Calc Avalanche'!F$10,'Calc Snowball'!F$10,'Calc Cashflow'!F$10),"") | U10: =IF(NOT(AND(ISNUMBER($D10),$D10>0)),"",IF($H10="Not sure - ask lender",DATE(2199,12,1),IF($H10="Locked until a date",IF(N(+$J10)=0,DATE(2199,12,1),$J10),IF(AND($H10="Allowed with a fee",N(+$I10)>0,ISNUMBER($P10),N(+$I10)>=N(+$P10)),IF(N(+$J10)=0,DATE(2199,12,1),$J10),DATE(1900,1,1))))) | V10: =IF(NOT(AND(ISNUMBER($D10),$D10>0)),"",IF($AE10,"⚠ Cleared after the promo ends ("&CHOOSE(MONTH($K10),"Jan","Feb","Mar","Apr","May","Jun","Jul","Aug","Sep","Oct","Nov","Dec")&" "&YEAR($K10)&"): back-interest likely, not counted here. Try Smart.",IF($G10="Yes","Behind on payments: deal with this first",IF(AND($M10="Yes",N(+$K10)>Plan!$C$6),"Deferred interest: clear by "&CHOOSE(MONTH($K10),"Jan","Feb","Mar","Apr","May","Jun","Jul","Aug","Sep","Oct","Nov","Dec")&" "&YEAR($K10)&" or back-interest is added",IF($U10>Plan!$C$6,$Q10,CHOOSE(Plan!$K$5,IF(Plan!$K$7,"Frees up monthly money fastest","Highest APR among the rest"),"APR "&TEXT(N(+$E10),"0.0%"),"Balance "&TEXT($D10,"#,##0"),"Frees "&TEXT(N(+$F10),"#,##0")&"/month when cleared")))))) | W10: =IF(AND(ISNUMBER($D10),$D10>0),1000-N(+$E10)*100+ROW()/1000000,"") | X10: =IF(AND(ISNUMBER($D10),$D10>0),$D10+ROW()/1000000,"") | Y10: =IF(AND(ISNUMBER($D10),$D10>0),1000-IF(N(+$F10)>0,N(+$F10)/$D10,0)*100+ROW()/1000000,"") | Z10: =IF(AND(ISNUMBER($D10),$D10>0),IF($G10="Yes",0,IF(AND($M10="Yes",N(+$K10)>Plan!$C$6),1,2))*1000000+IF(IF($G10="Yes",0,IF(AND($M10="Yes",N(+$K10)>Plan!$C$6),1,2))=0,1000-IF(N(+$F10)>0,N(+$F10)/$D10,0)*100+ROW()/1000000,IF(IF($G10="Yes",0,IF(AND($M10="Yes",N(+$K10)>Plan!$C$6),1,2))=1,N(+$K10)/100,IF(Plan!$K$7,1000-IF(N(+$F10)>0,N(+$F10)/$D10,0)*100+ROW()/1000000,1000-N(+$E10)*100+ROW()/1000000))),"") | AA10: =IF(Z10="","",COUNTIF(Z$7:Z$18,"<"&Z10)+1) | AB10: =IF(W10="","",COUNTIF(W$7:W$18,"<"&W10)+1) | AC10: =IF(X10="","",COUNTIF(X$7:X$18,"<"&X10)+1) | AD10: =IF(Y10="","",COUNTIF(Y$7:Y$18,"<"&Y10)+1) | AE10: =AND(AND(ISNUMBER($D10),$D10>0),$M10="Yes",N(+$K10)>0,ISNUMBER($T10),N(+$T10)>=N(+$K10))
B11: Medical bill (sample) | C11: Medical bill | D11: 650 | E11: 0 | F11: 50 | G11: Yes | N11: late notice | O11: =IF(AND(ISNUMBER($D11),$D11>0),$D11*N(+$E11)/12,"") | P11: =IF(NOT(AND(ISNUMBER($D11),$D11>0)),"",IF(N(+$F11)<=0,"No minimum",IF(N(+$F11)<=$D11*N(+$E11)/12,"Never at minimum",IF(N(+$E11)=0,0,N(+$F11)*NPER(N(+$E11)/12,-N(+$F11),$D11)-$D11)))) | Q11: =IF(NOT(AND(ISNUMBER($D11),$D11>0)),"",IF(AND(N(+$F11)>0,N(+$F11)<=$D11*N(+$E11)/12),"Minimum doesn't cover interest: pay more here",IF(N(+$F11)<=0,"Add the minimum payment",IF($H11="Not sure - ask lender","Ask your lender before paying extra",IF($H11="Locked until a date",IF(N(+$J11)=0,"Locked: add the unlock date","Locked until "&CHOOSE(MONTH($J11),"Jan","Feb","Mar","Apr","May","Jun","Jul","Aug","Sep","Oct","Nov","Dec")&" "&YEAR($J11)),IF($H11="Allowed with a fee",IF(N(+$I11)=0,"Add the fee amount (blank = no fee)",IF(NOT(ISNUMBER($P11)),"Fee is worth paying: minimums never clear this",IF(N(+$I11)<$P11,"Worth it: saves about "&TEXT($P11-$I11,"#,##0")&" after the fee","Wait: the fee is more than the interest you'd save"&IF(N(+$J11)>0," (until "&CHOOSE(MONTH($J11),"Jan","Feb","Mar","Apr","May","Jun","Jul","Aug","Sep","Oct","Nov","Dec")&" "&YEAR($J11)&")","")))),"OK to pay early")))))) | R11: =IF($U11="","",IF($U11<=Plan!$C$6,"Now",IF($U11>=DATE(2199,12,1),"Not yet",CHOOSE(MONTH($U11),"Jan","Feb","Mar","Apr","May","Jun","Jul","Aug","Sep","Oct","Nov","Dec")&" "&YEAR($U11)))) | S11: =IF(AND(ISNUMBER($D11),$D11>0),CHOOSE(Plan!$K$5,AA11,AB11,AC11,AD11),"") | T11: =IF(AND(ISNUMBER($D11),$D11>0),CHOOSE(Plan!$K$5,'Calc Smart'!G$10,'Calc Avalanche'!G$10,'Calc Snowball'!G$10,'Calc Cashflow'!G$10),"") | U11: =IF(NOT(AND(ISNUMBER($D11),$D11>0)),"",IF($H11="Not sure - ask lender",DATE(2199,12,1),IF($H11="Locked until a date",IF(N(+$J11)=0,DATE(2199,12,1),$J11),IF(AND($H11="Allowed with a fee",N(+$I11)>0,ISNUMBER($P11),N(+$I11)>=N(+$P11)),IF(N(+$J11)=0,DATE(2199,12,1),$J11),DATE(1900,1,1))))) | V11: =IF(NOT(AND(ISNUMBER($D11),$D11>0)),"",IF($AE11,"⚠ Cleared after the promo ends ("&CHOOSE(MONTH($K11),"Jan","Feb","Mar","Apr","May","Jun","Jul","Aug","Sep","Oct","Nov","Dec")&" "&YEAR($K11)&"): back-interest likely, not counted here. Try Smart.",IF($G11="Yes","Behind on payments: deal with this first",IF(AND($M11="Yes",N(+$K11)>Plan!$C$6),"Deferred interest: clear by "&CHOOSE(MONTH($K11),"Jan","Feb","Mar","Apr","May","Jun","Jul","Aug","Sep","Oct","Nov","Dec")&" "&YEAR($K11)&" or back-interest is added",IF($U11>Plan!$C$6,$Q11,CHOOSE(Plan!$K$5,IF(Plan!$K$7,"Frees up monthly money fastest","Highest APR among the rest"),"APR "&TEXT(N(+$E11),"0.0%"),"Balance "&TEXT($D11,"#,##0"),"Frees "&TEXT(N(+$F11),"#,##0")&"/month when cleared")))))) | W11: =IF(AND(ISNUMBER($D11),$D11>0),1000-N(+$E11)*100+ROW()/1000000,"") | X11: =IF(AND(ISNUMBER($D11),$D11>0),$D11+ROW()/1000000,"") | Y11: =IF(AND(ISNUMBER($D11),$D11>0),1000-IF(N(+$F11)>0,N(+$F11)/$D11,0)*100+ROW()/1000000,"") | Z11: =IF(AND(ISNUMBER($D11),$D11>0),IF($G11="Yes",0,IF(AND($M11="Yes",N(+$K11)>Plan!$C$6),1,2))*1000000+IF(IF($G11="Yes",0,IF(AND($M11="Yes",N(+$K11)>Plan!$C$6),1,2))=0,1000-IF(N(+$F11)>0,N(+$F11)/$D11,0)*100+ROW()/1000000,IF(IF($G11="Yes",0,IF(AND($M11="Yes",N(+$K11)>Plan!$C$6),1,2))=1,N(+$K11)/100,IF(Plan!$K$7,1000-IF(N(+$F11)>0,N(+$F11)/$D11,0)*100+ROW()/1000000,1000-N(+$E11)*100+ROW()/1000000))),"") | AA11: =IF(Z11="","",COUNTIF(Z$7:Z$18,"<"&Z11)+1) | AB11: =IF(W11="","",COUNTIF(W$7:W$18,"<"&W11)+1) | AC11: =IF(X11="","",COUNTIF(X$7:X$18,"<"&X11)+1) | AD11: =IF(Y11="","",COUNTIF(Y$7:Y$18,"<"&Y11)+1) | AE11: =AND(AND(ISNUMBER($D11),$D11>0),$M11="Yes",N(+$K11)>0,ISNUMBER($T11),N(+$T11)>=N(+$K11))
O12: =IF(AND(ISNUMBER($D12),$D12>0),$D12*N(+$E12)/12,"") | P12: =IF(NOT(AND(ISNUMBER($D12),$D12>0)),"",IF(N(+$F12)<=0,"No minimum",IF(N(+$F12)<=$D12*N(+$E12)/12,"Never at minimum",IF(N(+$E12)=0,0,N(+$F12)*NPER(N(+$E12)/12,-N(+$F12),$D12)-$D12)))) | Q12: =IF(NOT(AND(ISNUMBER($D12),$D12>0)),"",IF(AND(N(+$F12)>0,N(+$F12)<=$D12*N(+$E12)/12),"Minimum doesn't cover interest: pay more here",IF(N(+$F12)<=0,"Add the minimum payment",IF($H12="Not sure - ask lender","Ask your lender before paying extra",IF($H12="Locked until a date",IF(N(+$J12)=0,"Locked: add the unlock date","Locked until "&CHOOSE(MONTH($J12),"Jan","Feb","Mar","Apr","May","Jun","Jul","Aug","Sep","Oct","Nov","Dec")&" "&YEAR($J12)),IF($H12="Allowed with a fee",IF(N(+$I12)=0,"Add the fee amount (blank = no fee)",IF(NOT(ISNUMBER($P12)),"Fee is worth paying: minimums never clear this",IF(N(+$I12)<$P12,"Worth it: saves about "&TEXT($P12-$I12,"#,##0")&" after the fee","Wait: the fee is more than the interest you'd save"&IF(N(+$J12)>0," (until "&CHOOSE(MONTH($J12),"Jan","Feb","Mar","Apr","May","Jun","Jul","Aug","Sep","Oct","Nov","Dec")&" "&YEAR($J12)&")","")))),"OK to pay early")))))) | R12: =IF($U12="","",IF($U12<=Plan!$C$6,"Now",IF($U12>=DATE(2199,12,1),"Not yet",CHOOSE(MONTH($U12),"Jan","Feb","Mar","Apr","May","Jun","Jul","Aug","Sep","Oct","Nov","Dec")&" "&YEAR($U12)))) | S12: =IF(AND(ISNUMBER($D12),$D12>0),CHOOSE(Plan!$K$5,AA12,AB12,AC12,AD12),"") | T12: =IF(AND(ISNUMBER($D12),$D12>0),CHOOSE(Plan!$K$5,'Calc Smart'!H$10,'Calc Avalanche'!H$10,'Calc Snowball'!H$10,'Calc Cashflow'!H$10),"") | U12: =IF(NOT(AND(ISNUMBER($D12),$D12>0)),"",IF($H12="Not sure - ask lender",DATE(2199,12,1),IF($H12="Locked until a date",IF(N(+$J12)=0,DATE(2199,12,1),$J12),IF(AND($H12="Allowed with a fee",N(+$I12)>0,ISNUMBER($P12),N(+$I12)>=N(+$P12)),IF(N(+$J12)=0,DATE(2199,12,1),$J12),DATE(1900,1,1))))) | V12: =IF(NOT(AND(ISNUMBER($D12),$D12>0)),"",IF($AE12,"⚠ Cleared after the promo ends ("&CHOOSE(MONTH($K12),"Jan","Feb","Mar","Apr","May","Jun","Jul","Aug","Sep","Oct","Nov","Dec")&" "&YEAR($K12)&"): back-interest likely, not counted here. Try Smart.",IF($G12="Yes","Behind on payments: deal with this first",IF(AND($M12="Yes",N(+$K12)>Plan!$C$6),"Deferred interest: clear by "&CHOOSE(MONTH($K12),"Jan","Feb","Mar","Apr","May","Jun","Jul","Aug","Sep","Oct","Nov","Dec")&" "&YEAR($K12)&" or back-interest is added",IF($U12>Plan!$C$6,$Q12,CHOOSE(Plan!$K$5,IF(Plan!$K$7,"Frees up monthly money fastest","Highest APR among the rest"),"APR "&TEXT(N(+$E12),"0.0%"),"Balance "&TEXT($D12,"#,##0"),"Frees "&TEXT(N(+$F12),"#,##0")&"/month when cleared")))))) | W12: =IF(AND(ISNUMBER($D12),$D12>0),1000-N(+$E12)*100+ROW()/1000000,"") | X12: =IF(AND(ISNUMBER($D12),$D12>0),$D12+ROW()/1000000,"") | Y12: =IF(AND(ISNUMBER($D12),$D12>0),1000-IF(N(+$F12)>0,N(+$F12)/$D12,0)*100+ROW()/1000000,"") | Z12: =IF(AND(ISNUMBER($D12),$D12>0),IF($G12="Yes",0,IF(AND($M12="Yes",N(+$K12)>Plan!$C$6),1,2))*1000000+IF(IF($G12="Yes",0,IF(AND($M12="Yes",N(+$K12)>Plan!$C$6),1,2))=0,1000-IF(N(+$F12)>0,N(+$F12)/$D12,0)*100+ROW()/1000000,IF(IF($G12="Yes",0,IF(AND($M12="Yes",N(+$K12)>Plan!$C$6),1,2))=1,N(+$K12)/100,IF(Plan!$K$7,1000-IF(N(+$F12)>0,N(+$F12)/$D12,0)*100+ROW()/1000000,1000-N(+$E12)*100+ROW()/1000000))),"") | AA12: =IF(Z12="","",COUNTIF(Z$7:Z$18,"<"&Z12)+1) | AB12: =IF(W12="","",COUNTIF(W$7:W$18,"<"&W12)+1) | AC12: =IF(X12="","",COUNTIF(X$7:X$18,"<"&X12)+1) | AD12: =IF(Y12="","",COUNTIF(Y$7:Y$18,"<"&Y12)+1) | AE12: =AND(AND(ISNUMBER($D12),$D12>0),$M12="Yes",N(+$K12)>0,ISNUMBER($T12),N(+$T12)>=N(+$K12))
O13: =IF(AND(ISNUMBER($D13),$D13>0),$D13*N(+$E13)/12,"") | P13: =IF(NOT(AND(ISNUMBER($D13),$D13>0)),"",IF(N(+$F13)<=0,"No minimum",IF(N(+$F13)<=$D13*N(+$E13)/12,"Never at minimum",IF(N(+$E13)=0,0,N(+$F13)*NPER(N(+$E13)/12,-N(+$F13),$D13)-$D13)))) | Q13: =IF(NOT(AND(ISNUMBER($D13),$D13>0)),"",IF(AND(N(+$F13)>0,N(+$F13)<=$D13*N(+$E13)/12),"Minimum doesn't cover interest: pay more here",IF(N(+$F13)<=0,"Add the minimum payment",IF($H13="Not sure - ask lender","Ask your lender before paying extra",IF($H13="Locked until a date",IF(N(+$J13)=0,"Locked: add the unlock date","Locked until "&CHOOSE(MONTH($J13),"Jan","Feb","Mar","Apr","May","Jun","Jul","Aug","Sep","Oct","Nov","Dec")&" "&YEAR($J13)),IF($H13="Allowed with a fee",IF(N(+$I13)=0,"Add the fee amount (blank = no fee)",IF(NOT(ISNUMBER($P13)),"Fee is worth paying: minimums never clear this",IF(N(+$I13)<$P13,"Worth it: saves about "&TEXT($P13-$I13,"#,##0")&" after the fee","Wait: the fee is more than the interest you'd save"&IF(N(+$J13)>0," (until "&CHOOSE(MONTH($J13),"Jan","Feb","Mar","Apr","May","Jun","Jul","Aug","Sep","Oct","Nov","Dec")&" "&YEAR($J13)&")","")))),"OK to pay early")))))) | R13: =IF($U13="","",IF($U13<=Plan!$C$6,"Now",IF($U13>=DATE(2199,12,1),"Not yet",CHOOSE(MONTH($U13),"Jan","Feb","Mar","Apr","May","Jun","Jul","Aug","Sep","Oct","Nov","Dec")&" "&YEAR($U13)))) | S13: =IF(AND(ISNUMBER($D13),$D13>0),CHOOSE(Plan!$K$5,AA13,AB13,AC13,AD13),"") | T13: =IF(AND(ISNUMBER($D13),$D13>0),CHOOSE(Plan!$K$5,'Calc Smart'!I$10,'Calc Avalanche'!I$10,'Calc Snowball'!I$10,'Calc Cashflow'!I$10),"") | U13: =IF(NOT(AND(ISNUMBER($D13),$D13>0)),"",IF($H13="Not sure - ask lender",DATE(2199,12,1),IF($H13="Locked until a date",IF(N(+$J13)=0,DATE(2199,12,1),$J13),IF(AND($H13="Allowed with a fee",N(+$I13)>0,ISNUMBER($P13),N(+$I13)>=N(+$P13)),IF(N(+$J13)=0,DATE(2199,12,1),$J13),DATE(1900,1,1))))) | V13: =IF(NOT(AND(ISNUMBER($D13),$D13>0)),"",IF($AE13,"⚠ Cleared after the promo ends ("&CHOOSE(MONTH($K13),"Jan","Feb","Mar","Apr","May","Jun","Jul","Aug","Sep","Oct","Nov","Dec")&" "&YEAR($K13)&"): back-interest likely, not counted here. Try Smart.",IF($G13="Yes","Behind on payments: deal with this first",IF(AND($M13="Yes",N(+$K13)>Plan!$C$6),"Deferred interest: clear by "&CHOOSE(MONTH($K13),"Jan","Feb","Mar","Apr","May","Jun","Jul","Aug","Sep","Oct","Nov","Dec")&" "&YEAR($K13)&" or back-interest is added",IF($U13>Plan!$C$6,$Q13,CHOOSE(Plan!$K$5,IF(Plan!$K$7,"Frees up monthly money fastest","Highest APR among the rest"),"APR "&TEXT(N(+$E13),"0.0%"),"Balance "&TEXT($D13,"#,##0"),"Frees "&TEXT(N(+$F13),"#,##0")&"/month when cleared")))))) | W13: =IF(AND(ISNUMBER($D13),$D13>0),1000-N(+$E13)*100+ROW()/1000000,"") | X13: =IF(AND(ISNUMBER($D13),$D13>0),$D13+ROW()/1000000,"") | Y13: =IF(AND(ISNUMBER($D13),$D13>0),1000-IF(N(+$F13)>0,N(+$F13)/$D13,0)*100+ROW()/1000000,"") | Z13: =IF(AND(ISNUMBER($D13),$D13>0),IF($G13="Yes",0,IF(AND($M13="Yes",N(+$K13)>Plan!$C$6),1,2))*1000000+IF(IF($G13="Yes",0,IF(AND($M13="Yes",N(+$K13)>Plan!$C$6),1,2))=0,1000-IF(N(+$F13)>0,N(+$F13)/$D13,0)*100+ROW()/1000000,IF(IF($G13="Yes",0,IF(AND($M13="Yes",N(+$K13)>Plan!$C$6),1,2))=1,N(+$K13)/100,IF(Plan!$K$7,1000-IF(N(+$F13)>0,N(+$F13)/$D13,0)*100+ROW()/1000000,1000-N(+$E13)*100+ROW()/1000000))),"") | AA13: =IF(Z13="","",COUNTIF(Z$7:Z$18,"<"&Z13)+1) | AB13: =IF(W13="","",COUNTIF(W$7:W$18,"<"&W13)+1) | AC13: =IF(X13="","",COUNTIF(X$7:X$18,"<"&X13)+1) | AD13: =IF(Y13="","",COUNTIF(Y$7:Y$18,"<"&Y13)+1) | AE13: =AND(AND(ISNUMBER($D13),$D13>0),$M13="Yes",N(+$K13)>0,ISNUMBER($T13),N(+$T13)>=N(+$K13))
O14: =IF(AND(ISNUMBER($D14),$D14>0),$D14*N(+$E14)/12,"") | P14: =IF(NOT(AND(ISNUMBER($D14),$D14>0)),"",IF(N(+$F14)<=0,"No minimum",IF(N(+$F14)<=$D14*N(+$E14)/12,"Never at minimum",IF(N(+$E14)=0,0,N(+$F14)*NPER(N(+$E14)/12,-N(+$F14),$D14)-$D14)))) | Q14: =IF(NOT(AND(ISNUMBER($D14),$D14>0)),"",IF(AND(N(+$F14)>0,N(+$F14)<=$D14*N(+$E14)/12),"Minimum doesn't cover interest: pay more here",IF(N(+$F14)<=0,"Add the minimum payment",IF($H14="Not sure - ask lender","Ask your lender before paying extra",IF($H14="Locked until a date",IF(N(+$J14)=0,"Locked: add the unlock date","Locked until "&CHOOSE(MONTH($J14),"Jan","Feb","Mar","Apr","May","Jun","Jul","Aug","Sep","Oct","Nov","Dec")&" "&YEAR($J14)),IF($H14="Allowed with a fee",IF(N(+$I14)=0,"Add the fee amount (blank = no fee)",IF(NOT(ISNUMBER($P14)),"Fee is worth paying: minimums never clear this",IF(N(+$I14)<$P14,"Worth it: saves about "&TEXT($P14-$I14,"#,##0")&" after the fee","Wait: the fee is more than the interest you'd save"&IF(N(+$J14)>0," (until "&CHOOSE(MONTH($J14),"Jan","Feb","Mar","Apr","May","Jun","Jul","Aug","Sep","Oct","Nov","Dec")&" "&YEAR($J14)&")","")))),"OK to pay early")))))) | R14: =IF($U14="","",IF($U14<=Plan!$C$6,"Now",IF($U14>=DATE(2199,12,1),"Not yet",CHOOSE(MONTH($U14),"Jan","Feb","Mar","Apr","May","Jun","Jul","Aug","Sep","Oct","Nov","Dec")&" "&YEAR($U14)))) | S14: =IF(AND(ISNUMBER($D14),$D14>0),CHOOSE(Plan!$K$5,AA14,AB14,AC14,AD14),"") | T14: =IF(AND(ISNUMBER($D14),$D14>0),CHOOSE(Plan!$K$5,'Calc Smart'!J$10,'Calc Avalanche'!J$10,'Calc Snowball'!J$10,'Calc Cashflow'!J$10),"") | U14: =IF(NOT(AND(ISNUMBER($D14),$D14>0)),"",IF($H14="Not sure - ask lender",DATE(2199,12,1),IF($H14="Locked until a date",IF(N(+$J14)=0,DATE(2199,12,1),$J14),IF(AND($H14="Allowed with a fee",N(+$I14)>0,ISNUMBER($P14),N(+$I14)>=N(+$P14)),IF(N(+$J14)=0,DATE(2199,12,1),$J14),DATE(1900,1,1))))) | V14: =IF(NOT(AND(ISNUMBER($D14),$D14>0)),"",IF($AE14,"⚠ Cleared after the promo ends ("&CHOOSE(MONTH($K14),"Jan","Feb","Mar","Apr","May","Jun","Jul","Aug","Sep","Oct","Nov","Dec")&" "&YEAR($K14)&"): back-interest likely, not counted here. Try Smart.",IF($G14="Yes","Behind on payments: deal with this first",IF(AND($M14="Yes",N(+$K14)>Plan!$C$6),"Deferred interest: clear by "&CHOOSE(MONTH($K14),"Jan","Feb","Mar","Apr","May","Jun","Jul","Aug","Sep","Oct","Nov","Dec")&" "&YEAR($K14)&" or back-interest is added",IF($U14>Plan!$C$6,$Q14,CHOOSE(Plan!$K$5,IF(Plan!$K$7,"Frees up monthly money fastest","Highest APR among the rest"),"APR "&TEXT(N(+$E14),"0.0%"),"Balance "&TEXT($D14,"#,##0"),"Frees "&TEXT(N(+$F14),"#,##0")&"/month when cleared")))))) | W14: =IF(AND(ISNUMBER($D14),$D14>0),1000-N(+$E14)*100+ROW()/1000000,"") | X14: =IF(AND(ISNUMBER($D14),$D14>0),$D14+ROW()/1000000,"") | Y14: =IF(AND(ISNUMBER($D14),$D14>0),1000-IF(N(+$F14)>0,N(+$F14)/$D14,0)*100+ROW()/1000000,"") | Z14: =IF(AND(ISNUMBER($D14),$D14>0),IF($G14="Yes",0,IF(AND($M14="Yes",N(+$K14)>Plan!$C$6),1,2))*1000000+IF(IF($G14="Yes",0,IF(AND($M14="Yes",N(+$K14)>Plan!$C$6),1,2))=0,1000-IF(N(+$F14)>0,N(+$F14)/$D14,0)*100+ROW()/1000000,IF(IF($G14="Yes",0,IF(AND($M14="Yes",N(+$K14)>Plan!$C$6),1,2))=1,N(+$K14)/100,IF(Plan!$K$7,1000-IF(N(+$F14)>0,N(+$F14)/$D14,0)*100+ROW()/1000000,1000-N(+$E14)*100+ROW()/1000000))),"") | AA14: =IF(Z14="","",COUNTIF(Z$7:Z$18,"<"&Z14)+1) | AB14: =IF(W14="","",COUNTIF(W$7:W$18,"<"&W14)+1) | AC14: =IF(X14="","",COUNTIF(X$7:X$18,"<"&X14)+1) | AD14: =IF(Y14="","",COUNTIF(Y$7:Y$18,"<"&Y14)+1) | AE14: =AND(AND(ISNUMBER($D14),$D14>0),$M14="Yes",N(+$K14)>0,ISNUMBER($T14),N(+$T14)>=N(+$K14))
O15: =IF(AND(ISNUMBER($D15),$D15>0),$D15*N(+$E15)/12,"") | P15: =IF(NOT(AND(ISNUMBER($D15),$D15>0)),"",IF(N(+$F15)<=0,"No minimum",IF(N(+$F15)<=$D15*N(+$E15)/12,"Never at minimum",IF(N(+$E15)=0,0,N(+$F15)*NPER(N(+$E15)/12,-N(+$F15),$D15)-$D15)))) | Q15: =IF(NOT(AND(ISNUMBER($D15),$D15>0)),"",IF(AND(N(+$F15)>0,N(+$F15)<=$D15*N(+$E15)/12),"Minimum doesn't cover interest: pay more here",IF(N(+$F15)<=0,"Add the minimum payment",IF($H15="Not sure - ask lender","Ask your lender before paying extra",IF($H15="Locked until a date",IF(N(+$J15)=0,"Locked: add the unlock date","Locked until "&CHOOSE(MONTH($J15),"Jan","Feb","Mar","Apr","May","Jun","Jul","Aug","Sep","Oct","Nov","Dec")&" "&YEAR($J15)),IF($H15="Allowed with a fee",IF(N(+$I15)=0,"Add the fee amount (blank = no fee)",IF(NOT(ISNUMBER($P15)),"Fee is worth paying: minimums never clear this",IF(N(+$I15)<$P15,"Worth it: saves about "&TEXT($P15-$I15,"#,##0")&" after the fee","Wait: the fee is more than the interest you'd save"&IF(N(+$J15)>0," (until "&CHOOSE(MONTH($J15),"Jan","Feb","Mar","Apr","May","Jun","Jul","Aug","Sep","Oct","Nov","Dec")&" "&YEAR($J15)&")","")))),"OK to pay early")))))) | R15: =IF($U15="","",IF($U15<=Plan!$C$6,"Now",IF($U15>=DATE(2199,12,1),"Not yet",CHOOSE(MONTH($U15),"Jan","Feb","Mar","Apr","May","Jun","Jul","Aug","Sep","Oct","Nov","Dec")&" "&YEAR($U15)))) | S15: =IF(AND(ISNUMBER($D15),$D15>0),CHOOSE(Plan!$K$5,AA15,AB15,AC15,AD15),"") | T15: =IF(AND(ISNUMBER($D15),$D15>0),CHOOSE(Plan!$K$5,'Calc Smart'!K$10,'Calc Avalanche'!K$10,'Calc Snowball'!K$10,'Calc Cashflow'!K$10),"") | U15: =IF(NOT(AND(ISNUMBER($D15),$D15>0)),"",IF($H15="Not sure - ask lender",DATE(2199,12,1),IF($H15="Locked until a date",IF(N(+$J15)=0,DATE(2199,12,1),$J15),IF(AND($H15="Allowed with a fee",N(+$I15)>0,ISNUMBER($P15),N(+$I15)>=N(+$P15)),IF(N(+$J15)=0,DATE(2199,12,1),$J15),DATE(1900,1,1))))) | V15: =IF(NOT(AND(ISNUMBER($D15),$D15>0)),"",IF($AE15,"⚠ Cleared after the promo ends ("&CHOOSE(MONTH($K15),"Jan","Feb","Mar","Apr","May","Jun","Jul","Aug","Sep","Oct","Nov","Dec")&" "&YEAR($K15)&"): back-interest likely, not counted here. Try Smart.",IF($G15="Yes","Behind on payments: deal with this first",IF(AND($M15="Yes",N(+$K15)>Plan!$C$6),"Deferred interest: clear by "&CHOOSE(MONTH($K15),"Jan","Feb","Mar","Apr","May","Jun","Jul","Aug","Sep","Oct","Nov","Dec")&" "&YEAR($K15)&" or back-interest is added",IF($U15>Plan!$C$6,$Q15,CHOOSE(Plan!$K$5,IF(Plan!$K$7,"Frees up monthly money fastest","Highest APR among the rest"),"APR "&TEXT(N(+$E15),"0.0%"),"Balance "&TEXT($D15,"#,##0"),"Frees "&TEXT(N(+$F15),"#,##0")&"/month when cleared")))))) | W15: =IF(AND(ISNUMBER($D15),$D15>0),1000-N(+$E15)*100+ROW()/1000000,"") | X15: =IF(AND(ISNUMBER($D15),$D15>0),$D15+ROW()/1000000,"") | Y15: =IF(AND(ISNUMBER($D15),$D15>0),1000-IF(N(+$F15)>0,N(+$F15)/$D15,0)*100+ROW()/1000000,"") | Z15: =IF(AND(ISNUMBER($D15),$D15>0),IF($G15="Yes",0,IF(AND($M15="Yes",N(+$K15)>Plan!$C$6),1,2))*1000000+IF(IF($G15="Yes",0,IF(AND($M15="Yes",N(+$K15)>Plan!$C$6),1,2))=0,1000-IF(N(+$F15)>0,N(+$F15)/$D15,0)*100+ROW()/1000000,IF(IF($G15="Yes",0,IF(AND($M15="Yes",N(+$K15)>Plan!$C$6),1,2))=1,N(+$K15)/100,IF(Plan!$K$7,1000-IF(N(+$F15)>0,N(+$F15)/$D15,0)*100+ROW()/1000000,1000-N(+$E15)*100+ROW()/1000000))),"") | AA15: =IF(Z15="","",COUNTIF(Z$7:Z$18,"<"&Z15)+1) | AB15: =IF(W15="","",COUNTIF(W$7:W$18,"<"&W15)+1) | AC15: =IF(X15="","",COUNTIF(X$7:X$18,"<"&X15)+1) | AD15: =IF(Y15="","",COUNTIF(Y$7:Y$18,"<"&Y15)+1) | AE15: =AND(AND(ISNUMBER($D15),$D15>0),$M15="Yes",N(+$K15)>0,ISNUMBER($T15),N(+$T15)>=N(+$K15))
O16: =IF(AND(ISNUMBER($D16),$D16>0),$D16*N(+$E16)/12,"") | P16: =IF(NOT(AND(ISNUMBER($D16),$D16>0)),"",IF(N(+$F16)<=0,"No minimum",IF(N(+$F16)<=$D16*N(+$E16)/12,"Never at minimum",IF(N(+$E16)=0,0,N(+$F16)*NPER(N(+$E16)/12,-N(+$F16),$D16)-$D16)))) | Q16: =IF(NOT(AND(ISNUMBER($D16),$D16>0)),"",IF(AND(N(+$F16)>0,N(+$F16)<=$D16*N(+$E16)/12),"Minimum doesn't cover interest: pay more here",IF(N(+$F16)<=0,"Add the minimum payment",IF($H16="Not sure - ask lender","Ask your lender before paying extra",IF($H16="Locked until a date",IF(N(+$J16)=0,"Locked: add the unlock date","Locked until "&CHOOSE(MONTH($J16),"Jan","Feb","Mar","Apr","May","Jun","Jul","Aug","Sep","Oct","Nov","Dec")&" "&YEAR($J16)),IF($H16="Allowed with a fee",IF(N(+$I16)=0,"Add the fee amount (blank = no fee)",IF(NOT(ISNUMBER($P16)),"Fee is worth paying: minimums never clear this",IF(N(+$I16)<$P16,"Worth it: saves about "&TEXT($P16-$I16,"#,##0")&" after the fee","Wait: the fee is more than the interest you'd save"&IF(N(+$J16)>0," (until "&CHOOSE(MONTH($J16),"Jan","Feb","Mar","Apr","May","Jun","Jul","Aug","Sep","Oct","Nov","Dec")&" "&YEAR($J16)&")","")))),"OK to pay early")))))) | R16: =IF($U16="","",IF($U16<=Plan!$C$6,"Now",IF($U16>=DATE(2199,12,1),"Not yet",CHOOSE(MONTH($U16),"Jan","Feb","Mar","Apr","May","Jun","Jul","Aug","Sep","Oct","Nov","Dec")&" "&YEAR($U16)))) | S16: =IF(AND(ISNUMBER($D16),$D16>0),CHOOSE(Plan!$K$5,AA16,AB16,AC16,AD16),"") | T16: =IF(AND(ISNUMBER($D16),$D16>0),CHOOSE(Plan!$K$5,'Calc Smart'!L$10,'Calc Avalanche'!L$10,'Calc Snowball'!L$10,'Calc Cashflow'!L$10),"") | U16: =IF(NOT(AND(ISNUMBER($D16),$D16>0)),"",IF($H16="Not sure - ask lender",DATE(2199,12,1),IF($H16="Locked until a date",IF(N(+$J16)=0,DATE(2199,12,1),$J16),IF(AND($H16="Allowed with a fee",N(+$I16)>0,ISNUMBER($P16),N(+$I16)>=N(+$P16)),IF(N(+$J16)=0,DATE(2199,12,1),$J16),DATE(1900,1,1))))) | V16: =IF(NOT(AND(ISNUMBER($D16),$D16>0)),"",IF($AE16,"⚠ Cleared after the promo ends ("&CHOOSE(MONTH($K16),"Jan","Feb","Mar","Apr","May","Jun","Jul","Aug","Sep","Oct","Nov","Dec")&" "&YEAR($K16)&"): back-interest likely, not counted here. Try Smart.",IF($G16="Yes","Behind on payments: deal with this first",IF(AND($M16="Yes",N(+$K16)>Plan!$C$6),"Deferred interest: clear by "&CHOOSE(MONTH($K16),"Jan","Feb","Mar","Apr","May","Jun","Jul","Aug","Sep","Oct","Nov","Dec")&" "&YEAR($K16)&" or back-interest is added",IF($U16>Plan!$C$6,$Q16,CHOOSE(Plan!$K$5,IF(Plan!$K$7,"Frees up monthly money fastest","Highest APR among the rest"),"APR "&TEXT(N(+$E16),"0.0%"),"Balance "&TEXT($D16,"#,##0"),"Frees "&TEXT(N(+$F16),"#,##0")&"/month when cleared")))))) | W16: =IF(AND(ISNUMBER($D16),$D16>0),1000-N(+$E16)*100+ROW()/1000000,"") | X16: =IF(AND(ISNUMBER($D16),$D16>0),$D16+ROW()/1000000,"") | Y16: =IF(AND(ISNUMBER($D16),$D16>0),1000-IF(N(+$F16)>0,N(+$F16)/$D16,0)*100+ROW()/1000000,"") | Z16: =IF(AND(ISNUMBER($D16),$D16>0),IF($G16="Yes",0,IF(AND($M16="Yes",N(+$K16)>Plan!$C$6),1,2))*1000000+IF(IF($G16="Yes",0,IF(AND($M16="Yes",N(+$K16)>Plan!$C$6),1,2))=0,1000-IF(N(+$F16)>0,N(+$F16)/$D16,0)*100+ROW()/1000000,IF(IF($G16="Yes",0,IF(AND($M16="Yes",N(+$K16)>Plan!$C$6),1,2))=1,N(+$K16)/100,IF(Plan!$K$7,1000-IF(N(+$F16)>0,N(+$F16)/$D16,0)*100+ROW()/1000000,1000-N(+$E16)*100+ROW()/1000000))),"") | AA16: =IF(Z16="","",COUNTIF(Z$7:Z$18,"<"&Z16)+1) | AB16: =IF(W16="","",COUNTIF(W$7:W$18,"<"&W16)+1) | AC16: =IF(X16="","",COUNTIF(X$7:X$18,"<"&X16)+1) | AD16: =IF(Y16="","",COUNTIF(Y$7:Y$18,"<"&Y16)+1) | AE16: =AND(AND(ISNUMBER($D16),$D16>0),$M16="Yes",N(+$K16)>0,ISNUMBER($T16),N(+$T16)>=N(+$K16))
O17: =IF(AND(ISNUMBER($D17),$D17>0),$D17*N(+$E17)/12,"") | P17: =IF(NOT(AND(ISNUMBER($D17),$D17>0)),"",IF(N(+$F17)<=0,"No minimum",IF(N(+$F17)<=$D17*N(+$E17)/12,"Never at minimum",IF(N(+$E17)=0,0,N(+$F17)*NPER(N(+$E17)/12,-N(+$F17),$D17)-$D17)))) | Q17: =IF(NOT(AND(ISNUMBER($D17),$D17>0)),"",IF(AND(N(+$F17)>0,N(+$F17)<=$D17*N(+$E17)/12),"Minimum doesn't cover interest: pay more here",IF(N(+$F17)<=0,"Add the minimum payment",IF($H17="Not sure - ask lender","Ask your lender before paying extra",IF($H17="Locked until a date",IF(N(+$J17)=0,"Locked: add the unlock date","Locked until "&CHOOSE(MONTH($J17),"Jan","Feb","Mar","Apr","May","Jun","Jul","Aug","Sep","Oct","Nov","Dec")&" "&YEAR($J17)),IF($H17="Allowed with a fee",IF(N(+$I17)=0,"Add the fee amount (blank = no fee)",IF(NOT(ISNUMBER($P17)),"Fee is worth paying: minimums never clear this",IF(N(+$I17)<$P17,"Worth it: saves about "&TEXT($P17-$I17,"#,##0")&" after the fee","Wait: the fee is more than the interest you'd save"&IF(N(+$J17)>0," (until "&CHOOSE(MONTH($J17),"Jan","Feb","Mar","Apr","May","Jun","Jul","Aug","Sep","Oct","Nov","Dec")&" "&YEAR($J17)&")","")))),"OK to pay early")))))) | R17: =IF($U17="","",IF($U17<=Plan!$C$6,"Now",IF($U17>=DATE(2199,12,1),"Not yet",CHOOSE(MONTH($U17),"Jan","Feb","Mar","Apr","May","Jun","Jul","Aug","Sep","Oct","Nov","Dec")&" "&YEAR($U17)))) | S17: =IF(AND(ISNUMBER($D17),$D17>0),CHOOSE(Plan!$K$5,AA17,AB17,AC17,AD17),"") | T17: =IF(AND(ISNUMBER($D17),$D17>0),CHOOSE(Plan!$K$5,'Calc Smart'!M$10,'Calc Avalanche'!M$10,'Calc Snowball'!M$10,'Calc Cashflow'!M$10),"") | U17: =IF(NOT(AND(ISNUMBER($D17),$D17>0)),"",IF($H17="Not sure - ask lender",DATE(2199,12,1),IF($H17="Locked until a date",IF(N(+$J17)=0,DATE(2199,12,1),$J17),IF(AND($H17="Allowed with a fee",N(+$I17)>0,ISNUMBER($P17),N(+$I17)>=N(+$P17)),IF(N(+$J17)=0,DATE(2199,12,1),$J17),DATE(1900,1,1))))) | V17: =IF(NOT(AND(ISNUMBER($D17),$D17>0)),"",IF($AE17,"⚠ Cleared after the promo ends ("&CHOOSE(MONTH($K17),"Jan","Feb","Mar","Apr","May","Jun","Jul","Aug","Sep","Oct","Nov","Dec")&" "&YEAR($K17)&"): back-interest likely, not counted here. Try Smart.",IF($G17="Yes","Behind on payments: deal with this first",IF(AND($M17="Yes",N(+$K17)>Plan!$C$6),"Deferred interest: clear by "&CHOOSE(MONTH($K17),"Jan","Feb","Mar","Apr","May","Jun","Jul","Aug","Sep","Oct","Nov","Dec")&" "&YEAR($K17)&" or back-interest is added",IF($U17>Plan!$C$6,$Q17,CHOOSE(Plan!$K$5,IF(Plan!$K$7,"Frees up monthly money fastest","Highest APR among the rest"),"APR "&TEXT(N(+$E17),"0.0%"),"Balance "&TEXT($D17,"#,##0"),"Frees "&TEXT(N(+$F17),"#,##0")&"/month when cleared")))))) | W17: =IF(AND(ISNUMBER($D17),$D17>0),1000-N(+$E17)*100+ROW()/1000000,"") | X17: =IF(AND(ISNUMBER($D17),$D17>0),$D17+ROW()/1000000,"") | Y17: =IF(AND(ISNUMBER($D17),$D17>0),1000-IF(N(+$F17)>0,N(+$F17)/$D17,0)*100+ROW()/1000000,"") | Z17: =IF(AND(ISNUMBER($D17),$D17>0),IF($G17="Yes",0,IF(AND($M17="Yes",N(+$K17)>Plan!$C$6),1,2))*1000000+IF(IF($G17="Yes",0,IF(AND($M17="Yes",N(+$K17)>Plan!$C$6),1,2))=0,1000-IF(N(+$F17)>0,N(+$F17)/$D17,0)*100+ROW()/1000000,IF(IF($G17="Yes",0,IF(AND($M17="Yes",N(+$K17)>Plan!$C$6),1,2))=1,N(+$K17)/100,IF(Plan!$K$7,1000-IF(N(+$F17)>0,N(+$F17)/$D17,0)*100+ROW()/1000000,1000-N(+$E17)*100+ROW()/1000000))),"") | AA17: =IF(Z17="","",COUNTIF(Z$7:Z$18,"<"&Z17)+1) | AB17: =IF(W17="","",COUNTIF(W$7:W$18,"<"&W17)+1) | AC17: =IF(X17="","",COUNTIF(X$7:X$18,"<"&X17)+1) | AD17: =IF(Y17="","",COUNTIF(Y$7:Y$18,"<"&Y17)+1) | AE17: =AND(AND(ISNUMBER($D17),$D17>0),$M17="Yes",N(+$K17)>0,ISNUMBER($T17),N(+$T17)>=N(+$K17))
O18: =IF(AND(ISNUMBER($D18),$D18>0),$D18*N(+$E18)/12,"") | P18: =IF(NOT(AND(ISNUMBER($D18),$D18>0)),"",IF(N(+$F18)<=0,"No minimum",IF(N(+$F18)<=$D18*N(+$E18)/12,"Never at minimum",IF(N(+$E18)=0,0,N(+$F18)*NPER(N(+$E18)/12,-N(+$F18),$D18)-$D18)))) | Q18: =IF(NOT(AND(ISNUMBER($D18),$D18>0)),"",IF(AND(N(+$F18)>0,N(+$F18)<=$D18*N(+$E18)/12),"Minimum doesn't cover interest: pay more here",IF(N(+$F18)<=0,"Add the minimum payment",IF($H18="Not sure - ask lender","Ask your lender before paying extra",IF($H18="Locked until a date",IF(N(+$J18)=0,"Locked: add the unlock date","Locked until "&CHOOSE(MONTH($J18),"Jan","Feb","Mar","Apr","May","Jun","Jul","Aug","Sep","Oct","Nov","Dec")&" "&YEAR($J18)),IF($H18="Allowed with a fee",IF(N(+$I18)=0,"Add the fee amount (blank = no fee)",IF(NOT(ISNUMBER($P18)),"Fee is worth paying: minimums never clear this",IF(N(+$I18)<$P18,"Worth it: saves about "&TEXT($P18-$I18,"#,##0")&" after the fee","Wait: the fee is more than the interest you'd save"&IF(N(+$J18)>0," (until "&CHOOSE(MONTH($J18),"Jan","Feb","Mar","Apr","May","Jun","Jul","Aug","Sep","Oct","Nov","Dec")&" "&YEAR($J18)&")","")))),"OK to pay early")))))) | R18: =IF($U18="","",IF($U18<=Plan!$C$6,"Now",IF($U18>=DATE(2199,12,1),"Not yet",CHOOSE(MONTH($U18),"Jan","Feb","Mar","Apr","May","Jun","Jul","Aug","Sep","Oct","Nov","Dec")&" "&YEAR($U18)))) | S18: =IF(AND(ISNUMBER($D18),$D18>0),CHOOSE(Plan!$K$5,AA18,AB18,AC18,AD18),"") | T18: =IF(AND(ISNUMBER($D18),$D18>0),CHOOSE(Plan!$K$5,'Calc Smart'!N$10,'Calc Avalanche'!N$10,'Calc Snowball'!N$10,'Calc Cashflow'!N$10),"") | U18: =IF(NOT(AND(ISNUMBER($D18),$D18>0)),"",IF($H18="Not sure - ask lender",DATE(2199,12,1),IF($H18="Locked until a date",IF(N(+$J18)=0,DATE(2199,12,1),$J18),IF(AND($H18="Allowed with a fee",N(+$I18)>0,ISNUMBER($P18),N(+$I18)>=N(+$P18)),IF(N(+$J18)=0,DATE(2199,12,1),$J18),DATE(1900,1,1))))) | V18: =IF(NOT(AND(ISNUMBER($D18),$D18>0)),"",IF($AE18,"⚠ Cleared after the promo ends ("&CHOOSE(MONTH($K18),"Jan","Feb","Mar","Apr","May","Jun","Jul","Aug","Sep","Oct","Nov","Dec")&" "&YEAR($K18)&"): back-interest likely, not counted here. Try Smart.",IF($G18="Yes","Behind on payments: deal with this first",IF(AND($M18="Yes",N(+$K18)>Plan!$C$6),"Deferred interest: clear by "&CHOOSE(MONTH($K18),"Jan","Feb","Mar","Apr","May","Jun","Jul","Aug","Sep","Oct","Nov","Dec")&" "&YEAR($K18)&" or back-interest is added",IF($U18>Plan!$C$6,$Q18,CHOOSE(Plan!$K$5,IF(Plan!$K$7,"Frees up monthly money fastest","Highest APR among the rest"),"APR "&TEXT(N(+$E18),"0.0%"),"Balance "&TEXT($D18,"#,##0"),"Frees "&TEXT(N(+$F18),"#,##0")&"/month when cleared")))))) | W18: =IF(AND(ISNUMBER($D18),$D18>0),1000-N(+$E18)*100+ROW()/1000000,"") | X18: =IF(AND(ISNUMBER($D18),$D18>0),$D18+ROW()/1000000,"") | Y18: =IF(AND(ISNUMBER($D18),$D18>0),1000-IF(N(+$F18)>0,N(+$F18)/$D18,0)*100+ROW()/1000000,"") | Z18: =IF(AND(ISNUMBER($D18),$D18>0),IF($G18="Yes",0,IF(AND($M18="Yes",N(+$K18)>Plan!$C$6),1,2))*1000000+IF(IF($G18="Yes",0,IF(AND($M18="Yes",N(+$K18)>Plan!$C$6),1,2))=0,1000-IF(N(+$F18)>0,N(+$F18)/$D18,0)*100+ROW()/1000000,IF(IF($G18="Yes",0,IF(AND($M18="Yes",N(+$K18)>Plan!$C$6),1,2))=1,N(+$K18)/100,IF(Plan!$K$7,1000-IF(N(+$F18)>0,N(+$F18)/$D18,0)*100+ROW()/1000000,1000-N(+$E18)*100+ROW()/1000000))),"") | AA18: =IF(Z18="","",COUNTIF(Z$7:Z$18,"<"&Z18)+1) | AB18: =IF(W18="","",COUNTIF(W$7:W$18,"<"&W18)+1) | AC18: =IF(X18="","",COUNTIF(X$7:X$18,"<"&X18)+1) | AD18: =IF(Y18="","",COUNTIF(Y$7:Y$18,"<"&Y18)+1) | AE18: =AND(AND(ISNUMBER($D18),$D18>0),$M18="Yes",N(+$K18)>0,ISNUMBER($T18),N(+$T18)>=N(+$K18))
B20: Rows marked (sample) are made up: overwrite or clear them. Up to 12 debts.

Sheet Schedule
B2: Month by month
B3: Your chosen order. Each column is one debt's balance at the end of the month.
F4: =IF('My Debts'!$B$7="","",'My Debts'!$B$7) | G4: =IF('My Debts'!$B$8="","",'My Debts'!$B$8) | H4: =IF('My Debts'!$B$9="","",'My Debts'!$B$9) | I4: =IF('My Debts'!$B$10="","",'My Debts'!$B$10) | J4: =IF('My Debts'!$B$11="","",'My Debts'!$B$11) | K4: =IF('My Debts'!$B$12="","",'My Debts'!$B$12) | L4: =IF('My Debts'!$B$13="","",'My Debts'!$B$13) | M4: =IF('My Debts'!$B$14="","",'My Debts'!$B$14) | N4: =IF('My Debts'!$B$15="","",'My Debts'!$B$15) | O4: =IF('My Debts'!$B$16="","",'My Debts'!$B$16) | P4: =IF('My Debts'!$B$17="","",'My Debts'!$B$17) | Q4: =IF('My Debts'!$B$18="","",'My Debts'!$B$18)
B5: MONTH | C5: PAID THIS MONTH | D5: TOTAL LEFT | E5: DEBTS LEFT | F5: DEBT 1 | G5: DEBT 2 | H5: DEBT 3 | I5: DEBT 4 | J5: DEBT 5 | K5: DEBT 6 | L5: DEBT 7 | M5: DEBT 8 | N5: DEBT 9 | O5: DEBT 10 | P5: DEBT 11 | Q5: DEBT 12
B6: =EDATE(Plan!$C$6,0) | C6: =CHOOSE(Plan!$K$5,'Calc Smart'!AE12,'Calc Avalanche'!AE12,'Calc Snowball'!AE12,'Calc Cashflow'!AE12) | D6: =CHOOSE(Plan!$K$5,'Calc Smart'!AD12,'Calc Avalanche'!AD12,'Calc Snowball'!AD12,'Calc Cashflow'!AD12) | E6: =CHOOSE(Plan!$K$5,COUNTIF('Calc Smart'!C12:N12,">0"),COUNTIF('Calc Avalanche'!C12:N12,">0"),COUNTIF('Calc Snowball'!C12:N12,">0"),COUNTIF('Calc Cashflow'!C12:N12,">0")) | F6: =CHOOSE(Plan!$K$5,'Calc Smart'!C12,'Calc Avalanche'!C12,'Calc Snowball'!C12,'Calc Cashflow'!C12) | G6: =CHOOSE(Plan!$K$5,'Calc Smart'!D12,'Calc Avalanche'!D12,'Calc Snowball'!D12,'Calc Cashflow'!D12) | H6: =CHOOSE(Plan!$K$5,'Calc Smart'!E12,'Calc Avalanche'!E12,'Calc Snowball'!E12,'Calc Cashflow'!E12) | I6: =CHOOSE(Plan!$K$5,'Calc Smart'!F12,'Calc Avalanche'!F12,'Calc Snowball'!F12,'Calc Cashflow'!F12) | J6: =CHOOSE(Plan!$K$5,'Calc Smart'!G12,'Calc Avalanche'!G12,'Calc Snowball'!G12,'Calc Cashflow'!G12) | K6: =CHOOSE(Plan!$K$5,'Calc Smart'!H12,'Calc Avalanche'!H12,'Calc Snowball'!H12,'Calc Cashflow'!H12) | L6: =CHOOSE(Plan!$K$5,'Calc Smart'!I12,'Calc Avalanche'!I12,'Calc Snowball'!I12,'Calc Cashflow'!I12) | M6: =CHOOSE(Plan!$K$5,'Calc Smart'!J12,'Calc Avalanche'!J12,'Calc Snowball'!J12,'Calc Cashflow'!J12) | ... Q6: =CHOOSE(Plan!$K$5,'Calc Smart'!N12,'Calc Avalanche'!N12,'Calc Snowball'!N12,'Calc Cashflow'!N12)
B7: =EDATE(Plan!$C$6,1) | C7: =CHOOSE(Plan!$K$5,'Calc Smart'!AE13,'Calc Avalanche'!AE13,'Calc Snowball'!AE13,'Calc Cashflow'!AE13) | D7: =CHOOSE(Plan!$K$5,'Calc Smart'!AD13,'Calc Avalanche'!AD13,'Calc Snowball'!AD13,'Calc Cashflow'!AD13) | E7: =CHOOSE(Plan!$K$5,COUNTIF('Calc Smart'!C13:N13,">0"),COUNTIF('Calc Avalanche'!C13:N13,">0"),COUNTIF('Calc Snowball'!C13:N13,">0"),COUNTIF('Calc Cashflow'!C13:N13,">0")) | F7: =CHOOSE(Plan!$K$5,'Calc Smart'!C13,'Calc Avalanche'!C13,'Calc Snowball'!C13,'Calc Cashflow'!C13) | G7: =CHOOSE(Plan!$K$5,'Calc Smart'!D13,'Calc Avalanche'!D13,'Calc Snowball'!D13,'Calc Cashflow'!D13) | H7: =CHOOSE(Plan!$K$5,'Calc Smart'!E13,'Calc Avalanche'!E13,'Calc Snowball'!E13,'Calc Cashflow'!E13) | I7: =CHOOSE(Plan!$K$5,'Calc Smart'!F13,'Calc Avalanche'!F13,'Calc Snowball'!F13,'Calc Cashflow'!F13) | J7: =CHOOSE(Plan!$K$5,'Calc Smart'!G13,'Calc Avalanche'!G13,'Calc Snowball'!G13,'Calc Cashflow'!G13) | K7: =CHOOSE(Plan!$K$5,'Calc Smart'!H13,'Calc Avalanche'!H13,'Calc Snowball'!H13,'Calc Cashflow'!H13) | L7: =CHOOSE(Plan!$K$5,'Calc Smart'!I13,'Calc Avalanche'!I13,'Calc Snowball'!I13,'Calc Cashflow'!I13) | M7: =CHOOSE(Plan!$K$5,'Calc Smart'!J13,'Calc Avalanche'!J13,'Calc Snowball'!J13,'Calc Cashflow'!J13) | ... Q7: =CHOOSE(Plan!$K$5,'Calc Smart'!N13,'Calc Avalanche'!N13,'Calc Snowball'!N13,'Calc Cashflow'!N13)
B8: =EDATE(Plan!$C$6,2) | C8: =CHOOSE(Plan!$K$5,'Calc Smart'!AE14,'Calc Avalanche'!AE14,'Calc Snowball'!AE14,'Calc Cashflow'!AE14) | D8: =CHOOSE(Plan!$K$5,'Calc Smart'!AD14,'Calc Avalanche'!AD14,'Calc Snowball'!AD14,'Calc Cashflow'!AD14) | E8: =CHOOSE(Plan!$K$5,COUNTIF('Calc Smart'!C14:N14,">0"),COUNTIF('Calc Avalanche'!C14:N14,">0"),COUNTIF('Calc Snowball'!C14:N14,">0"),COUNTIF('Calc Cashflow'!C14:N14,">0")) | F8: =CHOOSE(Plan!$K$5,'Calc Smart'!C14,'Calc Avalanche'!C14,'Calc Snowball'!C14,'Calc Cashflow'!C14) | G8: =CHOOSE(Plan!$K$5,'Calc Smart'!D14,'Calc Avalanche'!D14,'Calc Snowball'!D14,'Calc Cashflow'!D14) | H8: =CHOOSE(Plan!$K$5,'Calc Smart'!E14,'Calc Avalanche'!E14,'Calc Snowball'!E14,'Calc Cashflow'!E14) | I8: =CHOOSE(Plan!$K$5,'Calc Smart'!F14,'Calc Avalanche'!F14,'Calc Snowball'!F14,'Calc Cashflow'!F14) | J8: =CHOOSE(Plan!$K$5,'Calc Smart'!G14,'Calc Avalanche'!G14,'Calc Snowball'!G14,'Calc Cashflow'!G14) | K8: =CHOOSE(Plan!$K$5,'Calc Smart'!H14,'Calc Avalanche'!H14,'Calc Snowball'!H14,'Calc Cashflow'!H14) | L8: =CHOOSE(Plan!$K$5,'Calc Smart'!I14,'Calc Avalanche'!I14,'Calc Snowball'!I14,'Calc Cashflow'!I14) | M8: =CHOOSE(Plan!$K$5,'Calc Smart'!J14,'Calc Avalanche'!J14,'Calc Snowball'!J14,'Calc Cashflow'!J14) | ... Q8: =CHOOSE(Plan!$K$5,'Calc Smart'!N14,'Calc Avalanche'!N14,'Calc Snowball'!N14,'Calc Cashflow'!N14)
B9: =EDATE(Plan!$C$6,3) | C9: =CHOOSE(Plan!$K$5,'Calc Smart'!AE15,'Calc Avalanche'!AE15,'Calc Snowball'!AE15,'Calc Cashflow'!AE15) | D9: =CHOOSE(Plan!$K$5,'Calc Smart'!AD15,'Calc Avalanche'!AD15,'Calc Snowball'!AD15,'Calc Cashflow'!AD15) | E9: =CHOOSE(Plan!$K$5,COUNTIF('Calc Smart'!C15:N15,">0"),COUNTIF('Calc Avalanche'!C15:N15,">0"),COUNTIF('Calc Snowball'!C15:N15,">0"),COUNTIF('Calc Cashflow'!C15:N15,">0")) | F9: =CHOOSE(Plan!$K$5,'Calc Smart'!C15,'Calc Avalanche'!C15,'Calc Snowball'!C15,'Calc Cashflow'!C15) | G9: =CHOOSE(Plan!$K$5,'Calc Smart'!D15,'Calc Avalanche'!D15,'Calc Snowball'!D15,'Calc Cashflow'!D15) | H9: =CHOOSE(Plan!$K$5,'Calc Smart'!E15,'Calc Avalanche'!E15,'Calc Snowball'!E15,'Calc Cashflow'!E15) | I9: =CHOOSE(Plan!$K$5,'Calc Smart'!F15,'Calc Avalanche'!F15,'Calc Snowball'!F15,'Calc Cashflow'!F15) | J9: =CHOOSE(Plan!$K$5,'Calc Smart'!G15,'Calc Avalanche'!G15,'Calc Snowball'!G15,'Calc Cashflow'!G15) | K9: =CHOOSE(Plan!$K$5,'Calc Smart'!H15,'Calc Avalanche'!H15,'Calc Snowball'!H15,'Calc Cashflow'!H15) | L9: =CHOOSE(Plan!$K$5,'Calc Smart'!I15,'Calc Avalanche'!I15,'Calc Snowball'!I15,'Calc Cashflow'!I15) | M9: =CHOOSE(Plan!$K$5,'Calc Smart'!J15,'Calc Avalanche'!J15,'Calc Snowball'!J15,'Calc Cashflow'!J15) | ... Q9: =CHOOSE(Plan!$K$5,'Calc Smart'!N15,'Calc Avalanche'!N15,'Calc Snowball'!N15,'Calc Cashflow'!N15)
B10: =EDATE(Plan!$C$6,4) | C10: =CHOOSE(Plan!$K$5,'Calc Smart'!AE16,'Calc Avalanche'!AE16,'Calc Snowball'!AE16,'Calc Cashflow'!AE16) | D10: =CHOOSE(Plan!$K$5,'Calc Smart'!AD16,'Calc Avalanche'!AD16,'Calc Snowball'!AD16,'Calc Cashflow'!AD16) | E10: =CHOOSE(Plan!$K$5,COUNTIF('Calc Smart'!C16:N16,">0"),COUNTIF('Calc Avalanche'!C16:N16,">0"),COUNTIF('Calc Snowball'!C16:N16,">0"),COUNTIF('Calc Cashflow'!C16:N16,">0")) | F10: =CHOOSE(Plan!$K$5,'Calc Smart'!C16,'Calc Avalanche'!C16,'Calc Snowball'!C16,'Calc Cashflow'!C16) | G10: =CHOOSE(Plan!$K$5,'Calc Smart'!D16,'Calc Avalanche'!D16,'Calc Snowball'!D16,'Calc Cashflow'!D16) | H10: =CHOOSE(Plan!$K$5,'Calc Smart'!E16,'Calc Avalanche'!E16,'Calc Snowball'!E16,'Calc Cashflow'!E16) | I10: =CHOOSE(Plan!$K$5,'Calc Smart'!F16,'Calc Avalanche'!F16,'Calc Snowball'!F16,'Calc Cashflow'!F16) | J10: =CHOOSE(Plan!$K$5,'Calc Smart'!G16,'Calc Avalanche'!G16,'Calc Snowball'!G16,'Calc Cashflow'!G16) | K10: =CHOOSE(Plan!$K$5,'Calc Smart'!H16,'Calc Avalanche'!H16,'Calc Snowball'!H16,'Calc Cashflow'!H16) | L10: =CHOOSE(Plan!$K$5,'Calc Smart'!I16,'Calc Avalanche'!I16,'Calc Snowball'!I16,'Calc Cashflow'!I16) | M10: =CHOOSE(Plan!$K$5,'Calc Smart'!J16,'Calc Avalanche'!J16,'Calc Snowball'!J16,'Calc Cashflow'!J16) | ... Q10: =CHOOSE(Plan!$K$5,'Calc Smart'!N16,'Calc Avalanche'!N16,'Calc Snowball'!N16,'Calc Cashflow'!N16)
B11: =EDATE(Plan!$C$6,5) | C11: =CHOOSE(Plan!$K$5,'Calc Smart'!AE17,'Calc Avalanche'!AE17,'Calc Snowball'!AE17,'Calc Cashflow'!AE17) | D11: =CHOOSE(Plan!$K$5,'Calc Smart'!AD17,'Calc Avalanche'!AD17,'Calc Snowball'!AD17,'Calc Cashflow'!AD17) | E11: =CHOOSE(Plan!$K$5,COUNTIF('Calc Smart'!C17:N17,">0"),COUNTIF('Calc Avalanche'!C17:N17,">0"),COUNTIF('Calc Snowball'!C17:N17,">0"),COUNTIF('Calc Cashflow'!C17:N17,">0")) | F11: =CHOOSE(Plan!$K$5,'Calc Smart'!C17,'Calc Avalanche'!C17,'Calc Snowball'!C17,'Calc Cashflow'!C17) | G11: =CHOOSE(Plan!$K$5,'Calc Smart'!D17,'Calc Avalanche'!D17,'Calc Snowball'!D17,'Calc Cashflow'!D17) | H11: =CHOOSE(Plan!$K$5,'Calc Smart'!E17,'Calc Avalanche'!E17,'Calc Snowball'!E17,'Calc Cashflow'!E17) | I11: =CHOOSE(Plan!$K$5,'Calc Smart'!F17,'Calc Avalanche'!F17,'Calc Snowball'!F17,'Calc Cashflow'!F17) | J11: =CHOOSE(Plan!$K$5,'Calc Smart'!G17,'Calc Avalanche'!G17,'Calc Snowball'!G17,'Calc Cashflow'!G17) | K11: =CHOOSE(Plan!$K$5,'Calc Smart'!H17,'Calc Avalanche'!H17,'Calc Snowball'!H17,'Calc Cashflow'!H17) | L11: =CHOOSE(Plan!$K$5,'Calc Smart'!I17,'Calc Avalanche'!I17,'Calc Snowball'!I17,'Calc Cashflow'!I17) | M11: =CHOOSE(Plan!$K$5,'Calc Smart'!J17,'Calc Avalanche'!J17,'Calc Snowball'!J17,'Calc Cashflow'!J17) | ... Q11: =CHOOSE(Plan!$K$5,'Calc Smart'!N17,'Calc Avalanche'!N17,'Calc Snowball'!N17,'Calc Cashflow'!N17)
B12: =EDATE(Plan!$C$6,6) | C12: =CHOOSE(Plan!$K$5,'Calc Smart'!AE18,'Calc Avalanche'!AE18,'Calc Snowball'!AE18,'Calc Cashflow'!AE18) | D12: =CHOOSE(Plan!$K$5,'Calc Smart'!AD18,'Calc Avalanche'!AD18,'Calc Snowball'!AD18,'Calc Cashflow'!AD18) | E12: =CHOOSE(Plan!$K$5,COUNTIF('Calc Smart'!C18:N18,">0"),COUNTIF('Calc Avalanche'!C18:N18,">0"),COUNTIF('Calc Snowball'!C18:N18,">0"),COUNTIF('Calc Cashflow'!C18:N18,">0")) | F12: =CHOOSE(Plan!$K$5,'Calc Smart'!C18,'Calc Avalanche'!C18,'Calc Snowball'!C18,'Calc Cashflow'!C18) | G12: =CHOOSE(Plan!$K$5,'Calc Smart'!D18,'Calc Avalanche'!D18,'Calc Snowball'!D18,'Calc Cashflow'!D18) | H12: =CHOOSE(Plan!$K$5,'Calc Smart'!E18,'Calc Avalanche'!E18,'Calc Snowball'!E18,'Calc Cashflow'!E18) | I12: =CHOOSE(Plan!$K$5,'Calc Smart'!F18,'Calc Avalanche'!F18,'Calc Snowball'!F18,'Calc Cashflow'!F18) | J12: =CHOOSE(Plan!$K$5,'Calc Smart'!G18,'Calc Avalanche'!G18,'Calc Snowball'!G18,'Calc Cashflow'!G18) | K12: =CHOOSE(Plan!$K$5,'Calc Smart'!H18,'Calc Avalanche'!H18,'Calc Snowball'!H18,'Calc Cashflow'!H18) | L12: =CHOOSE(Plan!$K$5,'Calc Smart'!I18,'Calc Avalanche'!I18,'Calc Snowball'!I18,'Calc Cashflow'!I18) | M12: =CHOOSE(Plan!$K$5,'Calc Smart'!J18,'Calc Avalanche'!J18,'Calc Snowball'!J18,'Calc Cashflow'!J18) | ... Q12: =CHOOSE(Plan!$K$5,'Calc Smart'!N18,'Calc Avalanche'!N18,'Calc Snowball'!N18,'Calc Cashflow'!N18)
B13: =EDATE(Plan!$C$6,7) | C13: =CHOOSE(Plan!$K$5,'Calc Smart'!AE19,'Calc Avalanche'!AE19,'Calc Snowball'!AE19,'Calc Cashflow'!AE19) | D13: =CHOOSE(Plan!$K$5,'Calc Smart'!AD19,'Calc Avalanche'!AD19,'Calc Snowball'!AD19,'Calc Cashflow'!AD19) | E13: =CHOOSE(Plan!$K$5,COUNTIF('Calc Smart'!C19:N19,">0"),COUNTIF('Calc Avalanche'!C19:N19,">0"),COUNTIF('Calc Snowball'!C19:N19,">0"),COUNTIF('Calc Cashflow'!C19:N19,">0")) | F13: =CHOOSE(Plan!$K$5,'Calc Smart'!C19,'Calc Avalanche'!C19,'Calc Snowball'!C19,'Calc Cashflow'!C19) | G13: =CHOOSE(Plan!$K$5,'Calc Smart'!D19,'Calc Avalanche'!D19,'Calc Snowball'!D19,'Calc Cashflow'!D19) | H13: =CHOOSE(Plan!$K$5,'Calc Smart'!E19,'Calc Avalanche'!E19,'Calc Snowball'!E19,'Calc Cashflow'!E19) | I13: =CHOOSE(Plan!$K$5,'Calc Smart'!F19,'Calc Avalanche'!F19,'Calc Snowball'!F19,'Calc Cashflow'!F19) | J13: =CHOOSE(Plan!$K$5,'Calc Smart'!G19,'Calc Avalanche'!G19,'Calc Snowball'!G19,'Calc Cashflow'!G19) | K13: =CHOOSE(Plan!$K$5,'Calc Smart'!H19,'Calc Avalanche'!H19,'Calc Snowball'!H19,'Calc Cashflow'!H19) | L13: =CHOOSE(Plan!$K$5,'Calc Smart'!I19,'Calc Avalanche'!I19,'Calc Snowball'!I19,'Calc Cashflow'!I19) | M13: =CHOOSE(Plan!$K$5,'Calc Smart'!J19,'Calc Avalanche'!J19,'Calc Snowball'!J19,'Calc Cashflow'!J19) | ... Q13: =CHOOSE(Plan!$K$5,'Calc Smart'!N19,'Calc Avalanche'!N19,'Calc Snowball'!N19,'Calc Cashflow'!N19)
B14: =EDATE(Plan!$C$6,8) | C14: =CHOOSE(Plan!$K$5,'Calc Smart'!AE20,'Calc Avalanche'!AE20,'Calc Snowball'!AE20,'Calc Cashflow'!AE20) | D14: =CHOOSE(Plan!$K$5,'Calc Smart'!AD20,'Calc Avalanche'!AD20,'Calc Snowball'!AD20,'Calc Cashflow'!AD20) | E14: =CHOOSE(Plan!$K$5,COUNTIF('Calc Smart'!C20:N20,">0"),COUNTIF('Calc Avalanche'!C20:N20,">0"),COUNTIF('Calc Snowball'!C20:N20,">0"),COUNTIF('Calc Cashflow'!C20:N20,">0")) | F14: =CHOOSE(Plan!$K$5,'Calc Smart'!C20,'Calc Avalanche'!C20,'Calc Snowball'!C20,'Calc Cashflow'!C20) | G14: =CHOOSE(Plan!$K$5,'Calc Smart'!D20,'Calc Avalanche'!D20,'Calc Snowball'!D20,'Calc Cashflow'!D20) | H14: =CHOOSE(Plan!$K$5,'Calc Smart'!E20,'Calc Avalanche'!E20,'Calc Snowball'!E20,'Calc Cashflow'!E20) | I14: =CHOOSE(Plan!$K$5,'Calc Smart'!F20,'Calc Avalanche'!F20,'Calc Snowball'!F20,'Calc Cashflow'!F20) | J14: =CHOOSE(Plan!$K$5,'Calc Smart'!G20,'Calc Avalanche'!G20,'Calc Snowball'!G20,'Calc Cashflow'!G20) | K14: =CHOOSE(Plan!$K$5,'Calc Smart'!H20,'Calc Avalanche'!H20,'Calc Snowball'!H20,'Calc Cashflow'!H20) | L14: =CHOOSE(Plan!$K$5,'Calc Smart'!I20,'Calc Avalanche'!I20,'Calc Snowball'!I20,'Calc Cashflow'!I20) | M14: =CHOOSE(Plan!$K$5,'Calc Smart'!J20,'Calc Avalanche'!J20,'Calc Snowball'!J20,'Calc Cashflow'!J20) | ... Q14: =CHOOSE(Plan!$K$5,'Calc Smart'!N20,'Calc Avalanche'!N20,'Calc Snowball'!N20,'Calc Cashflow'!N20)
B15: =EDATE(Plan!$C$6,9) | C15: =CHOOSE(Plan!$K$5,'Calc Smart'!AE21,'Calc Avalanche'!AE21,'Calc Snowball'!AE21,'Calc Cashflow'!AE21) | D15: =CHOOSE(Plan!$K$5,'Calc Smart'!AD21,'Calc Avalanche'!AD21,'Calc Snowball'!AD21,'Calc Cashflow'!AD21) | E15: =CHOOSE(Plan!$K$5,COUNTIF('Calc Smart'!C21:N21,">0"),COUNTIF('Calc Avalanche'!C21:N21,">0"),COUNTIF('Calc Snowball'!C21:N21,">0"),COUNTIF('Calc Cashflow'!C21:N21,">0")) | F15: =CHOOSE(Plan!$K$5,'Calc Smart'!C21,'Calc Avalanche'!C21,'Calc Snowball'!C21,'Calc Cashflow'!C21) | G15: =CHOOSE(Plan!$K$5,'Calc Smart'!D21,'Calc Avalanche'!D21,'Calc Snowball'!D21,'Calc Cashflow'!D21) | H15: =CHOOSE(Plan!$K$5,'Calc Smart'!E21,'Calc Avalanche'!E21,'Calc Snowball'!E21,'Calc Cashflow'!E21) | I15: =CHOOSE(Plan!$K$5,'Calc Smart'!F21,'Calc Avalanche'!F21,'Calc Snowball'!F21,'Calc Cashflow'!F21) | J15: =CHOOSE(Plan!$K$5,'Calc Smart'!G21,'Calc Avalanche'!G21,'Calc Snowball'!G21,'Calc Cashflow'!G21) | K15: =CHOOSE(Plan!$K$5,'Calc Smart'!H21,'Calc Avalanche'!H21,'Calc Snowball'!H21,'Calc Cashflow'!H21) | L15: =CHOOSE(Plan!$K$5,'Calc Smart'!I21,'Calc Avalanche'!I21,'Calc Snowball'!I21,'Calc Cashflow'!I21) | M15: =CHOOSE(Plan!$K$5,'Calc Smart'!J21,'Calc Avalanche'!J21,'Calc Snowball'!J21,'Calc Cashflow'!J21) | ... Q15: =CHOOSE(Plan!$K$5,'Calc Smart'!N21,'Calc Avalanche'!N21,'Calc Snowball'!N21,'Calc Cashflow'!N21)
B16: =EDATE(Plan!$C$6,10) | C16: =CHOOSE(Plan!$K$5,'Calc Smart'!AE22,'Calc Avalanche'!AE22,'Calc Snowball'!AE22,'Calc Cashflow'!AE22) | D16: =CHOOSE(Plan!$K$5,'Calc Smart'!AD22,'Calc Avalanche'!AD22,'Calc Snowball'!AD22,'Calc Cashflow'!AD22) | E16: =CHOOSE(Plan!$K$5,COUNTIF('Calc Smart'!C22:N22,">0"),COUNTIF('Calc Avalanche'!C22:N22,">0"),COUNTIF('Calc Snowball'!C22:N22,">0"),COUNTIF('Calc Cashflow'!C22:N22,">0")) | F16: =CHOOSE(Plan!$K$5,'Calc Smart'!C22,'Calc Avalanche'!C22,'Calc Snowball'!C22,'Calc Cashflow'!C22) | G16: =CHOOSE(Plan!$K$5,'Calc Smart'!D22,'Calc Avalanche'!D22,'Calc Snowball'!D22,'Calc Cashflow'!D22) | H16: =CHOOSE(Plan!$K$5,'Calc Smart'!E22,'Calc Avalanche'!E22,'Calc Snowball'!E22,'Calc Cashflow'!E22) | I16: =CHOOSE(Plan!$K$5,'Calc Smart'!F22,'Calc Avalanche'!F22,'Calc Snowball'!F22,'Calc Cashflow'!F22) | J16: =CHOOSE(Plan!$K$5,'Calc Smart'!G22,'Calc Avalanche'!G22,'Calc Snowball'!G22,'Calc Cashflow'!G22) | K16: =CHOOSE(Plan!$K$5,'Calc Smart'!H22,'Calc Avalanche'!H22,'Calc Snowball'!H22,'Calc Cashflow'!H22) | L16: =CHOOSE(Plan!$K$5,'Calc Smart'!I22,'Calc Avalanche'!I22,'Calc Snowball'!I22,'Calc Cashflow'!I22) | M16: =CHOOSE(Plan!$K$5,'Calc Smart'!J22,'Calc Avalanche'!J22,'Calc Snowball'!J22,'Calc Cashflow'!J22) | ... Q16: =CHOOSE(Plan!$K$5,'Calc Smart'!N22,'Calc Avalanche'!N22,'Calc Snowball'!N22,'Calc Cashflow'!N22)
B17: =EDATE(Plan!$C$6,11) | C17: =CHOOSE(Plan!$K$5,'Calc Smart'!AE23,'Calc Avalanche'!AE23,'Calc Snowball'!AE23,'Calc Cashflow'!AE23) | D17: =CHOOSE(Plan!$K$5,'Calc Smart'!AD23,'Calc Avalanche'!AD23,'Calc Snowball'!AD23,'Calc Cashflow'!AD23) | E17: =CHOOSE(Plan!$K$5,COUNTIF('Calc Smart'!C23:N23,">0"),COUNTIF('Calc Avalanche'!C23:N23,">0"),COUNTIF('Calc Snowball'!C23:N23,">0"),COUNTIF('Calc Cashflow'!C23:N23,">0")) | F17: =CHOOSE(Plan!$K$5,'Calc Smart'!C23,'Calc Avalanche'!C23,'Calc Snowball'!C23,'Calc Cashflow'!C23) | G17: =CHOOSE(Plan!$K$5,'Calc Smart'!D23,'Calc Avalanche'!D23,'Calc Snowball'!D23,'Calc Cashflow'!D23) | H17: =CHOOSE(Plan!$K$5,'Calc Smart'!E23,'Calc Avalanche'!E23,'Calc Snowball'!E23,'Calc Cashflow'!E23) | I17: =CHOOSE(Plan!$K$5,'Calc Smart'!F23,'Calc Avalanche'!F23,'Calc Snowball'!F23,'Calc Cashflow'!F23) | J17: =CHOOSE(Plan!$K$5,'Calc Smart'!G23,'Calc Avalanche'!G23,'Calc Snowball'!G23,'Calc Cashflow'!G23) | K17: =CHOOSE(Plan!$K$5,'Calc Smart'!H23,'Calc Avalanche'!H23,'Calc Snowball'!H23,'Calc Cashflow'!H23) | L17: =CHOOSE(Plan!$K$5,'Calc Smart'!I23,'Calc Avalanche'!I23,'Calc Snowball'!I23,'Calc Cashflow'!I23) | M17: =CHOOSE(Plan!$K$5,'Calc Smart'!J23,'Calc Avalanche'!J23,'Calc Snowball'!J23,'Calc Cashflow'!J23) | ... Q17: =CHOOSE(Plan!$K$5,'Calc Smart'!N23,'Calc Avalanche'!N23,'Calc Snowball'!N23,'Calc Cashflow'!N23)
B18: =EDATE(Plan!$C$6,12) | C18: =CHOOSE(Plan!$K$5,'Calc Smart'!AE24,'Calc Avalanche'!AE24,'Calc Snowball'!AE24,'Calc Cashflow'!AE24) | D18: =CHOOSE(Plan!$K$5,'Calc Smart'!AD24,'Calc Avalanche'!AD24,'Calc Snowball'!AD24,'Calc Cashflow'!AD24) | E18: =CHOOSE(Plan!$K$5,COUNTIF('Calc Smart'!C24:N24,">0"),COUNTIF('Calc Avalanche'!C24:N24,">0"),COUNTIF('Calc Snowball'!C24:N24,">0"),COUNTIF('Calc Cashflow'!C24:N24,">0")) | F18: =CHOOSE(Plan!$K$5,'Calc Smart'!C24,'Calc Avalanche'!C24,'Calc Snowball'!C24,'Calc Cashflow'!C24) | G18: =CHOOSE(Plan!$K$5,'Calc Smart'!D24,'Calc Avalanche'!D24,'Calc Snowball'!D24,'Calc Cashflow'!D24) | H18: =CHOOSE(Plan!$K$5,'Calc Smart'!E24,'Calc Avalanche'!E24,'Calc Snowball'!E24,'Calc Cashflow'!E24) | I18: =CHOOSE(Plan!$K$5,'Calc Smart'!F24,'Calc Avalanche'!F24,'Calc Snowball'!F24,'Calc Cashflow'!F24) | J18: =CHOOSE(Plan!$K$5,'Calc Smart'!G24,'Calc Avalanche'!G24,'Calc Snowball'!G24,'Calc Cashflow'!G24) | K18: =CHOOSE(Plan!$K$5,'Calc Smart'!H24,'Calc Avalanche'!H24,'Calc Snowball'!H24,'Calc Cashflow'!H24) | L18: =CHOOSE(Plan!$K$5,'Calc Smart'!I24,'Calc Avalanche'!I24,'Calc Snowball'!I24,'Calc Cashflow'!I24) | M18: =CHOOSE(Plan!$K$5,'Calc Smart'!J24,'Calc Avalanche'!J24,'Calc Snowball'!J24,'Calc Cashflow'!J24) | ... Q18: =CHOOSE(Plan!$K$5,'Calc Smart'!N24,'Calc Avalanche'!N24,'Calc Snowball'!N24,'Calc Cashflow'!N24)
B19: =EDATE(Plan!$C$6,13) | C19: =CHOOSE(Plan!$K$5,'Calc Smart'!AE25,'Calc Avalanche'!AE25,'Calc Snowball'!AE25,'Calc Cashflow'!AE25) | D19: =CHOOSE(Plan!$K$5,'Calc Smart'!AD25,'Calc Avalanche'!AD25,'Calc Snowball'!AD25,'Calc Cashflow'!AD25) | E19: =CHOOSE(Plan!$K$5,COUNTIF('Calc Smart'!C25:N25,">0"),COUNTIF('Calc Avalanche'!C25:N25,">0"),COUNTIF('Calc Snowball'!C25:N25,">0"),COUNTIF('Calc Cashflow'!C25:N25,">0")) | F19: =CHOOSE(Plan!$K$5,'Calc Smart'!C25,'Calc Avalanche'!C25,'Calc Snowball'!C25,'Calc Cashflow'!C25) | G19: =CHOOSE(Plan!$K$5,'Calc Smart'!D25,'Calc Avalanche'!D25,'Calc Snowball'!D25,'Calc Cashflow'!D25) | H19: =CHOOSE(Plan!$K$5,'Calc Smart'!E25,'Calc Avalanche'!E25,'Calc Snowball'!E25,'Calc Cashflow'!E25) | I19: =CHOOSE(Plan!$K$5,'Calc Smart'!F25,'Calc Avalanche'!F25,'Calc Snowball'!F25,'Calc Cashflow'!F25) | J19: =CHOOSE(Plan!$K$5,'Calc Smart'!G25,'Calc Avalanche'!G25,'Calc Snowball'!G25,'Calc Cashflow'!G25) | K19: =CHOOSE(Plan!$K$5,'Calc Smart'!H25,'Calc Avalanche'!H25,'Calc Snowball'!H25,'Calc Cashflow'!H25) | L19: =CHOOSE(Plan!$K$5,'Calc Smart'!I25,'Calc Avalanche'!I25,'Calc Snowball'!I25,'Calc Cashflow'!I25) | M19: =CHOOSE(Plan!$K$5,'Calc Smart'!J25,'Calc Avalanche'!J25,'Calc Snowball'!J25,'Calc Cashflow'!J25) | ... Q19: =CHOOSE(Plan!$K$5,'Calc Smart'!N25,'Calc Avalanche'!N25,'Calc Snowball'!N25,'Calc Cashflow'!N25)
B20: =EDATE(Plan!$C$6,14) | C20: =CHOOSE(Plan!$K$5,'Calc Smart'!AE26,'Calc Avalanche'!AE26,'Calc Snowball'!AE26,'Calc Cashflow'!AE26) | D20: =CHOOSE(Plan!$K$5,'Calc Smart'!AD26,'Calc Avalanche'!AD26,'Calc Snowball'!AD26,'Calc Cashflow'!AD26) | E20: =CHOOSE(Plan!$K$5,COUNTIF('Calc Smart'!C26:N26,">0"),COUNTIF('Calc Avalanche'!C26:N26,">0"),COUNTIF('Calc Snowball'!C26:N26,">0"),COUNTIF('Calc Cashflow'!C26:N26,">0")) | F20: =CHOOSE(Plan!$K$5,'Calc Smart'!C26,'Calc Avalanche'!C26,'Calc Snowball'!C26,'Calc Cashflow'!C26) | G20: =CHOOSE(Plan!$K$5,'Calc Smart'!D26,'Calc Avalanche'!D26,'Calc Snowball'!D26,'Calc Cashflow'!D26) | H20: =CHOOSE(Plan!$K$5,'Calc Smart'!E26,'Calc Avalanche'!E26,'Calc Snowball'!E26,'Calc Cashflow'!E26) | I20: =CHOOSE(Plan!$K$5,'Calc Smart'!F26,'Calc Avalanche'!F26,'Calc Snowball'!F26,'Calc Cashflow'!F26) | J20: =CHOOSE(Plan!$K$5,'Calc Smart'!G26,'Calc Avalanche'!G26,'Calc Snowball'!G26,'Calc Cashflow'!G26) | K20: =CHOOSE(Plan!$K$5,'Calc Smart'!H26,'Calc Avalanche'!H26,'Calc Snowball'!H26,'Calc Cashflow'!H26) | L20: =CHOOSE(Plan!$K$5,'Calc Smart'!I26,'Calc Avalanche'!I26,'Calc Snowball'!I26,'Calc Cashflow'!I26) | M20: =CHOOSE(Plan!$K$5,'Calc Smart'!J26,'Calc Avalanche'!J26,'Calc Snowball'!J26,'Calc Cashflow'!J26) | ... Q20: =CHOOSE(Plan!$K$5,'Calc Smart'!N26,'Calc Avalanche'!N26,'Calc Snowball'!N26,'Calc Cashflow'!N26)
B21: =EDATE(Plan!$C$6,15) | C21: =CHOOSE(Plan!$K$5,'Calc Smart'!AE27,'Calc Avalanche'!AE27,'Calc Snowball'!AE27,'Calc Cashflow'!AE27) | D21: =CHOOSE(Plan!$K$5,'Calc Smart'!AD27,'Calc Avalanche'!AD27,'Calc Snowball'!AD27,'Calc Cashflow'!AD27) | E21: =CHOOSE(Plan!$K$5,COUNTIF('Calc Smart'!C27:N27,">0"),COUNTIF('Calc Avalanche'!C27:N27,">0"),COUNTIF('Calc Snowball'!C27:N27,">0"),COUNTIF('Calc Cashflow'!C27:N27,">0")) | F21: =CHOOSE(Plan!$K$5,'Calc Smart'!C27,'Calc Avalanche'!C27,'Calc Snowball'!C27,'Calc Cashflow'!C27) | G21: =CHOOSE(Plan!$K$5,'Calc Smart'!D27,'Calc Avalanche'!D27,'Calc Snowball'!D27,'Calc Cashflow'!D27) | H21: =CHOOSE(Plan!$K$5,'Calc Smart'!E27,'Calc Avalanche'!E27,'Calc Snowball'!E27,'Calc Cashflow'!E27) | I21: =CHOOSE(Plan!$K$5,'Calc Smart'!F27,'Calc Avalanche'!F27,'Calc Snowball'!F27,'Calc Cashflow'!F27) | J21: =CHOOSE(Plan!$K$5,'Calc Smart'!G27,'Calc Avalanche'!G27,'Calc Snowball'!G27,'Calc Cashflow'!G27) | K21: =CHOOSE(Plan!$K$5,'Calc Smart'!H27,'Calc Avalanche'!H27,'Calc Snowball'!H27,'Calc Cashflow'!H27) | L21: =CHOOSE(Plan!$K$5,'Calc Smart'!I27,'Calc Avalanche'!I27,'Calc Snowball'!I27,'Calc Cashflow'!I27) | M21: =CHOOSE(Plan!$K$5,'Calc Smart'!J27,'Calc Avalanche'!J27,'Calc Snowball'!J27,'Calc Cashflow'!J27) | ... Q21: =CHOOSE(Plan!$K$5,'Calc Smart'!N27,'Calc Avalanche'!N27,'Calc Snowball'!N27,'Calc Cashflow'!N27)
B22: =EDATE(Plan!$C$6,16) | C22: =CHOOSE(Plan!$K$5,'Calc Smart'!AE28,'Calc Avalanche'!AE28,'Calc Snowball'!AE28,'Calc Cashflow'!AE28) | D22: =CHOOSE(Plan!$K$5,'Calc Smart'!AD28,'Calc Avalanche'!AD28,'Calc Snowball'!AD28,'Calc Cashflow'!AD28) | E22: =CHOOSE(Plan!$K$5,COUNTIF('Calc Smart'!C28:N28,">0"),COUNTIF('Calc Avalanche'!C28:N28,">0"),COUNTIF('Calc Snowball'!C28:N28,">0"),COUNTIF('Calc Cashflow'!C28:N28,">0")) | F22: =CHOOSE(Plan!$K$5,'Calc Smart'!C28,'Calc Avalanche'!C28,'Calc Snowball'!C28,'Calc Cashflow'!C28) | G22: =CHOOSE(Plan!$K$5,'Calc Smart'!D28,'Calc Avalanche'!D28,'Calc Snowball'!D28,'Calc Cashflow'!D28) | H22: =CHOOSE(Plan!$K$5,'Calc Smart'!E28,'Calc Avalanche'!E28,'Calc Snowball'!E28,'Calc Cashflow'!E28) | I22: =CHOOSE(Plan!$K$5,'Calc Smart'!F28,'Calc Avalanche'!F28,'Calc Snowball'!F28,'Calc Cashflow'!F28) | J22: =CHOOSE(Plan!$K$5,'Calc Smart'!G28,'Calc Avalanche'!G28,'Calc Snowball'!G28,'Calc Cashflow'!G28) | K22: =CHOOSE(Plan!$K$5,'Calc Smart'!H28,'Calc Avalanche'!H28,'Calc Snowball'!H28,'Calc Cashflow'!H28) | L22: =CHOOSE(Plan!$K$5,'Calc Smart'!I28,'Calc Avalanche'!I28,'Calc Snowball'!I28,'Calc Cashflow'!I28) | M22: =CHOOSE(Plan!$K$5,'Calc Smart'!J28,'Calc Avalanche'!J28,'Calc Snowball'!J28,'Calc Cashflow'!J28) | ... Q22: =CHOOSE(Plan!$K$5,'Calc Smart'!N28,'Calc Avalanche'!N28,'Calc Snowball'!N28,'Calc Cashflow'!N28)
B23: =EDATE(Plan!$C$6,17) | C23: =CHOOSE(Plan!$K$5,'Calc Smart'!AE29,'Calc Avalanche'!AE29,'Calc Snowball'!AE29,'Calc Cashflow'!AE29) | D23: =CHOOSE(Plan!$K$5,'Calc Smart'!AD29,'Calc Avalanche'!AD29,'Calc Snowball'!AD29,'Calc Cashflow'!AD29) | E23: =CHOOSE(Plan!$K$5,COUNTIF('Calc Smart'!C29:N29,">0"),COUNTIF('Calc Avalanche'!C29:N29,">0"),COUNTIF('Calc Snowball'!C29:N29,">0"),COUNTIF('Calc Cashflow'!C29:N29,">0")) | F23: =CHOOSE(Plan!$K$5,'Calc Smart'!C29,'Calc Avalanche'!C29,'Calc Snowball'!C29,'Calc Cashflow'!C29) | G23: =CHOOSE(Plan!$K$5,'Calc Smart'!D29,'Calc Avalanche'!D29,'Calc Snowball'!D29,'Calc Cashflow'!D29) | H23: =CHOOSE(Plan!$K$5,'Calc Smart'!E29,'Calc Avalanche'!E29,'Calc Snowball'!E29,'Calc Cashflow'!E29) | I23: =CHOOSE(Plan!$K$5,'Calc Smart'!F29,'Calc Avalanche'!F29,'Calc Snowball'!F29,'Calc Cashflow'!F29) | J23: =CHOOSE(Plan!$K$5,'Calc Smart'!G29,'Calc Avalanche'!G29,'Calc Snowball'!G29,'Calc Cashflow'!G29) | K23: =CHOOSE(Plan!$K$5,'Calc Smart'!H29,'Calc Avalanche'!H29,'Calc Snowball'!H29,'Calc Cashflow'!H29) | L23: =CHOOSE(Plan!$K$5,'Calc Smart'!I29,'Calc Avalanche'!I29,'Calc Snowball'!I29,'Calc Cashflow'!I29) | M23: =CHOOSE(Plan!$K$5,'Calc Smart'!J29,'Calc Avalanche'!J29,'Calc Snowball'!J29,'Calc Cashflow'!J29) | ... Q23: =CHOOSE(Plan!$K$5,'Calc Smart'!N29,'Calc Avalanche'!N29,'Calc Snowball'!N29,'Calc Cashflow'!N29)
B24: =EDATE(Plan!$C$6,18) | C24: =CHOOSE(Plan!$K$5,'Calc Smart'!AE30,'Calc Avalanche'!AE30,'Calc Snowball'!AE30,'Calc Cashflow'!AE30) | D24: =CHOOSE(Plan!$K$5,'Calc Smart'!AD30,'Calc Avalanche'!AD30,'Calc Snowball'!AD30,'Calc Cashflow'!AD30) | E24: =CHOOSE(Plan!$K$5,COUNTIF('Calc Smart'!C30:N30,">0"),COUNTIF('Calc Avalanche'!C30:N30,">0"),COUNTIF('Calc Snowball'!C30:N30,">0"),COUNTIF('Calc Cashflow'!C30:N30,">0")) | F24: =CHOOSE(Plan!$K$5,'Calc Smart'!C30,'Calc Avalanche'!C30,'Calc Snowball'!C30,'Calc Cashflow'!C30) | G24: =CHOOSE(Plan!$K$5,'Calc Smart'!D30,'Calc Avalanche'!D30,'Calc Snowball'!D30,'Calc Cashflow'!D30) | H24: =CHOOSE(Plan!$K$5,'Calc Smart'!E30,'Calc Avalanche'!E30,'Calc Snowball'!E30,'Calc Cashflow'!E30) | I24: =CHOOSE(Plan!$K$5,'Calc Smart'!F30,'Calc Avalanche'!F30,'Calc Snowball'!F30,'Calc Cashflow'!F30) | J24: =CHOOSE(Plan!$K$5,'Calc Smart'!G30,'Calc Avalanche'!G30,'Calc Snowball'!G30,'Calc Cashflow'!G30) | K24: =CHOOSE(Plan!$K$5,'Calc Smart'!H30,'Calc Avalanche'!H30,'Calc Snowball'!H30,'Calc Cashflow'!H30) | L24: =CHOOSE(Plan!$K$5,'Calc Smart'!I30,'Calc Avalanche'!I30,'Calc Snowball'!I30,'Calc Cashflow'!I30) | M24: =CHOOSE(Plan!$K$5,'Calc Smart'!J30,'Calc Avalanche'!J30,'Calc Snowball'!J30,'Calc Cashflow'!J30) | ... Q24: =CHOOSE(Plan!$K$5,'Calc Smart'!N30,'Calc Avalanche'!N30,'Calc Snowball'!N30,'Calc Cashflow'!N30)
B25: =EDATE(Plan!$C$6,19) | C25: =CHOOSE(Plan!$K$5,'Calc Smart'!AE31,'Calc Avalanche'!AE31,'Calc Snowball'!AE31,'Calc Cashflow'!AE31) | D25: =CHOOSE(Plan!$K$5,'Calc Smart'!AD31,'Calc Avalanche'!AD31,'Calc Snowball'!AD31,'Calc Cashflow'!AD31) | E25: =CHOOSE(Plan!$K$5,COUNTIF('Calc Smart'!C31:N31,">0"),COUNTIF('Calc Avalanche'!C31:N31,">0"),COUNTIF('Calc Snowball'!C31:N31,">0"),COUNTIF('Calc Cashflow'!C31:N31,">0")) | F25: =CHOOSE(Plan!$K$5,'Calc Smart'!C31,'Calc Avalanche'!C31,'Calc Snowball'!C31,'Calc Cashflow'!C31) | G25: =CHOOSE(Plan!$K$5,'Calc Smart'!D31,'Calc Avalanche'!D31,'Calc Snowball'!D31,'Calc Cashflow'!D31) | H25: =CHOOSE(Plan!$K$5,'Calc Smart'!E31,'Calc Avalanche'!E31,'Calc Snowball'!E31,'Calc Cashflow'!E31) | I25: =CHOOSE(Plan!$K$5,'Calc Smart'!F31,'Calc Avalanche'!F31,'Calc Snowball'!F31,'Calc Cashflow'!F31) | J25: =CHOOSE(Plan!$K$5,'Calc Smart'!G31,'Calc Avalanche'!G31,'Calc Snowball'!G31,'Calc Cashflow'!G31) | K25: =CHOOSE(Plan!$K$5,'Calc Smart'!H31,'Calc Avalanche'!H31,'Calc Snowball'!H31,'Calc Cashflow'!H31) | L25: =CHOOSE(Plan!$K$5,'Calc Smart'!I31,'Calc Avalanche'!I31,'Calc Snowball'!I31,'Calc Cashflow'!I31) | M25: =CHOOSE(Plan!$K$5,'Calc Smart'!J31,'Calc Avalanche'!J31,'Calc Snowball'!J31,'Calc Cashflow'!J31) | ... Q25: =CHOOSE(Plan!$K$5,'Calc Smart'!N31,'Calc Avalanche'!N31,'Calc Snowball'!N31,'Calc Cashflow'!N31)
B26: =EDATE(Plan!$C$6,20) | C26: =CHOOSE(Plan!$K$5,'Calc Smart'!AE32,'Calc Avalanche'!AE32,'Calc Snowball'!AE32,'Calc Cashflow'!AE32) | D26: =CHOOSE(Plan!$K$5,'Calc Smart'!AD32,'Calc Avalanche'!AD32,'Calc Snowball'!AD32,'Calc Cashflow'!AD32) | E26: =CHOOSE(Plan!$K$5,COUNTIF('Calc Smart'!C32:N32,">0"),COUNTIF('Calc Avalanche'!C32:N32,">0"),COUNTIF('Calc Snowball'!C32:N32,">0"),COUNTIF('Calc Cashflow'!C32:N32,">0")) | F26: =CHOOSE(Plan!$K$5,'Calc Smart'!C32,'Calc Avalanche'!C32,'Calc Snowball'!C32,'Calc Cashflow'!C32) | G26: =CHOOSE(Plan!$K$5,'Calc Smart'!D32,'Calc Avalanche'!D32,'Calc Snowball'!D32,'Calc Cashflow'!D32) | H26: =CHOOSE(Plan!$K$5,'Calc Smart'!E32,'Calc Avalanche'!E32,'Calc Snowball'!E32,'Calc Cashflow'!E32) | I26: =CHOOSE(Plan!$K$5,'Calc Smart'!F32,'Calc Avalanche'!F32,'Calc Snowball'!F32,'Calc Cashflow'!F32) | J26: =CHOOSE(Plan!$K$5,'Calc Smart'!G32,'Calc Avalanche'!G32,'Calc Snowball'!G32,'Calc Cashflow'!G32) | K26: =CHOOSE(Plan!$K$5,'Calc Smart'!H32,'Calc Avalanche'!H32,'Calc Snowball'!H32,'Calc Cashflow'!H32) | L26: =CHOOSE(Plan!$K$5,'Calc Smart'!I32,'Calc Avalanche'!I32,'Calc Snowball'!I32,'Calc Cashflow'!I32) | M26: =CHOOSE(Plan!$K$5,'Calc Smart'!J32,'Calc Avalanche'!J32,'Calc Snowball'!J32,'Calc Cashflow'!J32) | ... Q26: =CHOOSE(Plan!$K$5,'Calc Smart'!N32,'Calc Avalanche'!N32,'Calc Snowball'!N32,'Calc Cashflow'!N32)
B27: =EDATE(Plan!$C$6,21) | C27: =CHOOSE(Plan!$K$5,'Calc Smart'!AE33,'Calc Avalanche'!AE33,'Calc Snowball'!AE33,'Calc Cashflow'!AE33) | D27: =CHOOSE(Plan!$K$5,'Calc Smart'!AD33,'Calc Avalanche'!AD33,'Calc Snowball'!AD33,'Calc Cashflow'!AD33) | E27: =CHOOSE(Plan!$K$5,COUNTIF('Calc Smart'!C33:N33,">0"),COUNTIF('Calc Avalanche'!C33:N33,">0"),COUNTIF('Calc Snowball'!C33:N33,">0"),COUNTIF('Calc Cashflow'!C33:N33,">0")) | F27: =CHOOSE(Plan!$K$5,'Calc Smart'!C33,'Calc Avalanche'!C33,'Calc Snowball'!C33,'Calc Cashflow'!C33) | G27: =CHOOSE(Plan!$K$5,'Calc Smart'!D33,'Calc Avalanche'!D33,'Calc Snowball'!D33,'Calc Cashflow'!D33) | H27: =CHOOSE(Plan!$K$5,'Calc Smart'!E33,'Calc Avalanche'!E33,'Calc Snowball'!E33,'Calc Cashflow'!E33) | I27: =CHOOSE(Plan!$K$5,'Calc Smart'!F33,'Calc Avalanche'!F33,'Calc Snowball'!F33,'Calc Cashflow'!F33) | J27: =CHOOSE(Plan!$K$5,'Calc Smart'!G33,'Calc Avalanche'!G33,'Calc Snowball'!G33,'Calc Cashflow'!G33) | K27: =CHOOSE(Plan!$K$5,'Calc Smart'!H33,'Calc Avalanche'!H33,'Calc Snowball'!H33,'Calc Cashflow'!H33) | L27: =CHOOSE(Plan!$K$5,'Calc Smart'!I33,'Calc Avalanche'!I33,'Calc Snowball'!I33,'Calc Cashflow'!I33) | M27: =CHOOSE(Plan!$K$5,'Calc Smart'!J33,'Calc Avalanche'!J33,'Calc Snowball'!J33,'Calc Cashflow'!J33) | ... Q27: =CHOOSE(Plan!$K$5,'Calc Smart'!N33,'Calc Avalanche'!N33,'Calc Snowball'!N33,'Calc Cashflow'!N33)
B28: =EDATE(Plan!$C$6,22) | C28: =CHOOSE(Plan!$K$5,'Calc Smart'!AE34,'Calc Avalanche'!AE34,'Calc Snowball'!AE34,'Calc Cashflow'!AE34) | D28: =CHOOSE(Plan!$K$5,'Calc Smart'!AD34,'Calc Avalanche'!AD34,'Calc Snowball'!AD34,'Calc Cashflow'!AD34) | E28: =CHOOSE(Plan!$K$5,COUNTIF('Calc Smart'!C34:N34,">0"),COUNTIF('Calc Avalanche'!C34:N34,">0"),COUNTIF('Calc Snowball'!C34:N34,">0"),COUNTIF('Calc Cashflow'!C34:N34,">0")) | F28: =CHOOSE(Plan!$K$5,'Calc Smart'!C34,'Calc Avalanche'!C34,'Calc Snowball'!C34,'Calc Cashflow'!C34) | G28: =CHOOSE(Plan!$K$5,'Calc Smart'!D34,'Calc Avalanche'!D34,'Calc Snowball'!D34,'Calc Cashflow'!D34) | H28: =CHOOSE(Plan!$K$5,'Calc Smart'!E34,'Calc Avalanche'!E34,'Calc Snowball'!E34,'Calc Cashflow'!E34) | I28: =CHOOSE(Plan!$K$5,'Calc Smart'!F34,'Calc Avalanche'!F34,'Calc Snowball'!F34,'Calc Cashflow'!F34) | J28: =CHOOSE(Plan!$K$5,'Calc Smart'!G34,'Calc Avalanche'!G34,'Calc Snowball'!G34,'Calc Cashflow'!G34) | K28: =CHOOSE(Plan!$K$5,'Calc Smart'!H34,'Calc Avalanche'!H34,'Calc Snowball'!H34,'Calc Cashflow'!H34) | L28: =CHOOSE(Plan!$K$5,'Calc Smart'!I34,'Calc Avalanche'!I34,'Calc Snowball'!I34,'Calc Cashflow'!I34) | M28: =CHOOSE(Plan!$K$5,'Calc Smart'!J34,'Calc Avalanche'!J34,'Calc Snowball'!J34,'Calc Cashflow'!J34) | ... Q28: =CHOOSE(Plan!$K$5,'Calc Smart'!N34,'Calc Avalanche'!N34,'Calc Snowball'!N34,'Calc Cashflow'!N34)
B29: =EDATE(Plan!$C$6,23) | C29: =CHOOSE(Plan!$K$5,'Calc Smart'!AE35,'Calc Avalanche'!AE35,'Calc Snowball'!AE35,'Calc Cashflow'!AE35) | D29: =CHOOSE(Plan!$K$5,'Calc Smart'!AD35,'Calc Avalanche'!AD35,'Calc Snowball'!AD35,'Calc Cashflow'!AD35) | E29: =CHOOSE(Plan!$K$5,COUNTIF('Calc Smart'!C35:N35,">0"),COUNTIF('Calc Avalanche'!C35:N35,">0"),COUNTIF('Calc Snowball'!C35:N35,">0"),COUNTIF('Calc Cashflow'!C35:N35,">0")) | F29: =CHOOSE(Plan!$K$5,'Calc Smart'!C35,'Calc Avalanche'!C35,'Calc Snowball'!C35,'Calc Cashflow'!C35) | G29: =CHOOSE(Plan!$K$5,'Calc Smart'!D35,'Calc Avalanche'!D35,'Calc Snowball'!D35,'Calc Cashflow'!D35) | H29: =CHOOSE(Plan!$K$5,'Calc Smart'!E35,'Calc Avalanche'!E35,'Calc Snowball'!E35,'Calc Cashflow'!E35) | I29: =CHOOSE(Plan!$K$5,'Calc Smart'!F35,'Calc Avalanche'!F35,'Calc Snowball'!F35,'Calc Cashflow'!F35) | J29: =CHOOSE(Plan!$K$5,'Calc Smart'!G35,'Calc Avalanche'!G35,'Calc Snowball'!G35,'Calc Cashflow'!G35) | K29: =CHOOSE(Plan!$K$5,'Calc Smart'!H35,'Calc Avalanche'!H35,'Calc Snowball'!H35,'Calc Cashflow'!H35) | L29: =CHOOSE(Plan!$K$5,'Calc Smart'!I35,'Calc Avalanche'!I35,'Calc Snowball'!I35,'Calc Cashflow'!I35) | M29: =CHOOSE(Plan!$K$5,'Calc Smart'!J35,'Calc Avalanche'!J35,'Calc Snowball'!J35,'Calc Cashflow'!J35) | ... Q29: =CHOOSE(Plan!$K$5,'Calc Smart'!N35,'Calc Avalanche'!N35,'Calc Snowball'!N35,'Calc Cashflow'!N35)
B30: =EDATE(Plan!$C$6,24) | C30: =CHOOSE(Plan!$K$5,'Calc Smart'!AE36,'Calc Avalanche'!AE36,'Calc Snowball'!AE36,'Calc Cashflow'!AE36) | D30: =CHOOSE(Plan!$K$5,'Calc Smart'!AD36,'Calc Avalanche'!AD36,'Calc Snowball'!AD36,'Calc Cashflow'!AD36) | E30: =CHOOSE(Plan!$K$5,COUNTIF('Calc Smart'!C36:N36,">0"),COUNTIF('Calc Avalanche'!C36:N36,">0"),COUNTIF('Calc Snowball'!C36:N36,">0"),COUNTIF('Calc Cashflow'!C36:N36,">0")) | F30: =CHOOSE(Plan!$K$5,'Calc Smart'!C36,'Calc Avalanche'!C36,'Calc Snowball'!C36,'Calc Cashflow'!C36) | G30: =CHOOSE(Plan!$K$5,'Calc Smart'!D36,'Calc Avalanche'!D36,'Calc Snowball'!D36,'Calc Cashflow'!D36) | H30: =CHOOSE(Plan!$K$5,'Calc Smart'!E36,'Calc Avalanche'!E36,'Calc Snowball'!E36,'Calc Cashflow'!E36) | I30: =CHOOSE(Plan!$K$5,'Calc Smart'!F36,'Calc Avalanche'!F36,'Calc Snowball'!F36,'Calc Cashflow'!F36) | J30: =CHOOSE(Plan!$K$5,'Calc Smart'!G36,'Calc Avalanche'!G36,'Calc Snowball'!G36,'Calc Cashflow'!G36) | K30: =CHOOSE(Plan!$K$5,'Calc Smart'!H36,'Calc Avalanche'!H36,'Calc Snowball'!H36,'Calc Cashflow'!H36) | L30: =CHOOSE(Plan!$K$5,'Calc Smart'!I36,'Calc Avalanche'!I36,'Calc Snowball'!I36,'Calc Cashflow'!I36) | M30: =CHOOSE(Plan!$K$5,'Calc Smart'!J36,'Calc Avalanche'!J36,'Calc Snowball'!J36,'Calc Cashflow'!J36) | ... Q30: =CHOOSE(Plan!$K$5,'Calc Smart'!N36,'Calc Avalanche'!N36,'Calc Snowball'!N36,'Calc Cashflow'!N36)
B31: =EDATE(Plan!$C$6,25) | C31: =CHOOSE(Plan!$K$5,'Calc Smart'!AE37,'Calc Avalanche'!AE37,'Calc Snowball'!AE37,'Calc Cashflow'!AE37) | D31: =CHOOSE(Plan!$K$5,'Calc Smart'!AD37,'Calc Avalanche'!AD37,'Calc Snowball'!AD37,'Calc Cashflow'!AD37) | E31: =CHOOSE(Plan!$K$5,COUNTIF('Calc Smart'!C37:N37,">0"),COUNTIF('Calc Avalanche'!C37:N37,">0"),COUNTIF('Calc Snowball'!C37:N37,">0"),COUNTIF('Calc Cashflow'!C37:N37,">0")) | F31: =CHOOSE(Plan!$K$5,'Calc Smart'!C37,'Calc Avalanche'!C37,'Calc Snowball'!C37,'Calc Cashflow'!C37) | G31: =CHOOSE(Plan!$K$5,'Calc Smart'!D37,'Calc Avalanche'!D37,'Calc Snowball'!D37,'Calc Cashflow'!D37) | H31: =CHOOSE(Plan!$K$5,'Calc Smart'!E37,'Calc Avalanche'!E37,'Calc Snowball'!E37,'Calc Cashflow'!E37) | I31: =CHOOSE(Plan!$K$5,'Calc Smart'!F37,'Calc Avalanche'!F37,'Calc Snowball'!F37,'Calc Cashflow'!F37) | J31: =CHOOSE(Plan!$K$5,'Calc Smart'!G37,'Calc Avalanche'!G37,'Calc Snowball'!G37,'Calc Cashflow'!G37) | K31: =CHOOSE(Plan!$K$5,'Calc Smart'!H37,'Calc Avalanche'!H37,'Calc Snowball'!H37,'Calc Cashflow'!H37) | L31: =CHOOSE(Plan!$K$5,'Calc Smart'!I37,'Calc Avalanche'!I37,'Calc Snowball'!I37,'Calc Cashflow'!I37) | M31: =CHOOSE(Plan!$K$5,'Calc Smart'!J37,'Calc Avalanche'!J37,'Calc Snowball'!J37,'Calc Cashflow'!J37) | ... Q31: =CHOOSE(Plan!$K$5,'Calc Smart'!N37,'Calc Avalanche'!N37,'Calc Snowball'!N37,'Calc Cashflow'!N37)
B32: =EDATE(Plan!$C$6,26) | C32: =CHOOSE(Plan!$K$5,'Calc Smart'!AE38,'Calc Avalanche'!AE38,'Calc Snowball'!AE38,'Calc Cashflow'!AE38) | D32: =CHOOSE(Plan!$K$5,'Calc Smart'!AD38,'Calc Avalanche'!AD38,'Calc Snowball'!AD38,'Calc Cashflow'!AD38) | E32: =CHOOSE(Plan!$K$5,COUNTIF('Calc Smart'!C38:N38,">0"),COUNTIF('Calc Avalanche'!C38:N38,">0"),COUNTIF('Calc Snowball'!C38:N38,">0"),COUNTIF('Calc Cashflow'!C38:N38,">0")) | F32: =CHOOSE(Plan!$K$5,'Calc Smart'!C38,'Calc Avalanche'!C38,'Calc Snowball'!C38,'Calc Cashflow'!C38) | G32: =CHOOSE(Plan!$K$5,'Calc Smart'!D38,'Calc Avalanche'!D38,'Calc Snowball'!D38,'Calc Cashflow'!D38) | H32: =CHOOSE(Plan!$K$5,'Calc Smart'!E38,'Calc Avalanche'!E38,'Calc Snowball'!E38,'Calc Cashflow'!E38) | I32: =CHOOSE(Plan!$K$5,'Calc Smart'!F38,'Calc Avalanche'!F38,'Calc Snowball'!F38,'Calc Cashflow'!F38) | J32: =CHOOSE(Plan!$K$5,'Calc Smart'!G38,'Calc Avalanche'!G38,'Calc Snowball'!G38,'Calc Cashflow'!G38) | K32: =CHOOSE(Plan!$K$5,'Calc Smart'!H38,'Calc Avalanche'!H38,'Calc Snowball'!H38,'Calc Cashflow'!H38) | L32: =CHOOSE(Plan!$K$5,'Calc Smart'!I38,'Calc Avalanche'!I38,'Calc Snowball'!I38,'Calc Cashflow'!I38) | M32: =CHOOSE(Plan!$K$5,'Calc Smart'!J38,'Calc Avalanche'!J38,'Calc Snowball'!J38,'Calc Cashflow'!J38) | ... Q32: =CHOOSE(Plan!$K$5,'Calc Smart'!N38,'Calc Avalanche'!N38,'Calc Snowball'!N38,'Calc Cashflow'!N38)
B33: =EDATE(Plan!$C$6,27) | C33: =CHOOSE(Plan!$K$5,'Calc Smart'!AE39,'Calc Avalanche'!AE39,'Calc Snowball'!AE39,'Calc Cashflow'!AE39) | D33: =CHOOSE(Plan!$K$5,'Calc Smart'!AD39,'Calc Avalanche'!AD39,'Calc Snowball'!AD39,'Calc Cashflow'!AD39) | E33: =CHOOSE(Plan!$K$5,COUNTIF('Calc Smart'!C39:N39,">0"),COUNTIF('Calc Avalanche'!C39:N39,">0"),COUNTIF('Calc Snowball'!C39:N39,">0"),COUNTIF('Calc Cashflow'!C39:N39,">0")) | F33: =CHOOSE(Plan!$K$5,'Calc Smart'!C39,'Calc Avalanche'!C39,'Calc Snowball'!C39,'Calc Cashflow'!C39) | G33: =CHOOSE(Plan!$K$5,'Calc Smart'!D39,'Calc Avalanche'!D39,'Calc Snowball'!D39,'Calc Cashflow'!D39) | H33: =CHOOSE(Plan!$K$5,'Calc Smart'!E39,'Calc Avalanche'!E39,'Calc Snowball'!E39,'Calc Cashflow'!E39) | I33: =CHOOSE(Plan!$K$5,'Calc Smart'!F39,'Calc Avalanche'!F39,'Calc Snowball'!F39,'Calc Cashflow'!F39) | J33: =CHOOSE(Plan!$K$5,'Calc Smart'!G39,'Calc Avalanche'!G39,'Calc Snowball'!G39,'Calc Cashflow'!G39) | K33: =CHOOSE(Plan!$K$5,'Calc Smart'!H39,'Calc Avalanche'!H39,'Calc Snowball'!H39,'Calc Cashflow'!H39) | L33: =CHOOSE(Plan!$K$5,'Calc Smart'!I39,'Calc Avalanche'!I39,'Calc Snowball'!I39,'Calc Cashflow'!I39) | M33: =CHOOSE(Plan!$K$5,'Calc Smart'!J39,'Calc Avalanche'!J39,'Calc Snowball'!J39,'Calc Cashflow'!J39) | ... Q33: =CHOOSE(Plan!$K$5,'Calc Smart'!N39,'Calc Avalanche'!N39,'Calc Snowball'!N39,'Calc Cashflow'!N39)
B34: =EDATE(Plan!$C$6,28) | C34: =CHOOSE(Plan!$K$5,'Calc Smart'!AE40,'Calc Avalanche'!AE40,'Calc Snowball'!AE40,'Calc Cashflow'!AE40) | D34: =CHOOSE(Plan!$K$5,'Calc Smart'!AD40,'Calc Avalanche'!AD40,'Calc Snowball'!AD40,'Calc Cashflow'!AD40) | E34: =CHOOSE(Plan!$K$5,COUNTIF('Calc Smart'!C40:N40,">0"),COUNTIF('Calc Avalanche'!C40:N40,">0"),COUNTIF('Calc Snowball'!C40:N40,">0"),COUNTIF('Calc Cashflow'!C40:N40,">0")) | F34: =CHOOSE(Plan!$K$5,'Calc Smart'!C40,'Calc Avalanche'!C40,'Calc Snowball'!C40,'Calc Cashflow'!C40) | G34: =CHOOSE(Plan!$K$5,'Calc Smart'!D40,'Calc Avalanche'!D40,'Calc Snowball'!D40,'Calc Cashflow'!D40) | H34: =CHOOSE(Plan!$K$5,'Calc Smart'!E40,'Calc Avalanche'!E40,'Calc Snowball'!E40,'Calc Cashflow'!E40) | I34: =CHOOSE(Plan!$K$5,'Calc Smart'!F40,'Calc Avalanche'!F40,'Calc Snowball'!F40,'Calc Cashflow'!F40) | J34: =CHOOSE(Plan!$K$5,'Calc Smart'!G40,'Calc Avalanche'!G40,'Calc Snowball'!G40,'Calc Cashflow'!G40) | K34: =CHOOSE(Plan!$K$5,'Calc Smart'!H40,'Calc Avalanche'!H40,'Calc Snowball'!H40,'Calc Cashflow'!H40) | L34: =CHOOSE(Plan!$K$5,'Calc Smart'!I40,'Calc Avalanche'!I40,'Calc Snowball'!I40,'Calc Cashflow'!I40) | M34: =CHOOSE(Plan!$K$5,'Calc Smart'!J40,'Calc Avalanche'!J40,'Calc Snowball'!J40,'Calc Cashflow'!J40) | ... Q34: =CHOOSE(Plan!$K$5,'Calc Smart'!N40,'Calc Avalanche'!N40,'Calc Snowball'!N40,'Calc Cashflow'!N40)
B35: =EDATE(Plan!$C$6,29) | C35: =CHOOSE(Plan!$K$5,'Calc Smart'!AE41,'Calc Avalanche'!AE41,'Calc Snowball'!AE41,'Calc Cashflow'!AE41) | D35: =CHOOSE(Plan!$K$5,'Calc Smart'!AD41,'Calc Avalanche'!AD41,'Calc Snowball'!AD41,'Calc Cashflow'!AD41) | E35: =CHOOSE(Plan!$K$5,COUNTIF('Calc Smart'!C41:N41,">0"),COUNTIF('Calc Avalanche'!C41:N41,">0"),COUNTIF('Calc Snowball'!C41:N41,">0"),COUNTIF('Calc Cashflow'!C41:N41,">0")) | F35: =CHOOSE(Plan!$K$5,'Calc Smart'!C41,'Calc Avalanche'!C41,'Calc Snowball'!C41,'Calc Cashflow'!C41) | G35: =CHOOSE(Plan!$K$5,'Calc Smart'!D41,'Calc Avalanche'!D41,'Calc Snowball'!D41,'Calc Cashflow'!D41) | H35: =CHOOSE(Plan!$K$5,'Calc Smart'!E41,'Calc Avalanche'!E41,'Calc Snowball'!E41,'Calc Cashflow'!E41) | I35: =CHOOSE(Plan!$K$5,'Calc Smart'!F41,'Calc Avalanche'!F41,'Calc Snowball'!F41,'Calc Cashflow'!F41) | J35: =CHOOSE(Plan!$K$5,'Calc Smart'!G41,'Calc Avalanche'!G41,'Calc Snowball'!G41,'Calc Cashflow'!G41) | K35: =CHOOSE(Plan!$K$5,'Calc Smart'!H41,'Calc Avalanche'!H41,'Calc Snowball'!H41,'Calc Cashflow'!H41) | L35: =CHOOSE(Plan!$K$5,'Calc Smart'!I41,'Calc Avalanche'!I41,'Calc Snowball'!I41,'Calc Cashflow'!I41) | M35: =CHOOSE(Plan!$K$5,'Calc Smart'!J41,'Calc Avalanche'!J41,'Calc Snowball'!J41,'Calc Cashflow'!J41) | ... Q35: =CHOOSE(Plan!$K$5,'Calc Smart'!N41,'Calc Avalanche'!N41,'Calc Snowball'!N41,'Calc Cashflow'!N41)
B36: =EDATE(Plan!$C$6,30) | C36: =CHOOSE(Plan!$K$5,'Calc Smart'!AE42,'Calc Avalanche'!AE42,'Calc Snowball'!AE42,'Calc Cashflow'!AE42) | D36: =CHOOSE(Plan!$K$5,'Calc Smart'!AD42,'Calc Avalanche'!AD42,'Calc Snowball'!AD42,'Calc Cashflow'!AD42) | E36: =CHOOSE(Plan!$K$5,COUNTIF('Calc Smart'!C42:N42,">0"),COUNTIF('Calc Avalanche'!C42:N42,">0"),COUNTIF('Calc Snowball'!C42:N42,">0"),COUNTIF('Calc Cashflow'!C42:N42,">0")) | F36: =CHOOSE(Plan!$K$5,'Calc Smart'!C42,'Calc Avalanche'!C42,'Calc Snowball'!C42,'Calc Cashflow'!C42) | G36: =CHOOSE(Plan!$K$5,'Calc Smart'!D42,'Calc Avalanche'!D42,'Calc Snowball'!D42,'Calc Cashflow'!D42) | H36: =CHOOSE(Plan!$K$5,'Calc Smart'!E42,'Calc Avalanche'!E42,'Calc Snowball'!E42,'Calc Cashflow'!E42) | I36: =CHOOSE(Plan!$K$5,'Calc Smart'!F42,'Calc Avalanche'!F42,'Calc Snowball'!F42,'Calc Cashflow'!F42) | J36: =CHOOSE(Plan!$K$5,'Calc Smart'!G42,'Calc Avalanche'!G42,'Calc Snowball'!G42,'Calc Cashflow'!G42) | K36: =CHOOSE(Plan!$K$5,'Calc Smart'!H42,'Calc Avalanche'!H42,'Calc Snowball'!H42,'Calc Cashflow'!H42) | L36: =CHOOSE(Plan!$K$5,'Calc Smart'!I42,'Calc Avalanche'!I42,'Calc Snowball'!I42,'Calc Cashflow'!I42) | M36: =CHOOSE(Plan!$K$5,'Calc Smart'!J42,'Calc Avalanche'!J42,'Calc Snowball'!J42,'Calc Cashflow'!J42) | ... Q36: =CHOOSE(Plan!$K$5,'Calc Smart'!N42,'Calc Avalanche'!N42,'Calc Snowball'!N42,'Calc Cashflow'!N42)
B37: =EDATE(Plan!$C$6,31) | C37: =CHOOSE(Plan!$K$5,'Calc Smart'!AE43,'Calc Avalanche'!AE43,'Calc Snowball'!AE43,'Calc Cashflow'!AE43) | D37: =CHOOSE(Plan!$K$5,'Calc Smart'!AD43,'Calc Avalanche'!AD43,'Calc Snowball'!AD43,'Calc Cashflow'!AD43) | E37: =CHOOSE(Plan!$K$5,COUNTIF('Calc Smart'!C43:N43,">0"),COUNTIF('Calc Avalanche'!C43:N43,">0"),COUNTIF('Calc Snowball'!C43:N43,">0"),COUNTIF('Calc Cashflow'!C43:N43,">0")) | F37: =CHOOSE(Plan!$K$5,'Calc Smart'!C43,'Calc Avalanche'!C43,'Calc Snowball'!C43,'Calc Cashflow'!C43) | G37: =CHOOSE(Plan!$K$5,'Calc Smart'!D43,'Calc Avalanche'!D43,'Calc Snowball'!D43,'Calc Cashflow'!D43) | H37: =CHOOSE(Plan!$K$5,'Calc Smart'!E43,'Calc Avalanche'!E43,'Calc Snowball'!E43,'Calc Cashflow'!E43) | I37: =CHOOSE(Plan!$K$5,'Calc Smart'!F43,'Calc Avalanche'!F43,'Calc Snowball'!F43,'Calc Cashflow'!F43) | J37: =CHOOSE(Plan!$K$5,'Calc Smart'!G43,'Calc Avalanche'!G43,'Calc Snowball'!G43,'Calc Cashflow'!G43) | K37: =CHOOSE(Plan!$K$5,'Calc Smart'!H43,'Calc Avalanche'!H43,'Calc Snowball'!H43,'Calc Cashflow'!H43) | L37: =CHOOSE(Plan!$K$5,'Calc Smart'!I43,'Calc Avalanche'!I43,'Calc Snowball'!I43,'Calc Cashflow'!I43) | M37: =CHOOSE(Plan!$K$5,'Calc Smart'!J43,'Calc Avalanche'!J43,'Calc Snowball'!J43,'Calc Cashflow'!J43) | ... Q37: =CHOOSE(Plan!$K$5,'Calc Smart'!N43,'Calc Avalanche'!N43,'Calc Snowball'!N43,'Calc Cashflow'!N43)
B38: =EDATE(Plan!$C$6,32) | C38: =CHOOSE(Plan!$K$5,'Calc Smart'!AE44,'Calc Avalanche'!AE44,'Calc Snowball'!AE44,'Calc Cashflow'!AE44) | D38: =CHOOSE(Plan!$K$5,'Calc Smart'!AD44,'Calc Avalanche'!AD44,'Calc Snowball'!AD44,'Calc Cashflow'!AD44) | E38: =CHOOSE(Plan!$K$5,COUNTIF('Calc Smart'!C44:N44,">0"),COUNTIF('Calc Avalanche'!C44:N44,">0"),COUNTIF('Calc Snowball'!C44:N44,">0"),COUNTIF('Calc Cashflow'!C44:N44,">0")) | F38: =CHOOSE(Plan!$K$5,'Calc Smart'!C44,'Calc Avalanche'!C44,'Calc Snowball'!C44,'Calc Cashflow'!C44) | G38: =CHOOSE(Plan!$K$5,'Calc Smart'!D44,'Calc Avalanche'!D44,'Calc Snowball'!D44,'Calc Cashflow'!D44) | H38: =CHOOSE(Plan!$K$5,'Calc Smart'!E44,'Calc Avalanche'!E44,'Calc Snowball'!E44,'Calc Cashflow'!E44) | I38: =CHOOSE(Plan!$K$5,'Calc Smart'!F44,'Calc Avalanche'!F44,'Calc Snowball'!F44,'Calc Cashflow'!F44) | J38: =CHOOSE(Plan!$K$5,'Calc Smart'!G44,'Calc Avalanche'!G44,'Calc Snowball'!G44,'Calc Cashflow'!G44) | K38: =CHOOSE(Plan!$K$5,'Calc Smart'!H44,'Calc Avalanche'!H44,'Calc Snowball'!H44,'Calc Cashflow'!H44) | L38: =CHOOSE(Plan!$K$5,'Calc Smart'!I44,'Calc Avalanche'!I44,'Calc Snowball'!I44,'Calc Cashflow'!I44) | M38: =CHOOSE(Plan!$K$5,'Calc Smart'!J44,'Calc Avalanche'!J44,'Calc Snowball'!J44,'Calc Cashflow'!J44) | ... Q38: =CHOOSE(Plan!$K$5,'Calc Smart'!N44,'Calc Avalanche'!N44,'Calc Snowball'!N44,'Calc Cashflow'!N44)
B39: =EDATE(Plan!$C$6,33) | C39: =CHOOSE(Plan!$K$5,'Calc Smart'!AE45,'Calc Avalanche'!AE45,'Calc Snowball'!AE45,'Calc Cashflow'!AE45) | D39: =CHOOSE(Plan!$K$5,'Calc Smart'!AD45,'Calc Avalanche'!AD45,'Calc Snowball'!AD45,'Calc Cashflow'!AD45) | E39: =CHOOSE(Plan!$K$5,COUNTIF('Calc Smart'!C45:N45,">0"),COUNTIF('Calc Avalanche'!C45:N45,">0"),COUNTIF('Calc Snowball'!C45:N45,">0"),COUNTIF('Calc Cashflow'!C45:N45,">0")) | F39: =CHOOSE(Plan!$K$5,'Calc Smart'!C45,'Calc Avalanche'!C45,'Calc Snowball'!C45,'Calc Cashflow'!C45) | G39: =CHOOSE(Plan!$K$5,'Calc Smart'!D45,'Calc Avalanche'!D45,'Calc Snowball'!D45,'Calc Cashflow'!D45) | H39: =CHOOSE(Plan!$K$5,'Calc Smart'!E45,'Calc Avalanche'!E45,'Calc Snowball'!E45,'Calc Cashflow'!E45) | I39: =CHOOSE(Plan!$K$5,'Calc Smart'!F45,'Calc Avalanche'!F45,'Calc Snowball'!F45,'Calc Cashflow'!F45) | J39: =CHOOSE(Plan!$K$5,'Calc Smart'!G45,'Calc Avalanche'!G45,'Calc Snowball'!G45,'Calc Cashflow'!G45) | K39: =CHOOSE(Plan!$K$5,'Calc Smart'!H45,'Calc Avalanche'!H45,'Calc Snowball'!H45,'Calc Cashflow'!H45) | L39: =CHOOSE(Plan!$K$5,'Calc Smart'!I45,'Calc Avalanche'!I45,'Calc Snowball'!I45,'Calc Cashflow'!I45) | M39: =CHOOSE(Plan!$K$5,'Calc Smart'!J45,'Calc Avalanche'!J45,'Calc Snowball'!J45,'Calc Cashflow'!J45) | ... Q39: =CHOOSE(Plan!$K$5,'Calc Smart'!N45,'Calc Avalanche'!N45,'Calc Snowball'!N45,'Calc Cashflow'!N45)
B40: =EDATE(Plan!$C$6,34) | C40: =CHOOSE(Plan!$K$5,'Calc Smart'!AE46,'Calc Avalanche'!AE46,'Calc Snowball'!AE46,'Calc Cashflow'!AE46) | D40: =CHOOSE(Plan!$K$5,'Calc Smart'!AD46,'Calc Avalanche'!AD46,'Calc Snowball'!AD46,'Calc Cashflow'!AD46) | E40: =CHOOSE(Plan!$K$5,COUNTIF('Calc Smart'!C46:N46,">0"),COUNTIF('Calc Avalanche'!C46:N46,">0"),COUNTIF('Calc Snowball'!C46:N46,">0"),COUNTIF('Calc Cashflow'!C46:N46,">0")) | F40: =CHOOSE(Plan!$K$5,'Calc Smart'!C46,'Calc Avalanche'!C46,'Calc Snowball'!C46,'Calc Cashflow'!C46) | G40: =CHOOSE(Plan!$K$5,'Calc Smart'!D46,'Calc Avalanche'!D46,'Calc Snowball'!D46,'Calc Cashflow'!D46) | H40: =CHOOSE(Plan!$K$5,'Calc Smart'!E46,'Calc Avalanche'!E46,'Calc Snowball'!E46,'Calc Cashflow'!E46) | I40: =CHOOSE(Plan!$K$5,'Calc Smart'!F46,'Calc Avalanche'!F46,'Calc Snowball'!F46,'Calc Cashflow'!F46) | J40: =CHOOSE(Plan!$K$5,'Calc Smart'!G46,'Calc Avalanche'!G46,'Calc Snowball'!G46,'Calc Cashflow'!G46) | K40: =CHOOSE(Plan!$K$5,'Calc Smart'!H46,'Calc Avalanche'!H46,'Calc Snowball'!H46,'Calc Cashflow'!H46) | L40: =CHOOSE(Plan!$K$5,'Calc Smart'!I46,'Calc Avalanche'!I46,'Calc Snowball'!I46,'Calc Cashflow'!I46) | M40: =CHOOSE(Plan!$K$5,'Calc Smart'!J46,'Calc Avalanche'!J46,'Calc Snowball'!J46,'Calc Cashflow'!J46) | ... Q40: =CHOOSE(Plan!$K$5,'Calc Smart'!N46,'Calc Avalanche'!N46,'Calc Snowball'!N46,'Calc Cashflow'!N46)
B41: =EDATE(Plan!$C$6,35) | C41: =CHOOSE(Plan!$K$5,'Calc Smart'!AE47,'Calc Avalanche'!AE47,'Calc Snowball'!AE47,'Calc Cashflow'!AE47) | D41: =CHOOSE(Plan!$K$5,'Calc Smart'!AD47,'Calc Avalanche'!AD47,'Calc Snowball'!AD47,'Calc Cashflow'!AD47) | E41: =CHOOSE(Plan!$K$5,COUNTIF('Calc Smart'!C47:N47,">0"),COUNTIF('Calc Avalanche'!C47:N47,">0"),COUNTIF('Calc Snowball'!C47:N47,">0"),COUNTIF('Calc Cashflow'!C47:N47,">0")) | F41: =CHOOSE(Plan!$K$5,'Calc Smart'!C47,'Calc Avalanche'!C47,'Calc Snowball'!C47,'Calc Cashflow'!C47) | G41: =CHOOSE(Plan!$K$5,'Calc Smart'!D47,'Calc Avalanche'!D47,'Calc Snowball'!D47,'Calc Cashflow'!D47) | H41: =CHOOSE(Plan!$K$5,'Calc Smart'!E47,'Calc Avalanche'!E47,'Calc Snowball'!E47,'Calc Cashflow'!E47) | I41: =CHOOSE(Plan!$K$5,'Calc Smart'!F47,'Calc Avalanche'!F47,'Calc Snowball'!F47,'Calc Cashflow'!F47) | J41: =CHOOSE(Plan!$K$5,'Calc Smart'!G47,'Calc Avalanche'!G47,'Calc Snowball'!G47,'Calc Cashflow'!G47) | K41: =CHOOSE(Plan!$K$5,'Calc Smart'!H47,'Calc Avalanche'!H47,'Calc Snowball'!H47,'Calc Cashflow'!H47) | L41: =CHOOSE(Plan!$K$5,'Calc Smart'!I47,'Calc Avalanche'!I47,'Calc Snowball'!I47,'Calc Cashflow'!I47) | M41: =CHOOSE(Plan!$K$5,'Calc Smart'!J47,'Calc Avalanche'!J47,'Calc Snowball'!J47,'Calc Cashflow'!J47) | ... Q41: =CHOOSE(Plan!$K$5,'Calc Smart'!N47,'Calc Avalanche'!N47,'Calc Snowball'!N47,'Calc Cashflow'!N47)
B42: =EDATE(Plan!$C$6,36) | C42: =CHOOSE(Plan!$K$5,'Calc Smart'!AE48,'Calc Avalanche'!AE48,'Calc Snowball'!AE48,'Calc Cashflow'!AE48) | D42: =CHOOSE(Plan!$K$5,'Calc Smart'!AD48,'Calc Avalanche'!AD48,'Calc Snowball'!AD48,'Calc Cashflow'!AD48) | E42: =CHOOSE(Plan!$K$5,COUNTIF('Calc Smart'!C48:N48,">0"),COUNTIF('Calc Avalanche'!C48:N48,">0"),COUNTIF('Calc Snowball'!C48:N48,">0"),COUNTIF('Calc Cashflow'!C48:N48,">0")) | F42: =CHOOSE(Plan!$K$5,'Calc Smart'!C48,'Calc Avalanche'!C48,'Calc Snowball'!C48,'Calc Cashflow'!C48) | G42: =CHOOSE(Plan!$K$5,'Calc Smart'!D48,'Calc Avalanche'!D48,'Calc Snowball'!D48,'Calc Cashflow'!D48) | H42: =CHOOSE(Plan!$K$5,'Calc Smart'!E48,'Calc Avalanche'!E48,'Calc Snowball'!E48,'Calc Cashflow'!E48) | I42: =CHOOSE(Plan!$K$5,'Calc Smart'!F48,'Calc Avalanche'!F48,'Calc Snowball'!F48,'Calc Cashflow'!F48) | J42: =CHOOSE(Plan!$K$5,'Calc Smart'!G48,'Calc Avalanche'!G48,'Calc Snowball'!G48,'Calc Cashflow'!G48) | K42: =CHOOSE(Plan!$K$5,'Calc Smart'!H48,'Calc Avalanche'!H48,'Calc Snowball'!H48,'Calc Cashflow'!H48) | L42: =CHOOSE(Plan!$K$5,'Calc Smart'!I48,'Calc Avalanche'!I48,'Calc Snowball'!I48,'Calc Cashflow'!I48) | M42: =CHOOSE(Plan!$K$5,'Calc Smart'!J48,'Calc Avalanche'!J48,'Calc Snowball'!J48,'Calc Cashflow'!J48) | ... Q42: =CHOOSE(Plan!$K$5,'Calc Smart'!N48,'Calc Avalanche'!N48,'Calc Snowball'!N48,'Calc Cashflow'!N48)
B43: =EDATE(Plan!$C$6,37) | C43: =CHOOSE(Plan!$K$5,'Calc Smart'!AE49,'Calc Avalanche'!AE49,'Calc Snowball'!AE49,'Calc Cashflow'!AE49) | D43: =CHOOSE(Plan!$K$5,'Calc Smart'!AD49,'Calc Avalanche'!AD49,'Calc Snowball'!AD49,'Calc Cashflow'!AD49) | E43: =CHOOSE(Plan!$K$5,COUNTIF('Calc Smart'!C49:N49,">0"),COUNTIF('Calc Avalanche'!C49:N49,">0"),COUNTIF('Calc Snowball'!C49:N49,">0"),COUNTIF('Calc Cashflow'!C49:N49,">0")) | F43: =CHOOSE(Plan!$K$5,'Calc Smart'!C49,'Calc Avalanche'!C49,'Calc Snowball'!C49,'Calc Cashflow'!C49) | G43: =CHOOSE(Plan!$K$5,'Calc Smart'!D49,'Calc Avalanche'!D49,'Calc Snowball'!D49,'Calc Cashflow'!D49) | H43: =CHOOSE(Plan!$K$5,'Calc Smart'!E49,'Calc Avalanche'!E49,'Calc Snowball'!E49,'Calc Cashflow'!E49) | I43: =CHOOSE(Plan!$K$5,'Calc Smart'!F49,'Calc Avalanche'!F49,'Calc Snowball'!F49,'Calc Cashflow'!F49) | J43: =CHOOSE(Plan!$K$5,'Calc Smart'!G49,'Calc Avalanche'!G49,'Calc Snowball'!G49,'Calc Cashflow'!G49) | K43: =CHOOSE(Plan!$K$5,'Calc Smart'!H49,'Calc Avalanche'!H49,'Calc Snowball'!H49,'Calc Cashflow'!H49) | L43: =CHOOSE(Plan!$K$5,'Calc Smart'!I49,'Calc Avalanche'!I49,'Calc Snowball'!I49,'Calc Cashflow'!I49) | M43: =CHOOSE(Plan!$K$5,'Calc Smart'!J49,'Calc Avalanche'!J49,'Calc Snowball'!J49,'Calc Cashflow'!J49) | ... Q43: =CHOOSE(Plan!$K$5,'Calc Smart'!N49,'Calc Avalanche'!N49,'Calc Snowball'!N49,'Calc Cashflow'!N49)
B44: =EDATE(Plan!$C$6,38) | C44: =CHOOSE(Plan!$K$5,'Calc Smart'!AE50,'Calc Avalanche'!AE50,'Calc Snowball'!AE50,'Calc Cashflow'!AE50) | D44: =CHOOSE(Plan!$K$5,'Calc Smart'!AD50,'Calc Avalanche'!AD50,'Calc Snowball'!AD50,'Calc Cashflow'!AD50) | E44: =CHOOSE(Plan!$K$5,COUNTIF('Calc Smart'!C50:N50,">0"),COUNTIF('Calc Avalanche'!C50:N50,">0"),COUNTIF('Calc Snowball'!C50:N50,">0"),COUNTIF('Calc Cashflow'!C50:N50,">0")) | F44: =CHOOSE(Plan!$K$5,'Calc Smart'!C50,'Calc Avalanche'!C50,'Calc Snowball'!C50,'Calc Cashflow'!C50) | G44: =CHOOSE(Plan!$K$5,'Calc Smart'!D50,'Calc Avalanche'!D50,'Calc Snowball'!D50,'Calc Cashflow'!D50) | H44: =CHOOSE(Plan!$K$5,'Calc Smart'!E50,'Calc Avalanche'!E50,'Calc Snowball'!E50,'Calc Cashflow'!E50) | I44: =CHOOSE(Plan!$K$5,'Calc Smart'!F50,'Calc Avalanche'!F50,'Calc Snowball'!F50,'Calc Cashflow'!F50) | J44: =CHOOSE(Plan!$K$5,'Calc Smart'!G50,'Calc Avalanche'!G50,'Calc Snowball'!G50,'Calc Cashflow'!G50) | K44: =CHOOSE(Plan!$K$5,'Calc Smart'!H50,'Calc Avalanche'!H50,'Calc Snowball'!H50,'Calc Cashflow'!H50) | L44: =CHOOSE(Plan!$K$5,'Calc Smart'!I50,'Calc Avalanche'!I50,'Calc Snowball'!I50,'Calc Cashflow'!I50) | M44: =CHOOSE(Plan!$K$5,'Calc Smart'!J50,'Calc Avalanche'!J50,'Calc Snowball'!J50,'Calc Cashflow'!J50) | ... Q44: =CHOOSE(Plan!$K$5,'Calc Smart'!N50,'Calc Avalanche'!N50,'Calc Snowball'!N50,'Calc Cashflow'!N50)
B45: =EDATE(Plan!$C$6,39) | C45: =CHOOSE(Plan!$K$5,'Calc Smart'!AE51,'Calc Avalanche'!AE51,'Calc Snowball'!AE51,'Calc Cashflow'!AE51) | D45: =CHOOSE(Plan!$K$5,'Calc Smart'!AD51,'Calc Avalanche'!AD51,'Calc Snowball'!AD51,'Calc Cashflow'!AD51) | E45: =CHOOSE(Plan!$K$5,COUNTIF('Calc Smart'!C51:N51,">0"),COUNTIF('Calc Avalanche'!C51:N51,">0"),COUNTIF('Calc Snowball'!C51:N51,">0"),COUNTIF('Calc Cashflow'!C51:N51,">0")) | F45: =CHOOSE(Plan!$K$5,'Calc Smart'!C51,'Calc Avalanche'!C51,'Calc Snowball'!C51,'Calc Cashflow'!C51) | G45: =CHOOSE(Plan!$K$5,'Calc Smart'!D51,'Calc Avalanche'!D51,'Calc Snowball'!D51,'Calc Cashflow'!D51) | H45: =CHOOSE(Plan!$K$5,'Calc Smart'!E51,'Calc Avalanche'!E51,'Calc Snowball'!E51,'Calc Cashflow'!E51) | I45: =CHOOSE(Plan!$K$5,'Calc Smart'!F51,'Calc Avalanche'!F51,'Calc Snowball'!F51,'Calc Cashflow'!F51) | J45: =CHOOSE(Plan!$K$5,'Calc Smart'!G51,'Calc Avalanche'!G51,'Calc Snowball'!G51,'Calc Cashflow'!G51) | K45: =CHOOSE(Plan!$K$5,'Calc Smart'!H51,'Calc Avalanche'!H51,'Calc Snowball'!H51,'Calc Cashflow'!H51) | L45: =CHOOSE(Plan!$K$5,'Calc Smart'!I51,'Calc Avalanche'!I51,'Calc Snowball'!I51,'Calc Cashflow'!I51) | M45: =CHOOSE(Plan!$K$5,'Calc Smart'!J51,'Calc Avalanche'!J51,'Calc Snowball'!J51,'Calc Cashflow'!J51) | ... Q45: =CHOOSE(Plan!$K$5,'Calc Smart'!N51,'Calc Avalanche'!N51,'Calc Snowball'!N51,'Calc Cashflow'!N51)
B46: =EDATE(Plan!$C$6,40) | C46: =CHOOSE(Plan!$K$5,'Calc Smart'!AE52,'Calc Avalanche'!AE52,'Calc Snowball'!AE52,'Calc Cashflow'!AE52) | D46: =CHOOSE(Plan!$K$5,'Calc Smart'!AD52,'Calc Avalanche'!AD52,'Calc Snowball'!AD52,'Calc Cashflow'!AD52) | E46: =CHOOSE(Plan!$K$5,COUNTIF('Calc Smart'!C52:N52,">0"),COUNTIF('Calc Avalanche'!C52:N52,">0"),COUNTIF('Calc Snowball'!C52:N52,">0"),COUNTIF('Calc Cashflow'!C52:N52,">0")) | F46: =CHOOSE(Plan!$K$5,'Calc Smart'!C52,'Calc Avalanche'!C52,'Calc Snowball'!C52,'Calc Cashflow'!C52) | G46: =CHOOSE(Plan!$K$5,'Calc Smart'!D52,'Calc Avalanche'!D52,'Calc Snowball'!D52,'Calc Cashflow'!D52) | H46: =CHOOSE(Plan!$K$5,'Calc Smart'!E52,'Calc Avalanche'!E52,'Calc Snowball'!E52,'Calc Cashflow'!E52) | I46: =CHOOSE(Plan!$K$5,'Calc Smart'!F52,'Calc Avalanche'!F52,'Calc Snowball'!F52,'Calc Cashflow'!F52) | J46: =CHOOSE(Plan!$K$5,'Calc Smart'!G52,'Calc Avalanche'!G52,'Calc Snowball'!G52,'Calc Cashflow'!G52) | K46: =CHOOSE(Plan!$K$5,'Calc Smart'!H52,'Calc Avalanche'!H52,'Calc Snowball'!H52,'Calc Cashflow'!H52) | L46: =CHOOSE(Plan!$K$5,'Calc Smart'!I52,'Calc Avalanche'!I52,'Calc Snowball'!I52,'Calc Cashflow'!I52) | M46: =CHOOSE(Plan!$K$5,'Calc Smart'!J52,'Calc Avalanche'!J52,'Calc Snowball'!J52,'Calc Cashflow'!J52) | ... Q46: =CHOOSE(Plan!$K$5,'Calc Smart'!N52,'Calc Avalanche'!N52,'Calc Snowball'!N52,'Calc Cashflow'!N52)
B47: =EDATE(Plan!$C$6,41) | C47: =CHOOSE(Plan!$K$5,'Calc Smart'!AE53,'Calc Avalanche'!AE53,'Calc Snowball'!AE53,'Calc Cashflow'!AE53) | D47: =CHOOSE(Plan!$K$5,'Calc Smart'!AD53,'Calc Avalanche'!AD53,'Calc Snowball'!AD53,'Calc Cashflow'!AD53) | E47: =CHOOSE(Plan!$K$5,COUNTIF('Calc Smart'!C53:N53,">0"),COUNTIF('Calc Avalanche'!C53:N53,">0"),COUNTIF('Calc Snowball'!C53:N53,">0"),COUNTIF('Calc Cashflow'!C53:N53,">0")) | F47: =CHOOSE(Plan!$K$5,'Calc Smart'!C53,'Calc Avalanche'!C53,'Calc Snowball'!C53,'Calc Cashflow'!C53) | G47: =CHOOSE(Plan!$K$5,'Calc Smart'!D53,'Calc Avalanche'!D53,'Calc Snowball'!D53,'Calc Cashflow'!D53) | H47: =CHOOSE(Plan!$K$5,'Calc Smart'!E53,'Calc Avalanche'!E53,'Calc Snowball'!E53,'Calc Cashflow'!E53) | I47: =CHOOSE(Plan!$K$5,'Calc Smart'!F53,'Calc Avalanche'!F53,'Calc Snowball'!F53,'Calc Cashflow'!F53) | J47: =CHOOSE(Plan!$K$5,'Calc Smart'!G53,'Calc Avalanche'!G53,'Calc Snowball'!G53,'Calc Cashflow'!G53) | K47: =CHOOSE(Plan!$K$5,'Calc Smart'!H53,'Calc Avalanche'!H53,'Calc Snowball'!H53,'Calc Cashflow'!H53) | L47: =CHOOSE(Plan!$K$5,'Calc Smart'!I53,'Calc Avalanche'!I53,'Calc Snowball'!I53,'Calc Cashflow'!I53) | M47: =CHOOSE(Plan!$K$5,'Calc Smart'!J53,'Calc Avalanche'!J53,'Calc Snowball'!J53,'Calc Cashflow'!J53) | ... Q47: =CHOOSE(Plan!$K$5,'Calc Smart'!N53,'Calc Avalanche'!N53,'Calc Snowball'!N53,'Calc Cashflow'!N53)
B48: =EDATE(Plan!$C$6,42) | C48: =CHOOSE(Plan!$K$5,'Calc Smart'!AE54,'Calc Avalanche'!AE54,'Calc Snowball'!AE54,'Calc Cashflow'!AE54) | D48: =CHOOSE(Plan!$K$5,'Calc Smart'!AD54,'Calc Avalanche'!AD54,'Calc Snowball'!AD54,'Calc Cashflow'!AD54) | E48: =CHOOSE(Plan!$K$5,COUNTIF('Calc Smart'!C54:N54,">0"),COUNTIF('Calc Avalanche'!C54:N54,">0"),COUNTIF('Calc Snowball'!C54:N54,">0"),COUNTIF('Calc Cashflow'!C54:N54,">0")) | F48: =CHOOSE(Plan!$K$5,'Calc Smart'!C54,'Calc Avalanche'!C54,'Calc Snowball'!C54,'Calc Cashflow'!C54) | G48: =CHOOSE(Plan!$K$5,'Calc Smart'!D54,'Calc Avalanche'!D54,'Calc Snowball'!D54,'Calc Cashflow'!D54) | H48: =CHOOSE(Plan!$K$5,'Calc Smart'!E54,'Calc Avalanche'!E54,'Calc Snowball'!E54,'Calc Cashflow'!E54) | I48: =CHOOSE(Plan!$K$5,'Calc Smart'!F54,'Calc Avalanche'!F54,'Calc Snowball'!F54,'Calc Cashflow'!F54) | J48: =CHOOSE(Plan!$K$5,'Calc Smart'!G54,'Calc Avalanche'!G54,'Calc Snowball'!G54,'Calc Cashflow'!G54) | K48: =CHOOSE(Plan!$K$5,'Calc Smart'!H54,'Calc Avalanche'!H54,'Calc Snowball'!H54,'Calc Cashflow'!H54) | L48: =CHOOSE(Plan!$K$5,'Calc Smart'!I54,'Calc Avalanche'!I54,'Calc Snowball'!I54,'Calc Cashflow'!I54) | M48: =CHOOSE(Plan!$K$5,'Calc Smart'!J54,'Calc Avalanche'!J54,'Calc Snowball'!J54,'Calc Cashflow'!J54) | ... Q48: =CHOOSE(Plan!$K$5,'Calc Smart'!N54,'Calc Avalanche'!N54,'Calc Snowball'!N54,'Calc Cashflow'!N54)
B49: =EDATE(Plan!$C$6,43) | C49: =CHOOSE(Plan!$K$5,'Calc Smart'!AE55,'Calc Avalanche'!AE55,'Calc Snowball'!AE55,'Calc Cashflow'!AE55) | D49: =CHOOSE(Plan!$K$5,'Calc Smart'!AD55,'Calc Avalanche'!AD55,'Calc Snowball'!AD55,'Calc Cashflow'!AD55) | E49: =CHOOSE(Plan!$K$5,COUNTIF('Calc Smart'!C55:N55,">0"),COUNTIF('Calc Avalanche'!C55:N55,">0"),COUNTIF('Calc Snowball'!C55:N55,">0"),COUNTIF('Calc Cashflow'!C55:N55,">0")) | F49: =CHOOSE(Plan!$K$5,'Calc Smart'!C55,'Calc Avalanche'!C55,'Calc Snowball'!C55,'Calc Cashflow'!C55) | G49: =CHOOSE(Plan!$K$5,'Calc Smart'!D55,'Calc Avalanche'!D55,'Calc Snowball'!D55,'Calc Cashflow'!D55) | H49: =CHOOSE(Plan!$K$5,'Calc Smart'!E55,'Calc Avalanche'!E55,'Calc Snowball'!E55,'Calc Cashflow'!E55) | I49: =CHOOSE(Plan!$K$5,'Calc Smart'!F55,'Calc Avalanche'!F55,'Calc Snowball'!F55,'Calc Cashflow'!F55) | J49: =CHOOSE(Plan!$K$5,'Calc Smart'!G55,'Calc Avalanche'!G55,'Calc Snowball'!G55,'Calc Cashflow'!G55) | K49: =CHOOSE(Plan!$K$5,'Calc Smart'!H55,'Calc Avalanche'!H55,'Calc Snowball'!H55,'Calc Cashflow'!H55) | L49: =CHOOSE(Plan!$K$5,'Calc Smart'!I55,'Calc Avalanche'!I55,'Calc Snowball'!I55,'Calc Cashflow'!I55) | M49: =CHOOSE(Plan!$K$5,'Calc Smart'!J55,'Calc Avalanche'!J55,'Calc Snowball'!J55,'Calc Cashflow'!J55) | ... Q49: =CHOOSE(Plan!$K$5,'Calc Smart'!N55,'Calc Avalanche'!N55,'Calc Snowball'!N55,'Calc Cashflow'!N55)
B50: =EDATE(Plan!$C$6,44) | C50: =CHOOSE(Plan!$K$5,'Calc Smart'!AE56,'Calc Avalanche'!AE56,'Calc Snowball'!AE56,'Calc Cashflow'!AE56) | D50: =CHOOSE(Plan!$K$5,'Calc Smart'!AD56,'Calc Avalanche'!AD56,'Calc Snowball'!AD56,'Calc Cashflow'!AD56) | E50: =CHOOSE(Plan!$K$5,COUNTIF('Calc Smart'!C56:N56,">0"),COUNTIF('Calc Avalanche'!C56:N56,">0"),COUNTIF('Calc Snowball'!C56:N56,">0"),COUNTIF('Calc Cashflow'!C56:N56,">0")) | F50: =CHOOSE(Plan!$K$5,'Calc Smart'!C56,'Calc Avalanche'!C56,'Calc Snowball'!C56,'Calc Cashflow'!C56) | G50: =CHOOSE(Plan!$K$5,'Calc Smart'!D56,'Calc Avalanche'!D56,'Calc Snowball'!D56,'Calc Cashflow'!D56) | H50: =CHOOSE(Plan!$K$5,'Calc Smart'!E56,'Calc Avalanche'!E56,'Calc Snowball'!E56,'Calc Cashflow'!E56) | I50: =CHOOSE(Plan!$K$5,'Calc Smart'!F56,'Calc Avalanche'!F56,'Calc Snowball'!F56,'Calc Cashflow'!F56) | J50: =CHOOSE(Plan!$K$5,'Calc Smart'!G56,'Calc Avalanche'!G56,'Calc Snowball'!G56,'Calc Cashflow'!G56) | K50: =CHOOSE(Plan!$K$5,'Calc Smart'!H56,'Calc Avalanche'!H56,'Calc Snowball'!H56,'Calc Cashflow'!H56) | L50: =CHOOSE(Plan!$K$5,'Calc Smart'!I56,'Calc Avalanche'!I56,'Calc Snowball'!I56,'Calc Cashflow'!I56) | M50: =CHOOSE(Plan!$K$5,'Calc Smart'!J56,'Calc Avalanche'!J56,'Calc Snowball'!J56,'Calc Cashflow'!J56) | ... Q50: =CHOOSE(Plan!$K$5,'Calc Smart'!N56,'Calc Avalanche'!N56,'Calc Snowball'!N56,'Calc Cashflow'!N56)
B51: =EDATE(Plan!$C$6,45) | C51: =CHOOSE(Plan!$K$5,'Calc Smart'!AE57,'Calc Avalanche'!AE57,'Calc Snowball'!AE57,'Calc Cashflow'!AE57) | D51: =CHOOSE(Plan!$K$5,'Calc Smart'!AD57,'Calc Avalanche'!AD57,'Calc Snowball'!AD57,'Calc Cashflow'!AD57) | E51: =CHOOSE(Plan!$K$5,COUNTIF('Calc Smart'!C57:N57,">0"),COUNTIF('Calc Avalanche'!C57:N57,">0"),COUNTIF('Calc Snowball'!C57:N57,">0"),COUNTIF('Calc Cashflow'!C57:N57,">0")) | F51: =CHOOSE(Plan!$K$5,'Calc Smart'!C57,'Calc Avalanche'!C57,'Calc Snowball'!C57,'Calc Cashflow'!C57) | G51: =CHOOSE(Plan!$K$5,'Calc Smart'!D57,'Calc Avalanche'!D57,'Calc Snowball'!D57,'Calc Cashflow'!D57) | H51: =CHOOSE(Plan!$K$5,'Calc Smart'!E57,'Calc Avalanche'!E57,'Calc Snowball'!E57,'Calc Cashflow'!E57) | I51: =CHOOSE(Plan!$K$5,'Calc Smart'!F57,'Calc Avalanche'!F57,'Calc Snowball'!F57,'Calc Cashflow'!F57) | J51: =CHOOSE(Plan!$K$5,'Calc Smart'!G57,'Calc Avalanche'!G57,'Calc Snowball'!G57,'Calc Cashflow'!G57) | K51: =CHOOSE(Plan!$K$5,'Calc Smart'!H57,'Calc Avalanche'!H57,'Calc Snowball'!H57,'Calc Cashflow'!H57) | L51: =CHOOSE(Plan!$K$5,'Calc Smart'!I57,'Calc Avalanche'!I57,'Calc Snowball'!I57,'Calc Cashflow'!I57) | M51: =CHOOSE(Plan!$K$5,'Calc Smart'!J57,'Calc Avalanche'!J57,'Calc Snowball'!J57,'Calc Cashflow'!J57) | ... Q51: =CHOOSE(Plan!$K$5,'Calc Smart'!N57,'Calc Avalanche'!N57,'Calc Snowball'!N57,'Calc Cashflow'!N57)
B52: =EDATE(Plan!$C$6,46) | C52: =CHOOSE(Plan!$K$5,'Calc Smart'!AE58,'Calc Avalanche'!AE58,'Calc Snowball'!AE58,'Calc Cashflow'!AE58) | D52: =CHOOSE(Plan!$K$5,'Calc Smart'!AD58,'Calc Avalanche'!AD58,'Calc Snowball'!AD58,'Calc Cashflow'!AD58) | E52: =CHOOSE(Plan!$K$5,COUNTIF('Calc Smart'!C58:N58,">0"),COUNTIF('Calc Avalanche'!C58:N58,">0"),COUNTIF('Calc Snowball'!C58:N58,">0"),COUNTIF('Calc Cashflow'!C58:N58,">0")) | F52: =CHOOSE(Plan!$K$5,'Calc Smart'!C58,'Calc Avalanche'!C58,'Calc Snowball'!C58,'Calc Cashflow'!C58) | G52: =CHOOSE(Plan!$K$5,'Calc Smart'!D58,'Calc Avalanche'!D58,'Calc Snowball'!D58,'Calc Cashflow'!D58) | H52: =CHOOSE(Plan!$K$5,'Calc Smart'!E58,'Calc Avalanche'!E58,'Calc Snowball'!E58,'Calc Cashflow'!E58) | I52: =CHOOSE(Plan!$K$5,'Calc Smart'!F58,'Calc Avalanche'!F58,'Calc Snowball'!F58,'Calc Cashflow'!F58) | J52: =CHOOSE(Plan!$K$5,'Calc Smart'!G58,'Calc Avalanche'!G58,'Calc Snowball'!G58,'Calc Cashflow'!G58) | K52: =CHOOSE(Plan!$K$5,'Calc Smart'!H58,'Calc Avalanche'!H58,'Calc Snowball'!H58,'Calc Cashflow'!H58) | L52: =CHOOSE(Plan!$K$5,'Calc Smart'!I58,'Calc Avalanche'!I58,'Calc Snowball'!I58,'Calc Cashflow'!I58) | M52: =CHOOSE(Plan!$K$5,'Calc Smart'!J58,'Calc Avalanche'!J58,'Calc Snowball'!J58,'Calc Cashflow'!J58) | ... Q52: =CHOOSE(Plan!$K$5,'Calc Smart'!N58,'Calc Avalanche'!N58,'Calc Snowball'!N58,'Calc Cashflow'!N58)
B53: =EDATE(Plan!$C$6,47) | C53: =CHOOSE(Plan!$K$5,'Calc Smart'!AE59,'Calc Avalanche'!AE59,'Calc Snowball'!AE59,'Calc Cashflow'!AE59) | D53: =CHOOSE(Plan!$K$5,'Calc Smart'!AD59,'Calc Avalanche'!AD59,'Calc Snowball'!AD59,'Calc Cashflow'!AD59) | E53: =CHOOSE(Plan!$K$5,COUNTIF('Calc Smart'!C59:N59,">0"),COUNTIF('Calc Avalanche'!C59:N59,">0"),COUNTIF('Calc Snowball'!C59:N59,">0"),COUNTIF('Calc Cashflow'!C59:N59,">0")) | F53: =CHOOSE(Plan!$K$5,'Calc Smart'!C59,'Calc Avalanche'!C59,'Calc Snowball'!C59,'Calc Cashflow'!C59) | G53: =CHOOSE(Plan!$K$5,'Calc Smart'!D59,'Calc Avalanche'!D59,'Calc Snowball'!D59,'Calc Cashflow'!D59) | H53: =CHOOSE(Plan!$K$5,'Calc Smart'!E59,'Calc Avalanche'!E59,'Calc Snowball'!E59,'Calc Cashflow'!E59) | I53: =CHOOSE(Plan!$K$5,'Calc Smart'!F59,'Calc Avalanche'!F59,'Calc Snowball'!F59,'Calc Cashflow'!F59) | J53: =CHOOSE(Plan!$K$5,'Calc Smart'!G59,'Calc Avalanche'!G59,'Calc Snowball'!G59,'Calc Cashflow'!G59) | K53: =CHOOSE(Plan!$K$5,'Calc Smart'!H59,'Calc Avalanche'!H59,'Calc Snowball'!H59,'Calc Cashflow'!H59) | L53: =CHOOSE(Plan!$K$5,'Calc Smart'!I59,'Calc Avalanche'!I59,'Calc Snowball'!I59,'Calc Cashflow'!I59) | M53: =CHOOSE(Plan!$K$5,'Calc Smart'!J59,'Calc Avalanche'!J59,'Calc Snowball'!J59,'Calc Cashflow'!J59) | ... Q53: =CHOOSE(Plan!$K$5,'Calc Smart'!N59,'Calc Avalanche'!N59,'Calc Snowball'!N59,'Calc Cashflow'!N59)
B54: =EDATE(Plan!$C$6,48) | C54: =CHOOSE(Plan!$K$5,'Calc Smart'!AE60,'Calc Avalanche'!AE60,'Calc Snowball'!AE60,'Calc Cashflow'!AE60) | D54: =CHOOSE(Plan!$K$5,'Calc Smart'!AD60,'Calc Avalanche'!AD60,'Calc Snowball'!AD60,'Calc Cashflow'!AD60) | E54: =CHOOSE(Plan!$K$5,COUNTIF('Calc Smart'!C60:N60,">0"),COUNTIF('Calc Avalanche'!C60:N60,">0"),COUNTIF('Calc Snowball'!C60:N60,">0"),COUNTIF('Calc Cashflow'!C60:N60,">0")) | F54: =CHOOSE(Plan!$K$5,'Calc Smart'!C60,'Calc Avalanche'!C60,'Calc Snowball'!C60,'Calc Cashflow'!C60) | G54: =CHOOSE(Plan!$K$5,'Calc Smart'!D60,'Calc Avalanche'!D60,'Calc Snowball'!D60,'Calc Cashflow'!D60) | H54: =CHOOSE(Plan!$K$5,'Calc Smart'!E60,'Calc Avalanche'!E60,'Calc Snowball'!E60,'Calc Cashflow'!E60) | I54: =CHOOSE(Plan!$K$5,'Calc Smart'!F60,'Calc Avalanche'!F60,'Calc Snowball'!F60,'Calc Cashflow'!F60) | J54: =CHOOSE(Plan!$K$5,'Calc Smart'!G60,'Calc Avalanche'!G60,'Calc Snowball'!G60,'Calc Cashflow'!G60) | K54: =CHOOSE(Plan!$K$5,'Calc Smart'!H60,'Calc Avalanche'!H60,'Calc Snowball'!H60,'Calc Cashflow'!H60) | L54: =CHOOSE(Plan!$K$5,'Calc Smart'!I60,'Calc Avalanche'!I60,'Calc Snowball'!I60,'Calc Cashflow'!I60) | M54: =CHOOSE(Plan!$K$5,'Calc Smart'!J60,'Calc Avalanche'!J60,'Calc Snowball'!J60,'Calc Cashflow'!J60) | ... Q54: =CHOOSE(Plan!$K$5,'Calc Smart'!N60,'Calc Avalanche'!N60,'Calc Snowball'!N60,'Calc Cashflow'!N60)
B55: =EDATE(Plan!$C$6,49) | C55: =CHOOSE(Plan!$K$5,'Calc Smart'!AE61,'Calc Avalanche'!AE61,'Calc Snowball'!AE61,'Calc Cashflow'!AE61) | D55: =CHOOSE(Plan!$K$5,'Calc Smart'!AD61,'Calc Avalanche'!AD61,'Calc Snowball'!AD61,'Calc Cashflow'!AD61) | E55: =CHOOSE(Plan!$K$5,COUNTIF('Calc Smart'!C61:N61,">0"),COUNTIF('Calc Avalanche'!C61:N61,">0"),COUNTIF('Calc Snowball'!C61:N61,">0"),COUNTIF('Calc Cashflow'!C61:N61,">0")) | F55: =CHOOSE(Plan!$K$5,'Calc Smart'!C61,'Calc Avalanche'!C61,'Calc Snowball'!C61,'Calc Cashflow'!C61) | G55: =CHOOSE(Plan!$K$5,'Calc Smart'!D61,'Calc Avalanche'!D61,'Calc Snowball'!D61,'Calc Cashflow'!D61) | H55: =CHOOSE(Plan!$K$5,'Calc Smart'!E61,'Calc Avalanche'!E61,'Calc Snowball'!E61,'Calc Cashflow'!E61) | I55: =CHOOSE(Plan!$K$5,'Calc Smart'!F61,'Calc Avalanche'!F61,'Calc Snowball'!F61,'Calc Cashflow'!F61) | J55: =CHOOSE(Plan!$K$5,'Calc Smart'!G61,'Calc Avalanche'!G61,'Calc Snowball'!G61,'Calc Cashflow'!G61) | K55: =CHOOSE(Plan!$K$5,'Calc Smart'!H61,'Calc Avalanche'!H61,'Calc Snowball'!H61,'Calc Cashflow'!H61) | L55: =CHOOSE(Plan!$K$5,'Calc Smart'!I61,'Calc Avalanche'!I61,'Calc Snowball'!I61,'Calc Cashflow'!I61) | M55: =CHOOSE(Plan!$K$5,'Calc Smart'!J61,'Calc Avalanche'!J61,'Calc Snowball'!J61,'Calc Cashflow'!J61) | ... Q55: =CHOOSE(Plan!$K$5,'Calc Smart'!N61,'Calc Avalanche'!N61,'Calc Snowball'!N61,'Calc Cashflow'!N61)
B56: =EDATE(Plan!$C$6,50) | C56: =CHOOSE(Plan!$K$5,'Calc Smart'!AE62,'Calc Avalanche'!AE62,'Calc Snowball'!AE62,'Calc Cashflow'!AE62) | D56: =CHOOSE(Plan!$K$5,'Calc Smart'!AD62,'Calc Avalanche'!AD62,'Calc Snowball'!AD62,'Calc Cashflow'!AD62) | E56: =CHOOSE(Plan!$K$5,COUNTIF('Calc Smart'!C62:N62,">0"),COUNTIF('Calc Avalanche'!C62:N62,">0"),COUNTIF('Calc Snowball'!C62:N62,">0"),COUNTIF('Calc Cashflow'!C62:N62,">0")) | F56: =CHOOSE(Plan!$K$5,'Calc Smart'!C62,'Calc Avalanche'!C62,'Calc Snowball'!C62,'Calc Cashflow'!C62) | G56: =CHOOSE(Plan!$K$5,'Calc Smart'!D62,'Calc Avalanche'!D62,'Calc Snowball'!D62,'Calc Cashflow'!D62) | H56: =CHOOSE(Plan!$K$5,'Calc Smart'!E62,'Calc Avalanche'!E62,'Calc Snowball'!E62,'Calc Cashflow'!E62) | I56: =CHOOSE(Plan!$K$5,'Calc Smart'!F62,'Calc Avalanche'!F62,'Calc Snowball'!F62,'Calc Cashflow'!F62) | J56: =CHOOSE(Plan!$K$5,'Calc Smart'!G62,'Calc Avalanche'!G62,'Calc Snowball'!G62,'Calc Cashflow'!G62) | K56: =CHOOSE(Plan!$K$5,'Calc Smart'!H62,'Calc Avalanche'!H62,'Calc Snowball'!H62,'Calc Cashflow'!H62) | L56: =CHOOSE(Plan!$K$5,'Calc Smart'!I62,'Calc Avalanche'!I62,'Calc Snowball'!I62,'Calc Cashflow'!I62) | M56: =CHOOSE(Plan!$K$5,'Calc Smart'!J62,'Calc Avalanche'!J62,'Calc Snowball'!J62,'Calc Cashflow'!J62) | ... Q56: =CHOOSE(Plan!$K$5,'Calc Smart'!N62,'Calc Avalanche'!N62,'Calc Snowball'!N62,'Calc Cashflow'!N62)
B57: =EDATE(Plan!$C$6,51) | C57: =CHOOSE(Plan!$K$5,'Calc Smart'!AE63,'Calc Avalanche'!AE63,'Calc Snowball'!AE63,'Calc Cashflow'!AE63) | D57: =CHOOSE(Plan!$K$5,'Calc Smart'!AD63,'Calc Avalanche'!AD63,'Calc Snowball'!AD63,'Calc Cashflow'!AD63) | E57: =CHOOSE(Plan!$K$5,COUNTIF('Calc Smart'!C63:N63,">0"),COUNTIF('Calc Avalanche'!C63:N63,">0"),COUNTIF('Calc Snowball'!C63:N63,">0"),COUNTIF('Calc Cashflow'!C63:N63,">0")) | F57: =CHOOSE(Plan!$K$5,'Calc Smart'!C63,'Calc Avalanche'!C63,'Calc Snowball'!C63,'Calc Cashflow'!C63) | G57: =CHOOSE(Plan!$K$5,'Calc Smart'!D63,'Calc Avalanche'!D63,'Calc Snowball'!D63,'Calc Cashflow'!D63) | H57: =CHOOSE(Plan!$K$5,'Calc Smart'!E63,'Calc Avalanche'!E63,'Calc Snowball'!E63,'Calc Cashflow'!E63) | I57: =CHOOSE(Plan!$K$5,'Calc Smart'!F63,'Calc Avalanche'!F63,'Calc Snowball'!F63,'Calc Cashflow'!F63) | J57: =CHOOSE(Plan!$K$5,'Calc Smart'!G63,'Calc Avalanche'!G63,'Calc Snowball'!G63,'Calc Cashflow'!G63) | K57: =CHOOSE(Plan!$K$5,'Calc Smart'!H63,'Calc Avalanche'!H63,'Calc Snowball'!H63,'Calc Cashflow'!H63) | L57: =CHOOSE(Plan!$K$5,'Calc Smart'!I63,'Calc Avalanche'!I63,'Calc Snowball'!I63,'Calc Cashflow'!I63) | M57: =CHOOSE(Plan!$K$5,'Calc Smart'!J63,'Calc Avalanche'!J63,'Calc Snowball'!J63,'Calc Cashflow'!J63) | ... Q57: =CHOOSE(Plan!$K$5,'Calc Smart'!N63,'Calc Avalanche'!N63,'Calc Snowball'!N63,'Calc Cashflow'!N63)
B58: =EDATE(Plan!$C$6,52) | C58: =CHOOSE(Plan!$K$5,'Calc Smart'!AE64,'Calc Avalanche'!AE64,'Calc Snowball'!AE64,'Calc Cashflow'!AE64) | D58: =CHOOSE(Plan!$K$5,'Calc Smart'!AD64,'Calc Avalanche'!AD64,'Calc Snowball'!AD64,'Calc Cashflow'!AD64) | E58: =CHOOSE(Plan!$K$5,COUNTIF('Calc Smart'!C64:N64,">0"),COUNTIF('Calc Avalanche'!C64:N64,">0"),COUNTIF('Calc Snowball'!C64:N64,">0"),COUNTIF('Calc Cashflow'!C64:N64,">0")) | F58: =CHOOSE(Plan!$K$5,'Calc Smart'!C64,'Calc Avalanche'!C64,'Calc Snowball'!C64,'Calc Cashflow'!C64) | G58: =CHOOSE(Plan!$K$5,'Calc Smart'!D64,'Calc Avalanche'!D64,'Calc Snowball'!D64,'Calc Cashflow'!D64) | H58: =CHOOSE(Plan!$K$5,'Calc Smart'!E64,'Calc Avalanche'!E64,'Calc Snowball'!E64,'Calc Cashflow'!E64) | I58: =CHOOSE(Plan!$K$5,'Calc Smart'!F64,'Calc Avalanche'!F64,'Calc Snowball'!F64,'Calc Cashflow'!F64) | J58: =CHOOSE(Plan!$K$5,'Calc Smart'!G64,'Calc Avalanche'!G64,'Calc Snowball'!G64,'Calc Cashflow'!G64) | K58: =CHOOSE(Plan!$K$5,'Calc Smart'!H64,'Calc Avalanche'!H64,'Calc Snowball'!H64,'Calc Cashflow'!H64) | L58: =CHOOSE(Plan!$K$5,'Calc Smart'!I64,'Calc Avalanche'!I64,'Calc Snowball'!I64,'Calc Cashflow'!I64) | M58: =CHOOSE(Plan!$K$5,'Calc Smart'!J64,'Calc Avalanche'!J64,'Calc Snowball'!J64,'Calc Cashflow'!J64) | ... Q58: =CHOOSE(Plan!$K$5,'Calc Smart'!N64,'Calc Avalanche'!N64,'Calc Snowball'!N64,'Calc Cashflow'!N64)
B59: =EDATE(Plan!$C$6,53) | C59: =CHOOSE(Plan!$K$5,'Calc Smart'!AE65,'Calc Avalanche'!AE65,'Calc Snowball'!AE65,'Calc Cashflow'!AE65) | D59: =CHOOSE(Plan!$K$5,'Calc Smart'!AD65,'Calc Avalanche'!AD65,'Calc Snowball'!AD65,'Calc Cashflow'!AD65) | E59: =CHOOSE(Plan!$K$5,COUNTIF('Calc Smart'!C65:N65,">0"),COUNTIF('Calc Avalanche'!C65:N65,">0"),COUNTIF('Calc Snowball'!C65:N65,">0"),COUNTIF('Calc Cashflow'!C65:N65,">0")) | F59: =CHOOSE(Plan!$K$5,'Calc Smart'!C65,'Calc Avalanche'!C65,'Calc Snowball'!C65,'Calc Cashflow'!C65) | G59: =CHOOSE(Plan!$K$5,'Calc Smart'!D65,'Calc Avalanche'!D65,'Calc Snowball'!D65,'Calc Cashflow'!D65) | H59: =CHOOSE(Plan!$K$5,'Calc Smart'!E65,'Calc Avalanche'!E65,'Calc Snowball'!E65,'Calc Cashflow'!E65) | I59: =CHOOSE(Plan!$K$5,'Calc Smart'!F65,'Calc Avalanche'!F65,'Calc Snowball'!F65,'Calc Cashflow'!F65) | J59: =CHOOSE(Plan!$K$5,'Calc Smart'!G65,'Calc Avalanche'!G65,'Calc Snowball'!G65,'Calc Cashflow'!G65) | K59: =CHOOSE(Plan!$K$5,'Calc Smart'!H65,'Calc Avalanche'!H65,'Calc Snowball'!H65,'Calc Cashflow'!H65) | L59: =CHOOSE(Plan!$K$5,'Calc Smart'!I65,'Calc Avalanche'!I65,'Calc Snowball'!I65,'Calc Cashflow'!I65) | M59: =CHOOSE(Plan!$K$5,'Calc Smart'!J65,'Calc Avalanche'!J65,'Calc Snowball'!J65,'Calc Cashflow'!J65) | ... Q59: =CHOOSE(Plan!$K$5,'Calc Smart'!N65,'Calc Avalanche'!N65,'Calc Snowball'!N65,'Calc Cashflow'!N65)
B60: =EDATE(Plan!$C$6,54) | C60: =CHOOSE(Plan!$K$5,'Calc Smart'!AE66,'Calc Avalanche'!AE66,'Calc Snowball'!AE66,'Calc Cashflow'!AE66) | D60: =CHOOSE(Plan!$K$5,'Calc Smart'!AD66,'Calc Avalanche'!AD66,'Calc Snowball'!AD66,'Calc Cashflow'!AD66) | E60: =CHOOSE(Plan!$K$5,COUNTIF('Calc Smart'!C66:N66,">0"),COUNTIF('Calc Avalanche'!C66:N66,">0"),COUNTIF('Calc Snowball'!C66:N66,">0"),COUNTIF('Calc Cashflow'!C66:N66,">0")) | F60: =CHOOSE(Plan!$K$5,'Calc Smart'!C66,'Calc Avalanche'!C66,'Calc Snowball'!C66,'Calc Cashflow'!C66) | G60: =CHOOSE(Plan!$K$5,'Calc Smart'!D66,'Calc Avalanche'!D66,'Calc Snowball'!D66,'Calc Cashflow'!D66) | H60: =CHOOSE(Plan!$K$5,'Calc Smart'!E66,'Calc Avalanche'!E66,'Calc Snowball'!E66,'Calc Cashflow'!E66) | I60: =CHOOSE(Plan!$K$5,'Calc Smart'!F66,'Calc Avalanche'!F66,'Calc Snowball'!F66,'Calc Cashflow'!F66) | J60: =CHOOSE(Plan!$K$5,'Calc Smart'!G66,'Calc Avalanche'!G66,'Calc Snowball'!G66,'Calc Cashflow'!G66) | K60: =CHOOSE(Plan!$K$5,'Calc Smart'!H66,'Calc Avalanche'!H66,'Calc Snowball'!H66,'Calc Cashflow'!H66) | L60: =CHOOSE(Plan!$K$5,'Calc Smart'!I66,'Calc Avalanche'!I66,'Calc Snowball'!I66,'Calc Cashflow'!I66) | M60: =CHOOSE(Plan!$K$5,'Calc Smart'!J66,'Calc Avalanche'!J66,'Calc Snowball'!J66,'Calc Cashflow'!J66) | ... Q60: =CHOOSE(Plan!$K$5,'Calc Smart'!N66,'Calc Avalanche'!N66,'Calc Snowball'!N66,'Calc Cashflow'!N66)
B61: =EDATE(Plan!$C$6,55) | C61: =CHOOSE(Plan!$K$5,'Calc Smart'!AE67,'Calc Avalanche'!AE67,'Calc Snowball'!AE67,'Calc Cashflow'!AE67) | D61: =CHOOSE(Plan!$K$5,'Calc Smart'!AD67,'Calc Avalanche'!AD67,'Calc Snowball'!AD67,'Calc Cashflow'!AD67) | E61: =CHOOSE(Plan!$K$5,COUNTIF('Calc Smart'!C67:N67,">0"),COUNTIF('Calc Avalanche'!C67:N67,">0"),COUNTIF('Calc Snowball'!C67:N67,">0"),COUNTIF('Calc Cashflow'!C67:N67,">0")) | F61: =CHOOSE(Plan!$K$5,'Calc Smart'!C67,'Calc Avalanche'!C67,'Calc Snowball'!C67,'Calc Cashflow'!C67) | G61: =CHOOSE(Plan!$K$5,'Calc Smart'!D67,'Calc Avalanche'!D67,'Calc Snowball'!D67,'Calc Cashflow'!D67) | H61: =CHOOSE(Plan!$K$5,'Calc Smart'!E67,'Calc Avalanche'!E67,'Calc Snowball'!E67,'Calc Cashflow'!E67) | I61: =CHOOSE(Plan!$K$5,'Calc Smart'!F67,'Calc Avalanche'!F67,'Calc Snowball'!F67,'Calc Cashflow'!F67) | J61: =CHOOSE(Plan!$K$5,'Calc Smart'!G67,'Calc Avalanche'!G67,'Calc Snowball'!G67,'Calc Cashflow'!G67) | K61: =CHOOSE(Plan!$K$5,'Calc Smart'!H67,'Calc Avalanche'!H67,'Calc Snowball'!H67,'Calc Cashflow'!H67) | L61: =CHOOSE(Plan!$K$5,'Calc Smart'!I67,'Calc Avalanche'!I67,'Calc Snowball'!I67,'Calc Cashflow'!I67) | M61: =CHOOSE(Plan!$K$5,'Calc Smart'!J67,'Calc Avalanche'!J67,'Calc Snowball'!J67,'Calc Cashflow'!J67) | ... Q61: =CHOOSE(Plan!$K$5,'Calc Smart'!N67,'Calc Avalanche'!N67,'Calc Snowball'!N67,'Calc Cashflow'!N67)
B62: =EDATE(Plan!$C$6,56) | C62: =CHOOSE(Plan!$K$5,'Calc Smart'!AE68,'Calc Avalanche'!AE68,'Calc Snowball'!AE68,'Calc Cashflow'!AE68) | D62: =CHOOSE(Plan!$K$5,'Calc Smart'!AD68,'Calc Avalanche'!AD68,'Calc Snowball'!AD68,'Calc Cashflow'!AD68) | E62: =CHOOSE(Plan!$K$5,COUNTIF('Calc Smart'!C68:N68,">0"),COUNTIF('Calc Avalanche'!C68:N68,">0"),COUNTIF('Calc Snowball'!C68:N68,">0"),COUNTIF('Calc Cashflow'!C68:N68,">0")) | F62: =CHOOSE(Plan!$K$5,'Calc Smart'!C68,'Calc Avalanche'!C68,'Calc Snowball'!C68,'Calc Cashflow'!C68) | G62: =CHOOSE(Plan!$K$5,'Calc Smart'!D68,'Calc Avalanche'!D68,'Calc Snowball'!D68,'Calc Cashflow'!D68) | H62: =CHOOSE(Plan!$K$5,'Calc Smart'!E68,'Calc Avalanche'!E68,'Calc Snowball'!E68,'Calc Cashflow'!E68) | I62: =CHOOSE(Plan!$K$5,'Calc Smart'!F68,'Calc Avalanche'!F68,'Calc Snowball'!F68,'Calc Cashflow'!F68) | J62: =CHOOSE(Plan!$K$5,'Calc Smart'!G68,'Calc Avalanche'!G68,'Calc Snowball'!G68,'Calc Cashflow'!G68) | K62: =CHOOSE(Plan!$K$5,'Calc Smart'!H68,'Calc Avalanche'!H68,'Calc Snowball'!H68,'Calc Cashflow'!H68) | L62: =CHOOSE(Plan!$K$5,'Calc Smart'!I68,'Calc Avalanche'!I68,'Calc Snowball'!I68,'Calc Cashflow'!I68) | M62: =CHOOSE(Plan!$K$5,'Calc Smart'!J68,'Calc Avalanche'!J68,'Calc Snowball'!J68,'Calc Cashflow'!J68) | ... Q62: =CHOOSE(Plan!$K$5,'Calc Smart'!N68,'Calc Avalanche'!N68,'Calc Snowball'!N68,'Calc Cashflow'!N68)
B63: =EDATE(Plan!$C$6,57) | C63: =CHOOSE(Plan!$K$5,'Calc Smart'!AE69,'Calc Avalanche'!AE69,'Calc Snowball'!AE69,'Calc Cashflow'!AE69) | D63: =CHOOSE(Plan!$K$5,'Calc Smart'!AD69,'Calc Avalanche'!AD69,'Calc Snowball'!AD69,'Calc Cashflow'!AD69) | E63: =CHOOSE(Plan!$K$5,COUNTIF('Calc Smart'!C69:N69,">0"),COUNTIF('Calc Avalanche'!C69:N69,">0"),COUNTIF('Calc Snowball'!C69:N69,">0"),COUNTIF('Calc Cashflow'!C69:N69,">0")) | F63: =CHOOSE(Plan!$K$5,'Calc Smart'!C69,'Calc Avalanche'!C69,'Calc Snowball'!C69,'Calc Cashflow'!C69) | G63: =CHOOSE(Plan!$K$5,'Calc Smart'!D69,'Calc Avalanche'!D69,'Calc Snowball'!D69,'Calc Cashflow'!D69) | H63: =CHOOSE(Plan!$K$5,'Calc Smart'!E69,'Calc Avalanche'!E69,'Calc Snowball'!E69,'Calc Cashflow'!E69) | I63: =CHOOSE(Plan!$K$5,'Calc Smart'!F69,'Calc Avalanche'!F69,'Calc Snowball'!F69,'Calc Cashflow'!F69) | J63: =CHOOSE(Plan!$K$5,'Calc Smart'!G69,'Calc Avalanche'!G69,'Calc Snowball'!G69,'Calc Cashflow'!G69) | K63: =CHOOSE(Plan!$K$5,'Calc Smart'!H69,'Calc Avalanche'!H69,'Calc Snowball'!H69,'Calc Cashflow'!H69) | L63: =CHOOSE(Plan!$K$5,'Calc Smart'!I69,'Calc Avalanche'!I69,'Calc Snowball'!I69,'Calc Cashflow'!I69) | M63: =CHOOSE(Plan!$K$5,'Calc Smart'!J69,'Calc Avalanche'!J69,'Calc Snowball'!J69,'Calc Cashflow'!J69) | ... Q63: =CHOOSE(Plan!$K$5,'Calc Smart'!N69,'Calc Avalanche'!N69,'Calc Snowball'!N69,'Calc Cashflow'!N69)
B64: =EDATE(Plan!$C$6,58) | C64: =CHOOSE(Plan!$K$5,'Calc Smart'!AE70,'Calc Avalanche'!AE70,'Calc Snowball'!AE70,'Calc Cashflow'!AE70) | D64: =CHOOSE(Plan!$K$5,'Calc Smart'!AD70,'Calc Avalanche'!AD70,'Calc Snowball'!AD70,'Calc Cashflow'!AD70) | E64: =CHOOSE(Plan!$K$5,COUNTIF('Calc Smart'!C70:N70,">0"),COUNTIF('Calc Avalanche'!C70:N70,">0"),COUNTIF('Calc Snowball'!C70:N70,">0"),COUNTIF('Calc Cashflow'!C70:N70,">0")) | F64: =CHOOSE(Plan!$K$5,'Calc Smart'!C70,'Calc Avalanche'!C70,'Calc Snowball'!C70,'Calc Cashflow'!C70) | G64: =CHOOSE(Plan!$K$5,'Calc Smart'!D70,'Calc Avalanche'!D70,'Calc Snowball'!D70,'Calc Cashflow'!D70) | H64: =CHOOSE(Plan!$K$5,'Calc Smart'!E70,'Calc Avalanche'!E70,'Calc Snowball'!E70,'Calc Cashflow'!E70) | I64: =CHOOSE(Plan!$K$5,'Calc Smart'!F70,'Calc Avalanche'!F70,'Calc Snowball'!F70,'Calc Cashflow'!F70) | J64: =CHOOSE(Plan!$K$5,'Calc Smart'!G70,'Calc Avalanche'!G70,'Calc Snowball'!G70,'Calc Cashflow'!G70) | K64: =CHOOSE(Plan!$K$5,'Calc Smart'!H70,'Calc Avalanche'!H70,'Calc Snowball'!H70,'Calc Cashflow'!H70) | L64: =CHOOSE(Plan!$K$5,'Calc Smart'!I70,'Calc Avalanche'!I70,'Calc Snowball'!I70,'Calc Cashflow'!I70) | M64: =CHOOSE(Plan!$K$5,'Calc Smart'!J70,'Calc Avalanche'!J70,'Calc Snowball'!J70,'Calc Cashflow'!J70) | ... Q64: =CHOOSE(Plan!$K$5,'Calc Smart'!N70,'Calc Avalanche'!N70,'Calc Snowball'!N70,'Calc Cashflow'!N70)
B65: =EDATE(Plan!$C$6,59) | C65: =CHOOSE(Plan!$K$5,'Calc Smart'!AE71,'Calc Avalanche'!AE71,'Calc Snowball'!AE71,'Calc Cashflow'!AE71) | D65: =CHOOSE(Plan!$K$5,'Calc Smart'!AD71,'Calc Avalanche'!AD71,'Calc Snowball'!AD71,'Calc Cashflow'!AD71) | E65: =CHOOSE(Plan!$K$5,COUNTIF('Calc Smart'!C71:N71,">0"),COUNTIF('Calc Avalanche'!C71:N71,">0"),COUNTIF('Calc Snowball'!C71:N71,">0"),COUNTIF('Calc Cashflow'!C71:N71,">0")) | F65: =CHOOSE(Plan!$K$5,'Calc Smart'!C71,'Calc Avalanche'!C71,'Calc Snowball'!C71,'Calc Cashflow'!C71) | G65: =CHOOSE(Plan!$K$5,'Calc Smart'!D71,'Calc Avalanche'!D71,'Calc Snowball'!D71,'Calc Cashflow'!D71) | H65: =CHOOSE(Plan!$K$5,'Calc Smart'!E71,'Calc Avalanche'!E71,'Calc Snowball'!E71,'Calc Cashflow'!E71) | I65: =CHOOSE(Plan!$K$5,'Calc Smart'!F71,'Calc Avalanche'!F71,'Calc Snowball'!F71,'Calc Cashflow'!F71) | J65: =CHOOSE(Plan!$K$5,'Calc Smart'!G71,'Calc Avalanche'!G71,'Calc Snowball'!G71,'Calc Cashflow'!G71) | K65: =CHOOSE(Plan!$K$5,'Calc Smart'!H71,'Calc Avalanche'!H71,'Calc Snowball'!H71,'Calc Cashflow'!H71) | L65: =CHOOSE(Plan!$K$5,'Calc Smart'!I71,'Calc Avalanche'!I71,'Calc Snowball'!I71,'Calc Cashflow'!I71) | M65: =CHOOSE(Plan!$K$5,'Calc Smart'!J71,'Calc Avalanche'!J71,'Calc Snowball'!J71,'Calc Cashflow'!J71) | ... Q65: =CHOOSE(Plan!$K$5,'Calc Smart'!N71,'Calc Avalanche'!N71,'Calc Snowball'!N71,'Calc Cashflow'!N71)
B66: =EDATE(Plan!$C$6,60) | C66: =CHOOSE(Plan!$K$5,'Calc Smart'!AE72,'Calc Avalanche'!AE72,'Calc Snowball'!AE72,'Calc Cashflow'!AE72) | D66: =CHOOSE(Plan!$K$5,'Calc Smart'!AD72,'Calc Avalanche'!AD72,'Calc Snowball'!AD72,'Calc Cashflow'!AD72) | E66: =CHOOSE(Plan!$K$5,COUNTIF('Calc Smart'!C72:N72,">0"),COUNTIF('Calc Avalanche'!C72:N72,">0"),COUNTIF('Calc Snowball'!C72:N72,">0"),COUNTIF('Calc Cashflow'!C72:N72,">0")) | F66: =CHOOSE(Plan!$K$5,'Calc Smart'!C72,'Calc Avalanche'!C72,'Calc Snowball'!C72,'Calc Cashflow'!C72) | G66: =CHOOSE(Plan!$K$5,'Calc Smart'!D72,'Calc Avalanche'!D72,'Calc Snowball'!D72,'Calc Cashflow'!D72) | H66: =CHOOSE(Plan!$K$5,'Calc Smart'!E72,'Calc Avalanche'!E72,'Calc Snowball'!E72,'Calc Cashflow'!E72) | I66: =CHOOSE(Plan!$K$5,'Calc Smart'!F72,'Calc Avalanche'!F72,'Calc Snowball'!F72,'Calc Cashflow'!F72) | J66: =CHOOSE(Plan!$K$5,'Calc Smart'!G72,'Calc Avalanche'!G72,'Calc Snowball'!G72,'Calc Cashflow'!G72) | K66: =CHOOSE(Plan!$K$5,'Calc Smart'!H72,'Calc Avalanche'!H72,'Calc Snowball'!H72,'Calc Cashflow'!H72) | L66: =CHOOSE(Plan!$K$5,'Calc Smart'!I72,'Calc Avalanche'!I72,'Calc Snowball'!I72,'Calc Cashflow'!I72) | M66: =CHOOSE(Plan!$K$5,'Calc Smart'!J72,'Calc Avalanche'!J72,'Calc Snowball'!J72,'Calc Cashflow'!J72) | ... Q66: =CHOOSE(Plan!$K$5,'Calc Smart'!N72,'Calc Avalanche'!N72,'Calc Snowball'!N72,'Calc Cashflow'!N72)
B67: =EDATE(Plan!$C$6,61) | C67: =CHOOSE(Plan!$K$5,'Calc Smart'!AE73,'Calc Avalanche'!AE73,'Calc Snowball'!AE73,'Calc Cashflow'!AE73) | D67: =CHOOSE(Plan!$K$5,'Calc Smart'!AD73,'Calc Avalanche'!AD73,'Calc Snowball'!AD73,'Calc Cashflow'!AD73) | E67: =CHOOSE(Plan!$K$5,COUNTIF('Calc Smart'!C73:N73,">0"),COUNTIF('Calc Avalanche'!C73:N73,">0"),COUNTIF('Calc Snowball'!C73:N73,">0"),COUNTIF('Calc Cashflow'!C73:N73,">0")) | F67: =CHOOSE(Plan!$K$5,'Calc Smart'!C73,'Calc Avalanche'!C73,'Calc Snowball'!C73,'Calc Cashflow'!C73) | G67: =CHOOSE(Plan!$K$5,'Calc Smart'!D73,'Calc Avalanche'!D73,'Calc Snowball'!D73,'Calc Cashflow'!D73) | H67: =CHOOSE(Plan!$K$5,'Calc Smart'!E73,'Calc Avalanche'!E73,'Calc Snowball'!E73,'Calc Cashflow'!E73) | I67: =CHOOSE(Plan!$K$5,'Calc Smart'!F73,'Calc Avalanche'!F73,'Calc Snowball'!F73,'Calc Cashflow'!F73) | J67: =CHOOSE(Plan!$K$5,'Calc Smart'!G73,'Calc Avalanche'!G73,'Calc Snowball'!G73,'Calc Cashflow'!G73) | K67: =CHOOSE(Plan!$K$5,'Calc Smart'!H73,'Calc Avalanche'!H73,'Calc Snowball'!H73,'Calc Cashflow'!H73) | L67: =CHOOSE(Plan!$K$5,'Calc Smart'!I73,'Calc Avalanche'!I73,'Calc Snowball'!I73,'Calc Cashflow'!I73) | M67: =CHOOSE(Plan!$K$5,'Calc Smart'!J73,'Calc Avalanche'!J73,'Calc Snowball'!J73,'Calc Cashflow'!J73) | ... Q67: =CHOOSE(Plan!$K$5,'Calc Smart'!N73,'Calc Avalanche'!N73,'Calc Snowball'!N73,'Calc Cashflow'!N73)
B68: =EDATE(Plan!$C$6,62) | C68: =CHOOSE(Plan!$K$5,'Calc Smart'!AE74,'Calc Avalanche'!AE74,'Calc Snowball'!AE74,'Calc Cashflow'!AE74) | D68: =CHOOSE(Plan!$K$5,'Calc Smart'!AD74,'Calc Avalanche'!AD74,'Calc Snowball'!AD74,'Calc Cashflow'!AD74) | E68: =CHOOSE(Plan!$K$5,COUNTIF('Calc Smart'!C74:N74,">0"),COUNTIF('Calc Avalanche'!C74:N74,">0"),COUNTIF('Calc Snowball'!C74:N74,">0"),COUNTIF('Calc Cashflow'!C74:N74,">0")) | F68: =CHOOSE(Plan!$K$5,'Calc Smart'!C74,'Calc Avalanche'!C74,'Calc Snowball'!C74,'Calc Cashflow'!C74) | G68: =CHOOSE(Plan!$K$5,'Calc Smart'!D74,'Calc Avalanche'!D74,'Calc Snowball'!D74,'Calc Cashflow'!D74) | H68: =CHOOSE(Plan!$K$5,'Calc Smart'!E74,'Calc Avalanche'!E74,'Calc Snowball'!E74,'Calc Cashflow'!E74) | I68: =CHOOSE(Plan!$K$5,'Calc Smart'!F74,'Calc Avalanche'!F74,'Calc Snowball'!F74,'Calc Cashflow'!F74) | J68: =CHOOSE(Plan!$K$5,'Calc Smart'!G74,'Calc Avalanche'!G74,'Calc Snowball'!G74,'Calc Cashflow'!G74) | K68: =CHOOSE(Plan!$K$5,'Calc Smart'!H74,'Calc Avalanche'!H74,'Calc Snowball'!H74,'Calc Cashflow'!H74) | L68: =CHOOSE(Plan!$K$5,'Calc Smart'!I74,'Calc Avalanche'!I74,'Calc Snowball'!I74,'Calc Cashflow'!I74) | M68: =CHOOSE(Plan!$K$5,'Calc Smart'!J74,'Calc Avalanche'!J74,'Calc Snowball'!J74,'Calc Cashflow'!J74) | ... Q68: =CHOOSE(Plan!$K$5,'Calc Smart'!N74,'Calc Avalanche'!N74,'Calc Snowball'!N74,'Calc Cashflow'!N74)
B69: =EDATE(Plan!$C$6,63) | C69: =CHOOSE(Plan!$K$5,'Calc Smart'!AE75,'Calc Avalanche'!AE75,'Calc Snowball'!AE75,'Calc Cashflow'!AE75) | D69: =CHOOSE(Plan!$K$5,'Calc Smart'!AD75,'Calc Avalanche'!AD75,'Calc Snowball'!AD75,'Calc Cashflow'!AD75) | E69: =CHOOSE(Plan!$K$5,COUNTIF('Calc Smart'!C75:N75,">0"),COUNTIF('Calc Avalanche'!C75:N75,">0"),COUNTIF('Calc Snowball'!C75:N75,">0"),COUNTIF('Calc Cashflow'!C75:N75,">0")) | F69: =CHOOSE(Plan!$K$5,'Calc Smart'!C75,'Calc Avalanche'!C75,'Calc Snowball'!C75,'Calc Cashflow'!C75) | G69: =CHOOSE(Plan!$K$5,'Calc Smart'!D75,'Calc Avalanche'!D75,'Calc Snowball'!D75,'Calc Cashflow'!D75) | H69: =CHOOSE(Plan!$K$5,'Calc Smart'!E75,'Calc Avalanche'!E75,'Calc Snowball'!E75,'Calc Cashflow'!E75) | I69: =CHOOSE(Plan!$K$5,'Calc Smart'!F75,'Calc Avalanche'!F75,'Calc Snowball'!F75,'Calc Cashflow'!F75) | J69: =CHOOSE(Plan!$K$5,'Calc Smart'!G75,'Calc Avalanche'!G75,'Calc Snowball'!G75,'Calc Cashflow'!G75) | K69: =CHOOSE(Plan!$K$5,'Calc Smart'!H75,'Calc Avalanche'!H75,'Calc Snowball'!H75,'Calc Cashflow'!H75) | L69: =CHOOSE(Plan!$K$5,'Calc Smart'!I75,'Calc Avalanche'!I75,'Calc Snowball'!I75,'Calc Cashflow'!I75) | M69: =CHOOSE(Plan!$K$5,'Calc Smart'!J75,'Calc Avalanche'!J75,'Calc Snowball'!J75,'Calc Cashflow'!J75) | ... Q69: =CHOOSE(Plan!$K$5,'Calc Smart'!N75,'Calc Avalanche'!N75,'Calc Snowball'!N75,'Calc Cashflow'!N75)
B70: =EDATE(Plan!$C$6,64) | C70: =CHOOSE(Plan!$K$5,'Calc Smart'!AE76,'Calc Avalanche'!AE76,'Calc Snowball'!AE76,'Calc Cashflow'!AE76) | D70: =CHOOSE(Plan!$K$5,'Calc Smart'!AD76,'Calc Avalanche'!AD76,'Calc Snowball'!AD76,'Calc Cashflow'!AD76) | E70: =CHOOSE(Plan!$K$5,COUNTIF('Calc Smart'!C76:N76,">0"),COUNTIF('Calc Avalanche'!C76:N76,">0"),COUNTIF('Calc Snowball'!C76:N76,">0"),COUNTIF('Calc Cashflow'!C76:N76,">0")) | F70: =CHOOSE(Plan!$K$5,'Calc Smart'!C76,'Calc Avalanche'!C76,'Calc Snowball'!C76,'Calc Cashflow'!C76) | G70: =CHOOSE(Plan!$K$5,'Calc Smart'!D76,'Calc Avalanche'!D76,'Calc Snowball'!D76,'Calc Cashflow'!D76) | H70: =CHOOSE(Plan!$K$5,'Calc Smart'!E76,'Calc Avalanche'!E76,'Calc Snowball'!E76,'Calc Cashflow'!E76) | I70: =CHOOSE(Plan!$K$5,'Calc Smart'!F76,'Calc Avalanche'!F76,'Calc Snowball'!F76,'Calc Cashflow'!F76) | J70: =CHOOSE(Plan!$K$5,'Calc Smart'!G76,'Calc Avalanche'!G76,'Calc Snowball'!G76,'Calc Cashflow'!G76) | K70: =CHOOSE(Plan!$K$5,'Calc Smart'!H76,'Calc Avalanche'!H76,'Calc Snowball'!H76,'Calc Cashflow'!H76) | L70: =CHOOSE(Plan!$K$5,'Calc Smart'!I76,'Calc Avalanche'!I76,'Calc Snowball'!I76,'Calc Cashflow'!I76) | M70: =CHOOSE(Plan!$K$5,'Calc Smart'!J76,'Calc Avalanche'!J76,'Calc Snowball'!J76,'Calc Cashflow'!J76) | ... Q70: =CHOOSE(Plan!$K$5,'Calc Smart'!N76,'Calc Avalanche'!N76,'Calc Snowball'!N76,'Calc Cashflow'!N76)
B71: =EDATE(Plan!$C$6,65) | C71: =CHOOSE(Plan!$K$5,'Calc Smart'!AE77,'Calc Avalanche'!AE77,'Calc Snowball'!AE77,'Calc Cashflow'!AE77) | D71: =CHOOSE(Plan!$K$5,'Calc Smart'!AD77,'Calc Avalanche'!AD77,'Calc Snowball'!AD77,'Calc Cashflow'!AD77) | E71: =CHOOSE(Plan!$K$5,COUNTIF('Calc Smart'!C77:N77,">0"),COUNTIF('Calc Avalanche'!C77:N77,">0"),COUNTIF('Calc Snowball'!C77:N77,">0"),COUNTIF('Calc Cashflow'!C77:N77,">0")) | F71: =CHOOSE(Plan!$K$5,'Calc Smart'!C77,'Calc Avalanche'!C77,'Calc Snowball'!C77,'Calc Cashflow'!C77) | G71: =CHOOSE(Plan!$K$5,'Calc Smart'!D77,'Calc Avalanche'!D77,'Calc Snowball'!D77,'Calc Cashflow'!D77) | H71: =CHOOSE(Plan!$K$5,'Calc Smart'!E77,'Calc Avalanche'!E77,'Calc Snowball'!E77,'Calc Cashflow'!E77) | I71: =CHOOSE(Plan!$K$5,'Calc Smart'!F77,'Calc Avalanche'!F77,'Calc Snowball'!F77,'Calc Cashflow'!F77) | J71: =CHOOSE(Plan!$K$5,'Calc Smart'!G77,'Calc Avalanche'!G77,'Calc Snowball'!G77,'Calc Cashflow'!G77) | K71: =CHOOSE(Plan!$K$5,'Calc Smart'!H77,'Calc Avalanche'!H77,'Calc Snowball'!H77,'Calc Cashflow'!H77) | L71: =CHOOSE(Plan!$K$5,'Calc Smart'!I77,'Calc Avalanche'!I77,'Calc Snowball'!I77,'Calc Cashflow'!I77) | M71: =CHOOSE(Plan!$K$5,'Calc Smart'!J77,'Calc Avalanche'!J77,'Calc Snowball'!J77,'Calc Cashflow'!J77) | ... Q71: =CHOOSE(Plan!$K$5,'Calc Smart'!N77,'Calc Avalanche'!N77,'Calc Snowball'!N77,'Calc Cashflow'!N77)
B72: =EDATE(Plan!$C$6,66) | C72: =CHOOSE(Plan!$K$5,'Calc Smart'!AE78,'Calc Avalanche'!AE78,'Calc Snowball'!AE78,'Calc Cashflow'!AE78) | D72: =CHOOSE(Plan!$K$5,'Calc Smart'!AD78,'Calc Avalanche'!AD78,'Calc Snowball'!AD78,'Calc Cashflow'!AD78) | E72: =CHOOSE(Plan!$K$5,COUNTIF('Calc Smart'!C78:N78,">0"),COUNTIF('Calc Avalanche'!C78:N78,">0"),COUNTIF('Calc Snowball'!C78:N78,">0"),COUNTIF('Calc Cashflow'!C78:N78,">0")) | F72: =CHOOSE(Plan!$K$5,'Calc Smart'!C78,'Calc Avalanche'!C78,'Calc Snowball'!C78,'Calc Cashflow'!C78) | G72: =CHOOSE(Plan!$K$5,'Calc Smart'!D78,'Calc Avalanche'!D78,'Calc Snowball'!D78,'Calc Cashflow'!D78) | H72: =CHOOSE(Plan!$K$5,'Calc Smart'!E78,'Calc Avalanche'!E78,'Calc Snowball'!E78,'Calc Cashflow'!E78) | I72: =CHOOSE(Plan!$K$5,'Calc Smart'!F78,'Calc Avalanche'!F78,'Calc Snowball'!F78,'Calc Cashflow'!F78) | J72: =CHOOSE(Plan!$K$5,'Calc Smart'!G78,'Calc Avalanche'!G78,'Calc Snowball'!G78,'Calc Cashflow'!G78) | K72: =CHOOSE(Plan!$K$5,'Calc Smart'!H78,'Calc Avalanche'!H78,'Calc Snowball'!H78,'Calc Cashflow'!H78) | L72: =CHOOSE(Plan!$K$5,'Calc Smart'!I78,'Calc Avalanche'!I78,'Calc Snowball'!I78,'Calc Cashflow'!I78) | M72: =CHOOSE(Plan!$K$5,'Calc Smart'!J78,'Calc Avalanche'!J78,'Calc Snowball'!J78,'Calc Cashflow'!J78) | ... Q72: =CHOOSE(Plan!$K$5,'Calc Smart'!N78,'Calc Avalanche'!N78,'Calc Snowball'!N78,'Calc Cashflow'!N78)
B73: =EDATE(Plan!$C$6,67) | C73: =CHOOSE(Plan!$K$5,'Calc Smart'!AE79,'Calc Avalanche'!AE79,'Calc Snowball'!AE79,'Calc Cashflow'!AE79) | D73: =CHOOSE(Plan!$K$5,'Calc Smart'!AD79,'Calc Avalanche'!AD79,'Calc Snowball'!AD79,'Calc Cashflow'!AD79) | E73: =CHOOSE(Plan!$K$5,COUNTIF('Calc Smart'!C79:N79,">0"),COUNTIF('Calc Avalanche'!C79:N79,">0"),COUNTIF('Calc Snowball'!C79:N79,">0"),COUNTIF('Calc Cashflow'!C79:N79,">0")) | F73: =CHOOSE(Plan!$K$5,'Calc Smart'!C79,'Calc Avalanche'!C79,'Calc Snowball'!C79,'Calc Cashflow'!C79) | G73: =CHOOSE(Plan!$K$5,'Calc Smart'!D79,'Calc Avalanche'!D79,'Calc Snowball'!D79,'Calc Cashflow'!D79) | H73: =CHOOSE(Plan!$K$5,'Calc Smart'!E79,'Calc Avalanche'!E79,'Calc Snowball'!E79,'Calc Cashflow'!E79) | I73: =CHOOSE(Plan!$K$5,'Calc Smart'!F79,'Calc Avalanche'!F79,'Calc Snowball'!F79,'Calc Cashflow'!F79) | J73: =CHOOSE(Plan!$K$5,'Calc Smart'!G79,'Calc Avalanche'!G79,'Calc Snowball'!G79,'Calc Cashflow'!G79) | K73: =CHOOSE(Plan!$K$5,'Calc Smart'!H79,'Calc Avalanche'!H79,'Calc Snowball'!H79,'Calc Cashflow'!H79) | L73: =CHOOSE(Plan!$K$5,'Calc Smart'!I79,'Calc Avalanche'!I79,'Calc Snowball'!I79,'Calc Cashflow'!I79) | M73: =CHOOSE(Plan!$K$5,'Calc Smart'!J79,'Calc Avalanche'!J79,'Calc Snowball'!J79,'Calc Cashflow'!J79) | ... Q73: =CHOOSE(Plan!$K$5,'Calc Smart'!N79,'Calc Avalanche'!N79,'Calc Snowball'!N79,'Calc Cashflow'!N79)
B74: =EDATE(Plan!$C$6,68) | C74: =CHOOSE(Plan!$K$5,'Calc Smart'!AE80,'Calc Avalanche'!AE80,'Calc Snowball'!AE80,'Calc Cashflow'!AE80) | D74: =CHOOSE(Plan!$K$5,'Calc Smart'!AD80,'Calc Avalanche'!AD80,'Calc Snowball'!AD80,'Calc Cashflow'!AD80) | E74: =CHOOSE(Plan!$K$5,COUNTIF('Calc Smart'!C80:N80,">0"),COUNTIF('Calc Avalanche'!C80:N80,">0"),COUNTIF('Calc Snowball'!C80:N80,">0"),COUNTIF('Calc Cashflow'!C80:N80,">0")) | F74: =CHOOSE(Plan!$K$5,'Calc Smart'!C80,'Calc Avalanche'!C80,'Calc Snowball'!C80,'Calc Cashflow'!C80) | G74: =CHOOSE(Plan!$K$5,'Calc Smart'!D80,'Calc Avalanche'!D80,'Calc Snowball'!D80,'Calc Cashflow'!D80) | H74: =CHOOSE(Plan!$K$5,'Calc Smart'!E80,'Calc Avalanche'!E80,'Calc Snowball'!E80,'Calc Cashflow'!E80) | I74: =CHOOSE(Plan!$K$5,'Calc Smart'!F80,'Calc Avalanche'!F80,'Calc Snowball'!F80,'Calc Cashflow'!F80) | J74: =CHOOSE(Plan!$K$5,'Calc Smart'!G80,'Calc Avalanche'!G80,'Calc Snowball'!G80,'Calc Cashflow'!G80) | K74: =CHOOSE(Plan!$K$5,'Calc Smart'!H80,'Calc Avalanche'!H80,'Calc Snowball'!H80,'Calc Cashflow'!H80) | L74: =CHOOSE(Plan!$K$5,'Calc Smart'!I80,'Calc Avalanche'!I80,'Calc Snowball'!I80,'Calc Cashflow'!I80) | M74: =CHOOSE(Plan!$K$5,'Calc Smart'!J80,'Calc Avalanche'!J80,'Calc Snowball'!J80,'Calc Cashflow'!J80) | ... Q74: =CHOOSE(Plan!$K$5,'Calc Smart'!N80,'Calc Avalanche'!N80,'Calc Snowball'!N80,'Calc Cashflow'!N80)
B75: =EDATE(Plan!$C$6,69) | C75: =CHOOSE(Plan!$K$5,'Calc Smart'!AE81,'Calc Avalanche'!AE81,'Calc Snowball'!AE81,'Calc Cashflow'!AE81) | D75: =CHOOSE(Plan!$K$5,'Calc Smart'!AD81,'Calc Avalanche'!AD81,'Calc Snowball'!AD81,'Calc Cashflow'!AD81) | E75: =CHOOSE(Plan!$K$5,COUNTIF('Calc Smart'!C81:N81,">0"),COUNTIF('Calc Avalanche'!C81:N81,">0"),COUNTIF('Calc Snowball'!C81:N81,">0"),COUNTIF('Calc Cashflow'!C81:N81,">0")) | F75: =CHOOSE(Plan!$K$5,'Calc Smart'!C81,'Calc Avalanche'!C81,'Calc Snowball'!C81,'Calc Cashflow'!C81) | G75: =CHOOSE(Plan!$K$5,'Calc Smart'!D81,'Calc Avalanche'!D81,'Calc Snowball'!D81,'Calc Cashflow'!D81) | H75: =CHOOSE(Plan!$K$5,'Calc Smart'!E81,'Calc Avalanche'!E81,'Calc Snowball'!E81,'Calc Cashflow'!E81) | I75: =CHOOSE(Plan!$K$5,'Calc Smart'!F81,'Calc Avalanche'!F81,'Calc Snowball'!F81,'Calc Cashflow'!F81) | J75: =CHOOSE(Plan!$K$5,'Calc Smart'!G81,'Calc Avalanche'!G81,'Calc Snowball'!G81,'Calc Cashflow'!G81) | K75: =CHOOSE(Plan!$K$5,'Calc Smart'!H81,'Calc Avalanche'!H81,'Calc Snowball'!H81,'Calc Cashflow'!H81) | L75: =CHOOSE(Plan!$K$5,'Calc Smart'!I81,'Calc Avalanche'!I81,'Calc Snowball'!I81,'Calc Cashflow'!I81) | M75: =CHOOSE(Plan!$K$5,'Calc Smart'!J81,'Calc Avalanche'!J81,'Calc Snowball'!J81,'Calc Cashflow'!J81) | ... Q75: =CHOOSE(Plan!$K$5,'Calc Smart'!N81,'Calc Avalanche'!N81,'Calc Snowball'!N81,'Calc Cashflow'!N81)
B76: =EDATE(Plan!$C$6,70) | C76: =CHOOSE(Plan!$K$5,'Calc Smart'!AE82,'Calc Avalanche'!AE82,'Calc Snowball'!AE82,'Calc Cashflow'!AE82) | D76: =CHOOSE(Plan!$K$5,'Calc Smart'!AD82,'Calc Avalanche'!AD82,'Calc Snowball'!AD82,'Calc Cashflow'!AD82) | E76: =CHOOSE(Plan!$K$5,COUNTIF('Calc Smart'!C82:N82,">0"),COUNTIF('Calc Avalanche'!C82:N82,">0"),COUNTIF('Calc Snowball'!C82:N82,">0"),COUNTIF('Calc Cashflow'!C82:N82,">0")) | F76: =CHOOSE(Plan!$K$5,'Calc Smart'!C82,'Calc Avalanche'!C82,'Calc Snowball'!C82,'Calc Cashflow'!C82) | G76: =CHOOSE(Plan!$K$5,'Calc Smart'!D82,'Calc Avalanche'!D82,'Calc Snowball'!D82,'Calc Cashflow'!D82) | H76: =CHOOSE(Plan!$K$5,'Calc Smart'!E82,'Calc Avalanche'!E82,'Calc Snowball'!E82,'Calc Cashflow'!E82) | I76: =CHOOSE(Plan!$K$5,'Calc Smart'!F82,'Calc Avalanche'!F82,'Calc Snowball'!F82,'Calc Cashflow'!F82) | J76: =CHOOSE(Plan!$K$5,'Calc Smart'!G82,'Calc Avalanche'!G82,'Calc Snowball'!G82,'Calc Cashflow'!G82) | K76: =CHOOSE(Plan!$K$5,'Calc Smart'!H82,'Calc Avalanche'!H82,'Calc Snowball'!H82,'Calc Cashflow'!H82) | L76: =CHOOSE(Plan!$K$5,'Calc Smart'!I82,'Calc Avalanche'!I82,'Calc Snowball'!I82,'Calc Cashflow'!I82) | M76: =CHOOSE(Plan!$K$5,'Calc Smart'!J82,'Calc Avalanche'!J82,'Calc Snowball'!J82,'Calc Cashflow'!J82) | ... Q76: =CHOOSE(Plan!$K$5,'Calc Smart'!N82,'Calc Avalanche'!N82,'Calc Snowball'!N82,'Calc Cashflow'!N82)
B77: =EDATE(Plan!$C$6,71) | C77: =CHOOSE(Plan!$K$5,'Calc Smart'!AE83,'Calc Avalanche'!AE83,'Calc Snowball'!AE83,'Calc Cashflow'!AE83) | D77: =CHOOSE(Plan!$K$5,'Calc Smart'!AD83,'Calc Avalanche'!AD83,'Calc Snowball'!AD83,'Calc Cashflow'!AD83) | E77: =CHOOSE(Plan!$K$5,COUNTIF('Calc Smart'!C83:N83,">0"),COUNTIF('Calc Avalanche'!C83:N83,">0"),COUNTIF('Calc Snowball'!C83:N83,">0"),COUNTIF('Calc Cashflow'!C83:N83,">0")) | F77: =CHOOSE(Plan!$K$5,'Calc Smart'!C83,'Calc Avalanche'!C83,'Calc Snowball'!C83,'Calc Cashflow'!C83) | G77: =CHOOSE(Plan!$K$5,'Calc Smart'!D83,'Calc Avalanche'!D83,'Calc Snowball'!D83,'Calc Cashflow'!D83) | H77: =CHOOSE(Plan!$K$5,'Calc Smart'!E83,'Calc Avalanche'!E83,'Calc Snowball'!E83,'Calc Cashflow'!E83) | I77: =CHOOSE(Plan!$K$5,'Calc Smart'!F83,'Calc Avalanche'!F83,'Calc Snowball'!F83,'Calc Cashflow'!F83) | J77: =CHOOSE(Plan!$K$5,'Calc Smart'!G83,'Calc Avalanche'!G83,'Calc Snowball'!G83,'Calc Cashflow'!G83) | K77: =CHOOSE(Plan!$K$5,'Calc Smart'!H83,'Calc Avalanche'!H83,'Calc Snowball'!H83,'Calc Cashflow'!H83) | L77: =CHOOSE(Plan!$K$5,'Calc Smart'!I83,'Calc Avalanche'!I83,'Calc Snowball'!I83,'Calc Cashflow'!I83) | M77: =CHOOSE(Plan!$K$5,'Calc Smart'!J83,'Calc Avalanche'!J83,'Calc Snowball'!J83,'Calc Cashflow'!J83) | ... Q77: =CHOOSE(Plan!$K$5,'Calc Smart'!N83,'Calc Avalanche'!N83,'Calc Snowball'!N83,'Calc Cashflow'!N83)
B78: =EDATE(Plan!$C$6,72) | C78: =CHOOSE(Plan!$K$5,'Calc Smart'!AE84,'Calc Avalanche'!AE84,'Calc Snowball'!AE84,'Calc Cashflow'!AE84) | D78: =CHOOSE(Plan!$K$5,'Calc Smart'!AD84,'Calc Avalanche'!AD84,'Calc Snowball'!AD84,'Calc Cashflow'!AD84) | E78: =CHOOSE(Plan!$K$5,COUNTIF('Calc Smart'!C84:N84,">0"),COUNTIF('Calc Avalanche'!C84:N84,">0"),COUNTIF('Calc Snowball'!C84:N84,">0"),COUNTIF('Calc Cashflow'!C84:N84,">0")) | F78: =CHOOSE(Plan!$K$5,'Calc Smart'!C84,'Calc Avalanche'!C84,'Calc Snowball'!C84,'Calc Cashflow'!C84) | G78: =CHOOSE(Plan!$K$5,'Calc Smart'!D84,'Calc Avalanche'!D84,'Calc Snowball'!D84,'Calc Cashflow'!D84) | H78: =CHOOSE(Plan!$K$5,'Calc Smart'!E84,'Calc Avalanche'!E84,'Calc Snowball'!E84,'Calc Cashflow'!E84) | I78: =CHOOSE(Plan!$K$5,'Calc Smart'!F84,'Calc Avalanche'!F84,'Calc Snowball'!F84,'Calc Cashflow'!F84) | J78: =CHOOSE(Plan!$K$5,'Calc Smart'!G84,'Calc Avalanche'!G84,'Calc Snowball'!G84,'Calc Cashflow'!G84) | K78: =CHOOSE(Plan!$K$5,'Calc Smart'!H84,'Calc Avalanche'!H84,'Calc Snowball'!H84,'Calc Cashflow'!H84) | L78: =CHOOSE(Plan!$K$5,'Calc Smart'!I84,'Calc Avalanche'!I84,'Calc Snowball'!I84,'Calc Cashflow'!I84) | M78: =CHOOSE(Plan!$K$5,'Calc Smart'!J84,'Calc Avalanche'!J84,'Calc Snowball'!J84,'Calc Cashflow'!J84) | ... Q78: =CHOOSE(Plan!$K$5,'Calc Smart'!N84,'Calc Avalanche'!N84,'Calc Snowball'!N84,'Calc Cashflow'!N84)
B79: =EDATE(Plan!$C$6,73) | C79: =CHOOSE(Plan!$K$5,'Calc Smart'!AE85,'Calc Avalanche'!AE85,'Calc Snowball'!AE85,'Calc Cashflow'!AE85) | D79: =CHOOSE(Plan!$K$5,'Calc Smart'!AD85,'Calc Avalanche'!AD85,'Calc Snowball'!AD85,'Calc Cashflow'!AD85) | E79: =CHOOSE(Plan!$K$5,COUNTIF('Calc Smart'!C85:N85,">0"),COUNTIF('Calc Avalanche'!C85:N85,">0"),COUNTIF('Calc Snowball'!C85:N85,">0"),COUNTIF('Calc Cashflow'!C85:N85,">0")) | F79: =CHOOSE(Plan!$K$5,'Calc Smart'!C85,'Calc Avalanche'!C85,'Calc Snowball'!C85,'Calc Cashflow'!C85) | G79: =CHOOSE(Plan!$K$5,'Calc Smart'!D85,'Calc Avalanche'!D85,'Calc Snowball'!D85,'Calc Cashflow'!D85) | H79: =CHOOSE(Plan!$K$5,'Calc Smart'!E85,'Calc Avalanche'!E85,'Calc Snowball'!E85,'Calc Cashflow'!E85) | I79: =CHOOSE(Plan!$K$5,'Calc Smart'!F85,'Calc Avalanche'!F85,'Calc Snowball'!F85,'Calc Cashflow'!F85) | J79: =CHOOSE(Plan!$K$5,'Calc Smart'!G85,'Calc Avalanche'!G85,'Calc Snowball'!G85,'Calc Cashflow'!G85) | K79: =CHOOSE(Plan!$K$5,'Calc Smart'!H85,'Calc Avalanche'!H85,'Calc Snowball'!H85,'Calc Cashflow'!H85) | L79: =CHOOSE(Plan!$K$5,'Calc Smart'!I85,'Calc Avalanche'!I85,'Calc Snowball'!I85,'Calc Cashflow'!I85) | M79: =CHOOSE(Plan!$K$5,'Calc Smart'!J85,'Calc Avalanche'!J85,'Calc Snowball'!J85,'Calc Cashflow'!J85) | ... Q79: =CHOOSE(Plan!$K$5,'Calc Smart'!N85,'Calc Avalanche'!N85,'Calc Snowball'!N85,'Calc Cashflow'!N85)
B80: =EDATE(Plan!$C$6,74) | C80: =CHOOSE(Plan!$K$5,'Calc Smart'!AE86,'Calc Avalanche'!AE86,'Calc Snowball'!AE86,'Calc Cashflow'!AE86) | D80: =CHOOSE(Plan!$K$5,'Calc Smart'!AD86,'Calc Avalanche'!AD86,'Calc Snowball'!AD86,'Calc Cashflow'!AD86) | E80: =CHOOSE(Plan!$K$5,COUNTIF('Calc Smart'!C86:N86,">0"),COUNTIF('Calc Avalanche'!C86:N86,">0"),COUNTIF('Calc Snowball'!C86:N86,">0"),COUNTIF('Calc Cashflow'!C86:N86,">0")) | F80: =CHOOSE(Plan!$K$5,'Calc Smart'!C86,'Calc Avalanche'!C86,'Calc Snowball'!C86,'Calc Cashflow'!C86) | G80: =CHOOSE(Plan!$K$5,'Calc Smart'!D86,'Calc Avalanche'!D86,'Calc Snowball'!D86,'Calc Cashflow'!D86) | H80: =CHOOSE(Plan!$K$5,'Calc Smart'!E86,'Calc Avalanche'!E86,'Calc Snowball'!E86,'Calc Cashflow'!E86) | I80: =CHOOSE(Plan!$K$5,'Calc Smart'!F86,'Calc Avalanche'!F86,'Calc Snowball'!F86,'Calc Cashflow'!F86) | J80: =CHOOSE(Plan!$K$5,'Calc Smart'!G86,'Calc Avalanche'!G86,'Calc Snowball'!G86,'Calc Cashflow'!G86) | K80: =CHOOSE(Plan!$K$5,'Calc Smart'!H86,'Calc Avalanche'!H86,'Calc Snowball'!H86,'Calc Cashflow'!H86) | L80: =CHOOSE(Plan!$K$5,'Calc Smart'!I86,'Calc Avalanche'!I86,'Calc Snowball'!I86,'Calc Cashflow'!I86) | M80: =CHOOSE(Plan!$K$5,'Calc Smart'!J86,'Calc Avalanche'!J86,'Calc Snowball'!J86,'Calc Cashflow'!J86) | ... Q80: =CHOOSE(Plan!$K$5,'Calc Smart'!N86,'Calc Avalanche'!N86,'Calc Snowball'!N86,'Calc Cashflow'!N86)
B81: =EDATE(Plan!$C$6,75) | C81: =CHOOSE(Plan!$K$5,'Calc Smart'!AE87,'Calc Avalanche'!AE87,'Calc Snowball'!AE87,'Calc Cashflow'!AE87) | D81: =CHOOSE(Plan!$K$5,'Calc Smart'!AD87,'Calc Avalanche'!AD87,'Calc Snowball'!AD87,'Calc Cashflow'!AD87) | E81: =CHOOSE(Plan!$K$5,COUNTIF('Calc Smart'!C87:N87,">0"),COUNTIF('Calc Avalanche'!C87:N87,">0"),COUNTIF('Calc Snowball'!C87:N87,">0"),COUNTIF('Calc Cashflow'!C87:N87,">0")) | F81: =CHOOSE(Plan!$K$5,'Calc Smart'!C87,'Calc Avalanche'!C87,'Calc Snowball'!C87,'Calc Cashflow'!C87) | G81: =CHOOSE(Plan!$K$5,'Calc Smart'!D87,'Calc Avalanche'!D87,'Calc Snowball'!D87,'Calc Cashflow'!D87) | H81: =CHOOSE(Plan!$K$5,'Calc Smart'!E87,'Calc Avalanche'!E87,'Calc Snowball'!E87,'Calc Cashflow'!E87) | I81: =CHOOSE(Plan!$K$5,'Calc Smart'!F87,'Calc Avalanche'!F87,'Calc Snowball'!F87,'Calc Cashflow'!F87) | J81: =CHOOSE(Plan!$K$5,'Calc Smart'!G87,'Calc Avalanche'!G87,'Calc Snowball'!G87,'Calc Cashflow'!G87) | K81: =CHOOSE(Plan!$K$5,'Calc Smart'!H87,'Calc Avalanche'!H87,'Calc Snowball'!H87,'Calc Cashflow'!H87) | L81: =CHOOSE(Plan!$K$5,'Calc Smart'!I87,'Calc Avalanche'!I87,'Calc Snowball'!I87,'Calc Cashflow'!I87) | M81: =CHOOSE(Plan!$K$5,'Calc Smart'!J87,'Calc Avalanche'!J87,'Calc Snowball'!J87,'Calc Cashflow'!J87) | ... Q81: =CHOOSE(Plan!$K$5,'Calc Smart'!N87,'Calc Avalanche'!N87,'Calc Snowball'!N87,'Calc Cashflow'!N87)
B82: =EDATE(Plan!$C$6,76) | C82: =CHOOSE(Plan!$K$5,'Calc Smart'!AE88,'Calc Avalanche'!AE88,'Calc Snowball'!AE88,'Calc Cashflow'!AE88) | D82: =CHOOSE(Plan!$K$5,'Calc Smart'!AD88,'Calc Avalanche'!AD88,'Calc Snowball'!AD88,'Calc Cashflow'!AD88) | E82: =CHOOSE(Plan!$K$5,COUNTIF('Calc Smart'!C88:N88,">0"),COUNTIF('Calc Avalanche'!C88:N88,">0"),COUNTIF('Calc Snowball'!C88:N88,">0"),COUNTIF('Calc Cashflow'!C88:N88,">0")) | F82: =CHOOSE(Plan!$K$5,'Calc Smart'!C88,'Calc Avalanche'!C88,'Calc Snowball'!C88,'Calc Cashflow'!C88) | G82: =CHOOSE(Plan!$K$5,'Calc Smart'!D88,'Calc Avalanche'!D88,'Calc Snowball'!D88,'Calc Cashflow'!D88) | H82: =CHOOSE(Plan!$K$5,'Calc Smart'!E88,'Calc Avalanche'!E88,'Calc Snowball'!E88,'Calc Cashflow'!E88) | I82: =CHOOSE(Plan!$K$5,'Calc Smart'!F88,'Calc Avalanche'!F88,'Calc Snowball'!F88,'Calc Cashflow'!F88) | J82: =CHOOSE(Plan!$K$5,'Calc Smart'!G88,'Calc Avalanche'!G88,'Calc Snowball'!G88,'Calc Cashflow'!G88) | K82: =CHOOSE(Plan!$K$5,'Calc Smart'!H88,'Calc Avalanche'!H88,'Calc Snowball'!H88,'Calc Cashflow'!H88) | L82: =CHOOSE(Plan!$K$5,'Calc Smart'!I88,'Calc Avalanche'!I88,'Calc Snowball'!I88,'Calc Cashflow'!I88) | M82: =CHOOSE(Plan!$K$5,'Calc Smart'!J88,'Calc Avalanche'!J88,'Calc Snowball'!J88,'Calc Cashflow'!J88) | ... Q82: =CHOOSE(Plan!$K$5,'Calc Smart'!N88,'Calc Avalanche'!N88,'Calc Snowball'!N88,'Calc Cashflow'!N88)
B83: =EDATE(Plan!$C$6,77) | C83: =CHOOSE(Plan!$K$5,'Calc Smart'!AE89,'Calc Avalanche'!AE89,'Calc Snowball'!AE89,'Calc Cashflow'!AE89) | D83: =CHOOSE(Plan!$K$5,'Calc Smart'!AD89,'Calc Avalanche'!AD89,'Calc Snowball'!AD89,'Calc Cashflow'!AD89) | E83: =CHOOSE(Plan!$K$5,COUNTIF('Calc Smart'!C89:N89,">0"),COUNTIF('Calc Avalanche'!C89:N89,">0"),COUNTIF('Calc Snowball'!C89:N89,">0"),COUNTIF('Calc Cashflow'!C89:N89,">0")) | F83: =CHOOSE(Plan!$K$5,'Calc Smart'!C89,'Calc Avalanche'!C89,'Calc Snowball'!C89,'Calc Cashflow'!C89) | G83: =CHOOSE(Plan!$K$5,'Calc Smart'!D89,'Calc Avalanche'!D89,'Calc Snowball'!D89,'Calc Cashflow'!D89) | H83: =CHOOSE(Plan!$K$5,'Calc Smart'!E89,'Calc Avalanche'!E89,'Calc Snowball'!E89,'Calc Cashflow'!E89) | I83: =CHOOSE(Plan!$K$5,'Calc Smart'!F89,'Calc Avalanche'!F89,'Calc Snowball'!F89,'Calc Cashflow'!F89) | J83: =CHOOSE(Plan!$K$5,'Calc Smart'!G89,'Calc Avalanche'!G89,'Calc Snowball'!G89,'Calc Cashflow'!G89) | K83: =CHOOSE(Plan!$K$5,'Calc Smart'!H89,'Calc Avalanche'!H89,'Calc Snowball'!H89,'Calc Cashflow'!H89) | L83: =CHOOSE(Plan!$K$5,'Calc Smart'!I89,'Calc Avalanche'!I89,'Calc Snowball'!I89,'Calc Cashflow'!I89) | M83: =CHOOSE(Plan!$K$5,'Calc Smart'!J89,'Calc Avalanche'!J89,'Calc Snowball'!J89,'Calc Cashflow'!J89) | ... Q83: =CHOOSE(Plan!$K$5,'Calc Smart'!N89,'Calc Avalanche'!N89,'Calc Snowball'!N89,'Calc Cashflow'!N89)
B84: =EDATE(Plan!$C$6,78) | C84: =CHOOSE(Plan!$K$5,'Calc Smart'!AE90,'Calc Avalanche'!AE90,'Calc Snowball'!AE90,'Calc Cashflow'!AE90) | D84: =CHOOSE(Plan!$K$5,'Calc Smart'!AD90,'Calc Avalanche'!AD90,'Calc Snowball'!AD90,'Calc Cashflow'!AD90) | E84: =CHOOSE(Plan!$K$5,COUNTIF('Calc Smart'!C90:N90,">0"),COUNTIF('Calc Avalanche'!C90:N90,">0"),COUNTIF('Calc Snowball'!C90:N90,">0"),COUNTIF('Calc Cashflow'!C90:N90,">0")) | F84: =CHOOSE(Plan!$K$5,'Calc Smart'!C90,'Calc Avalanche'!C90,'Calc Snowball'!C90,'Calc Cashflow'!C90) | G84: =CHOOSE(Plan!$K$5,'Calc Smart'!D90,'Calc Avalanche'!D90,'Calc Snowball'!D90,'Calc Cashflow'!D90) | H84: =CHOOSE(Plan!$K$5,'Calc Smart'!E90,'Calc Avalanche'!E90,'Calc Snowball'!E90,'Calc Cashflow'!E90) | I84: =CHOOSE(Plan!$K$5,'Calc Smart'!F90,'Calc Avalanche'!F90,'Calc Snowball'!F90,'Calc Cashflow'!F90) | J84: =CHOOSE(Plan!$K$5,'Calc Smart'!G90,'Calc Avalanche'!G90,'Calc Snowball'!G90,'Calc Cashflow'!G90) | K84: =CHOOSE(Plan!$K$5,'Calc Smart'!H90,'Calc Avalanche'!H90,'Calc Snowball'!H90,'Calc Cashflow'!H90) | L84: =CHOOSE(Plan!$K$5,'Calc Smart'!I90,'Calc Avalanche'!I90,'Calc Snowball'!I90,'Calc Cashflow'!I90) | M84: =CHOOSE(Plan!$K$5,'Calc Smart'!J90,'Calc Avalanche'!J90,'Calc Snowball'!J90,'Calc Cashflow'!J90) | ... Q84: =CHOOSE(Plan!$K$5,'Calc Smart'!N90,'Calc Avalanche'!N90,'Calc Snowball'!N90,'Calc Cashflow'!N90)
B85: =EDATE(Plan!$C$6,79) | C85: =CHOOSE(Plan!$K$5,'Calc Smart'!AE91,'Calc Avalanche'!AE91,'Calc Snowball'!AE91,'Calc Cashflow'!AE91) | D85: =CHOOSE(Plan!$K$5,'Calc Smart'!AD91,'Calc Avalanche'!AD91,'Calc Snowball'!AD91,'Calc Cashflow'!AD91) | E85: =CHOOSE(Plan!$K$5,COUNTIF('Calc Smart'!C91:N91,">0"),COUNTIF('Calc Avalanche'!C91:N91,">0"),COUNTIF('Calc Snowball'!C91:N91,">0"),COUNTIF('Calc Cashflow'!C91:N91,">0")) | F85: =CHOOSE(Plan!$K$5,'Calc Smart'!C91,'Calc Avalanche'!C91,'Calc Snowball'!C91,'Calc Cashflow'!C91) | G85: =CHOOSE(Plan!$K$5,'Calc Smart'!D91,'Calc Avalanche'!D91,'Calc Snowball'!D91,'Calc Cashflow'!D91) | H85: =CHOOSE(Plan!$K$5,'Calc Smart'!E91,'Calc Avalanche'!E91,'Calc Snowball'!E91,'Calc Cashflow'!E91) | I85: =CHOOSE(Plan!$K$5,'Calc Smart'!F91,'Calc Avalanche'!F91,'Calc Snowball'!F91,'Calc Cashflow'!F91) | J85: =CHOOSE(Plan!$K$5,'Calc Smart'!G91,'Calc Avalanche'!G91,'Calc Snowball'!G91,'Calc Cashflow'!G91) | K85: =CHOOSE(Plan!$K$5,'Calc Smart'!H91,'Calc Avalanche'!H91,'Calc Snowball'!H91,'Calc Cashflow'!H91) | L85: =CHOOSE(Plan!$K$5,'Calc Smart'!I91,'Calc Avalanche'!I91,'Calc Snowball'!I91,'Calc Cashflow'!I91) | M85: =CHOOSE(Plan!$K$5,'Calc Smart'!J91,'Calc Avalanche'!J91,'Calc Snowball'!J91,'Calc Cashflow'!J91) | ... Q85: =CHOOSE(Plan!$K$5,'Calc Smart'!N91,'Calc Avalanche'!N91,'Calc Snowball'!N91,'Calc Cashflow'!N91)
B86: =EDATE(Plan!$C$6,80) | C86: =CHOOSE(Plan!$K$5,'Calc Smart'!AE92,'Calc Avalanche'!AE92,'Calc Snowball'!AE92,'Calc Cashflow'!AE92) | D86: =CHOOSE(Plan!$K$5,'Calc Smart'!AD92,'Calc Avalanche'!AD92,'Calc Snowball'!AD92,'Calc Cashflow'!AD92) | E86: =CHOOSE(Plan!$K$5,COUNTIF('Calc Smart'!C92:N92,">0"),COUNTIF('Calc Avalanche'!C92:N92,">0"),COUNTIF('Calc Snowball'!C92:N92,">0"),COUNTIF('Calc Cashflow'!C92:N92,">0")) | F86: =CHOOSE(Plan!$K$5,'Calc Smart'!C92,'Calc Avalanche'!C92,'Calc Snowball'!C92,'Calc Cashflow'!C92) | G86: =CHOOSE(Plan!$K$5,'Calc Smart'!D92,'Calc Avalanche'!D92,'Calc Snowball'!D92,'Calc Cashflow'!D92) | H86: =CHOOSE(Plan!$K$5,'Calc Smart'!E92,'Calc Avalanche'!E92,'Calc Snowball'!E92,'Calc Cashflow'!E92) | I86: =CHOOSE(Plan!$K$5,'Calc Smart'!F92,'Calc Avalanche'!F92,'Calc Snowball'!F92,'Calc Cashflow'!F92) | J86: =CHOOSE(Plan!$K$5,'Calc Smart'!G92,'Calc Avalanche'!G92,'Calc Snowball'!G92,'Calc Cashflow'!G92) | K86: =CHOOSE(Plan!$K$5,'Calc Smart'!H92,'Calc Avalanche'!H92,'Calc Snowball'!H92,'Calc Cashflow'!H92) | L86: =CHOOSE(Plan!$K$5,'Calc Smart'!I92,'Calc Avalanche'!I92,'Calc Snowball'!I92,'Calc Cashflow'!I92) | M86: =CHOOSE(Plan!$K$5,'Calc Smart'!J92,'Calc Avalanche'!J92,'Calc Snowball'!J92,'Calc Cashflow'!J92) | ... Q86: =CHOOSE(Plan!$K$5,'Calc Smart'!N92,'Calc Avalanche'!N92,'Calc Snowball'!N92,'Calc Cashflow'!N92)
B87: =EDATE(Plan!$C$6,81) | C87: =CHOOSE(Plan!$K$5,'Calc Smart'!AE93,'Calc Avalanche'!AE93,'Calc Snowball'!AE93,'Calc Cashflow'!AE93) | D87: =CHOOSE(Plan!$K$5,'Calc Smart'!AD93,'Calc Avalanche'!AD93,'Calc Snowball'!AD93,'Calc Cashflow'!AD93) | E87: =CHOOSE(Plan!$K$5,COUNTIF('Calc Smart'!C93:N93,">0"),COUNTIF('Calc Avalanche'!C93:N93,">0"),COUNTIF('Calc Snowball'!C93:N93,">0"),COUNTIF('Calc Cashflow'!C93:N93,">0")) | F87: =CHOOSE(Plan!$K$5,'Calc Smart'!C93,'Calc Avalanche'!C93,'Calc Snowball'!C93,'Calc Cashflow'!C93) | G87: =CHOOSE(Plan!$K$5,'Calc Smart'!D93,'Calc Avalanche'!D93,'Calc Snowball'!D93,'Calc Cashflow'!D93) | H87: =CHOOSE(Plan!$K$5,'Calc Smart'!E93,'Calc Avalanche'!E93,'Calc Snowball'!E93,'Calc Cashflow'!E93) | I87: =CHOOSE(Plan!$K$5,'Calc Smart'!F93,'Calc Avalanche'!F93,'Calc Snowball'!F93,'Calc Cashflow'!F93) | J87: =CHOOSE(Plan!$K$5,'Calc Smart'!G93,'Calc Avalanche'!G93,'Calc Snowball'!G93,'Calc Cashflow'!G93) | K87: =CHOOSE(Plan!$K$5,'Calc Smart'!H93,'Calc Avalanche'!H93,'Calc Snowball'!H93,'Calc Cashflow'!H93) | L87: =CHOOSE(Plan!$K$5,'Calc Smart'!I93,'Calc Avalanche'!I93,'Calc Snowball'!I93,'Calc Cashflow'!I93) | M87: =CHOOSE(Plan!$K$5,'Calc Smart'!J93,'Calc Avalanche'!J93,'Calc Snowball'!J93,'Calc Cashflow'!J93) | ... Q87: =CHOOSE(Plan!$K$5,'Calc Smart'!N93,'Calc Avalanche'!N93,'Calc Snowball'!N93,'Calc Cashflow'!N93)
B88: =EDATE(Plan!$C$6,82) | C88: =CHOOSE(Plan!$K$5,'Calc Smart'!AE94,'Calc Avalanche'!AE94,'Calc Snowball'!AE94,'Calc Cashflow'!AE94) | D88: =CHOOSE(Plan!$K$5,'Calc Smart'!AD94,'Calc Avalanche'!AD94,'Calc Snowball'!AD94,'Calc Cashflow'!AD94) | E88: =CHOOSE(Plan!$K$5,COUNTIF('Calc Smart'!C94:N94,">0"),COUNTIF('Calc Avalanche'!C94:N94,">0"),COUNTIF('Calc Snowball'!C94:N94,">0"),COUNTIF('Calc Cashflow'!C94:N94,">0")) | F88: =CHOOSE(Plan!$K$5,'Calc Smart'!C94,'Calc Avalanche'!C94,'Calc Snowball'!C94,'Calc Cashflow'!C94) | G88: =CHOOSE(Plan!$K$5,'Calc Smart'!D94,'Calc Avalanche'!D94,'Calc Snowball'!D94,'Calc Cashflow'!D94) | H88: =CHOOSE(Plan!$K$5,'Calc Smart'!E94,'Calc Avalanche'!E94,'Calc Snowball'!E94,'Calc Cashflow'!E94) | I88: =CHOOSE(Plan!$K$5,'Calc Smart'!F94,'Calc Avalanche'!F94,'Calc Snowball'!F94,'Calc Cashflow'!F94) | J88: =CHOOSE(Plan!$K$5,'Calc Smart'!G94,'Calc Avalanche'!G94,'Calc Snowball'!G94,'Calc Cashflow'!G94) | K88: =CHOOSE(Plan!$K$5,'Calc Smart'!H94,'Calc Avalanche'!H94,'Calc Snowball'!H94,'Calc Cashflow'!H94) | L88: =CHOOSE(Plan!$K$5,'Calc Smart'!I94,'Calc Avalanche'!I94,'Calc Snowball'!I94,'Calc Cashflow'!I94) | M88: =CHOOSE(Plan!$K$5,'Calc Smart'!J94,'Calc Avalanche'!J94,'Calc Snowball'!J94,'Calc Cashflow'!J94) | ... Q88: =CHOOSE(Plan!$K$5,'Calc Smart'!N94,'Calc Avalanche'!N94,'Calc Snowball'!N94,'Calc Cashflow'!N94)
B89: =EDATE(Plan!$C$6,83) | C89: =CHOOSE(Plan!$K$5,'Calc Smart'!AE95,'Calc Avalanche'!AE95,'Calc Snowball'!AE95,'Calc Cashflow'!AE95) | D89: =CHOOSE(Plan!$K$5,'Calc Smart'!AD95,'Calc Avalanche'!AD95,'Calc Snowball'!AD95,'Calc Cashflow'!AD95) | E89: =CHOOSE(Plan!$K$5,COUNTIF('Calc Smart'!C95:N95,">0"),COUNTIF('Calc Avalanche'!C95:N95,">0"),COUNTIF('Calc Snowball'!C95:N95,">0"),COUNTIF('Calc Cashflow'!C95:N95,">0")) | F89: =CHOOSE(Plan!$K$5,'Calc Smart'!C95,'Calc Avalanche'!C95,'Calc Snowball'!C95,'Calc Cashflow'!C95) | G89: =CHOOSE(Plan!$K$5,'Calc Smart'!D95,'Calc Avalanche'!D95,'Calc Snowball'!D95,'Calc Cashflow'!D95) | H89: =CHOOSE(Plan!$K$5,'Calc Smart'!E95,'Calc Avalanche'!E95,'Calc Snowball'!E95,'Calc Cashflow'!E95) | I89: =CHOOSE(Plan!$K$5,'Calc Smart'!F95,'Calc Avalanche'!F95,'Calc Snowball'!F95,'Calc Cashflow'!F95) | J89: =CHOOSE(Plan!$K$5,'Calc Smart'!G95,'Calc Avalanche'!G95,'Calc Snowball'!G95,'Calc Cashflow'!G95) | K89: =CHOOSE(Plan!$K$5,'Calc Smart'!H95,'Calc Avalanche'!H95,'Calc Snowball'!H95,'Calc Cashflow'!H95) | L89: =CHOOSE(Plan!$K$5,'Calc Smart'!I95,'Calc Avalanche'!I95,'Calc Snowball'!I95,'Calc Cashflow'!I95) | M89: =CHOOSE(Plan!$K$5,'Calc Smart'!J95,'Calc Avalanche'!J95,'Calc Snowball'!J95,'Calc Cashflow'!J95) | ... Q89: =CHOOSE(Plan!$K$5,'Calc Smart'!N95,'Calc Avalanche'!N95,'Calc Snowball'!N95,'Calc Cashflow'!N95)
B90: =EDATE(Plan!$C$6,84) | C90: =CHOOSE(Plan!$K$5,'Calc Smart'!AE96,'Calc Avalanche'!AE96,'Calc Snowball'!AE96,'Calc Cashflow'!AE96) | D90: =CHOOSE(Plan!$K$5,'Calc Smart'!AD96,'Calc Avalanche'!AD96,'Calc Snowball'!AD96,'Calc Cashflow'!AD96) | E90: =CHOOSE(Plan!$K$5,COUNTIF('Calc Smart'!C96:N96,">0"),COUNTIF('Calc Avalanche'!C96:N96,">0"),COUNTIF('Calc Snowball'!C96:N96,">0"),COUNTIF('Calc Cashflow'!C96:N96,">0")) | F90: =CHOOSE(Plan!$K$5,'Calc Smart'!C96,'Calc Avalanche'!C96,'Calc Snowball'!C96,'Calc Cashflow'!C96) | G90: =CHOOSE(Plan!$K$5,'Calc Smart'!D96,'Calc Avalanche'!D96,'Calc Snowball'!D96,'Calc Cashflow'!D96) | H90: =CHOOSE(Plan!$K$5,'Calc Smart'!E96,'Calc Avalanche'!E96,'Calc Snowball'!E96,'Calc Cashflow'!E96) | I90: =CHOOSE(Plan!$K$5,'Calc Smart'!F96,'Calc Avalanche'!F96,'Calc Snowball'!F96,'Calc Cashflow'!F96) | J90: =CHOOSE(Plan!$K$5,'Calc Smart'!G96,'Calc Avalanche'!G96,'Calc Snowball'!G96,'Calc Cashflow'!G96) | K90: =CHOOSE(Plan!$K$5,'Calc Smart'!H96,'Calc Avalanche'!H96,'Calc Snowball'!H96,'Calc Cashflow'!H96) | L90: =CHOOSE(Plan!$K$5,'Calc Smart'!I96,'Calc Avalanche'!I96,'Calc Snowball'!I96,'Calc Cashflow'!I96) | M90: =CHOOSE(Plan!$K$5,'Calc Smart'!J96,'Calc Avalanche'!J96,'Calc Snowball'!J96,'Calc Cashflow'!J96) | ... Q90: =CHOOSE(Plan!$K$5,'Calc Smart'!N96,'Calc Avalanche'!N96,'Calc Snowball'!N96,'Calc Cashflow'!N96)
B91: =EDATE(Plan!$C$6,85) | C91: =CHOOSE(Plan!$K$5,'Calc Smart'!AE97,'Calc Avalanche'!AE97,'Calc Snowball'!AE97,'Calc Cashflow'!AE97) | D91: =CHOOSE(Plan!$K$5,'Calc Smart'!AD97,'Calc Avalanche'!AD97,'Calc Snowball'!AD97,'Calc Cashflow'!AD97) | E91: =CHOOSE(Plan!$K$5,COUNTIF('Calc Smart'!C97:N97,">0"),COUNTIF('Calc Avalanche'!C97:N97,">0"),COUNTIF('Calc Snowball'!C97:N97,">0"),COUNTIF('Calc Cashflow'!C97:N97,">0")) | F91: =CHOOSE(Plan!$K$5,'Calc Smart'!C97,'Calc Avalanche'!C97,'Calc Snowball'!C97,'Calc Cashflow'!C97) | G91: =CHOOSE(Plan!$K$5,'Calc Smart'!D97,'Calc Avalanche'!D97,'Calc Snowball'!D97,'Calc Cashflow'!D97) | H91: =CHOOSE(Plan!$K$5,'Calc Smart'!E97,'Calc Avalanche'!E97,'Calc Snowball'!E97,'Calc Cashflow'!E97) | I91: =CHOOSE(Plan!$K$5,'Calc Smart'!F97,'Calc Avalanche'!F97,'Calc Snowball'!F97,'Calc Cashflow'!F97) | J91: =CHOOSE(Plan!$K$5,'Calc Smart'!G97,'Calc Avalanche'!G97,'Calc Snowball'!G97,'Calc Cashflow'!G97) | K91: =CHOOSE(Plan!$K$5,'Calc Smart'!H97,'Calc Avalanche'!H97,'Calc Snowball'!H97,'Calc Cashflow'!H97) | L91: =CHOOSE(Plan!$K$5,'Calc Smart'!I97,'Calc Avalanche'!I97,'Calc Snowball'!I97,'Calc Cashflow'!I97) | M91: =CHOOSE(Plan!$K$5,'Calc Smart'!J97,'Calc Avalanche'!J97,'Calc Snowball'!J97,'Calc Cashflow'!J97) | ... Q91: =CHOOSE(Plan!$K$5,'Calc Smart'!N97,'Calc Avalanche'!N97,'Calc Snowball'!N97,'Calc Cashflow'!N97)
B92: =EDATE(Plan!$C$6,86) | C92: =CHOOSE(Plan!$K$5,'Calc Smart'!AE98,'Calc Avalanche'!AE98,'Calc Snowball'!AE98,'Calc Cashflow'!AE98) | D92: =CHOOSE(Plan!$K$5,'Calc Smart'!AD98,'Calc Avalanche'!AD98,'Calc Snowball'!AD98,'Calc Cashflow'!AD98) | E92: =CHOOSE(Plan!$K$5,COUNTIF('Calc Smart'!C98:N98,">0"),COUNTIF('Calc Avalanche'!C98:N98,">0"),COUNTIF('Calc Snowball'!C98:N98,">0"),COUNTIF('Calc Cashflow'!C98:N98,">0")) | F92: =CHOOSE(Plan!$K$5,'Calc Smart'!C98,'Calc Avalanche'!C98,'Calc Snowball'!C98,'Calc Cashflow'!C98) | G92: =CHOOSE(Plan!$K$5,'Calc Smart'!D98,'Calc Avalanche'!D98,'Calc Snowball'!D98,'Calc Cashflow'!D98) | H92: =CHOOSE(Plan!$K$5,'Calc Smart'!E98,'Calc Avalanche'!E98,'Calc Snowball'!E98,'Calc Cashflow'!E98) | I92: =CHOOSE(Plan!$K$5,'Calc Smart'!F98,'Calc Avalanche'!F98,'Calc Snowball'!F98,'Calc Cashflow'!F98) | J92: =CHOOSE(Plan!$K$5,'Calc Smart'!G98,'Calc Avalanche'!G98,'Calc Snowball'!G98,'Calc Cashflow'!G98) | K92: =CHOOSE(Plan!$K$5,'Calc Smart'!H98,'Calc Avalanche'!H98,'Calc Snowball'!H98,'Calc Cashflow'!H98) | L92: =CHOOSE(Plan!$K$5,'Calc Smart'!I98,'Calc Avalanche'!I98,'Calc Snowball'!I98,'Calc Cashflow'!I98) | M92: =CHOOSE(Plan!$K$5,'Calc Smart'!J98,'Calc Avalanche'!J98,'Calc Snowball'!J98,'Calc Cashflow'!J98) | ... Q92: =CHOOSE(Plan!$K$5,'Calc Smart'!N98,'Calc Avalanche'!N98,'Calc Snowball'!N98,'Calc Cashflow'!N98)
B93: =EDATE(Plan!$C$6,87) | C93: =CHOOSE(Plan!$K$5,'Calc Smart'!AE99,'Calc Avalanche'!AE99,'Calc Snowball'!AE99,'Calc Cashflow'!AE99) | D93: =CHOOSE(Plan!$K$5,'Calc Smart'!AD99,'Calc Avalanche'!AD99,'Calc Snowball'!AD99,'Calc Cashflow'!AD99) | E93: =CHOOSE(Plan!$K$5,COUNTIF('Calc Smart'!C99:N99,">0"),COUNTIF('Calc Avalanche'!C99:N99,">0"),COUNTIF('Calc Snowball'!C99:N99,">0"),COUNTIF('Calc Cashflow'!C99:N99,">0")) | F93: =CHOOSE(Plan!$K$5,'Calc Smart'!C99,'Calc Avalanche'!C99,'Calc Snowball'!C99,'Calc Cashflow'!C99) | G93: =CHOOSE(Plan!$K$5,'Calc Smart'!D99,'Calc Avalanche'!D99,'Calc Snowball'!D99,'Calc Cashflow'!D99) | H93: =CHOOSE(Plan!$K$5,'Calc Smart'!E99,'Calc Avalanche'!E99,'Calc Snowball'!E99,'Calc Cashflow'!E99) | I93: =CHOOSE(Plan!$K$5,'Calc Smart'!F99,'Calc Avalanche'!F99,'Calc Snowball'!F99,'Calc Cashflow'!F99) | J93: =CHOOSE(Plan!$K$5,'Calc Smart'!G99,'Calc Avalanche'!G99,'Calc Snowball'!G99,'Calc Cashflow'!G99) | K93: =CHOOSE(Plan!$K$5,'Calc Smart'!H99,'Calc Avalanche'!H99,'Calc Snowball'!H99,'Calc Cashflow'!H99) | L93: =CHOOSE(Plan!$K$5,'Calc Smart'!I99,'Calc Avalanche'!I99,'Calc Snowball'!I99,'Calc Cashflow'!I99) | M93: =CHOOSE(Plan!$K$5,'Calc Smart'!J99,'Calc Avalanche'!J99,'Calc Snowball'!J99,'Calc Cashflow'!J99) | ... Q93: =CHOOSE(Plan!$K$5,'Calc Smart'!N99,'Calc Avalanche'!N99,'Calc Snowball'!N99,'Calc Cashflow'!N99)
B94: =EDATE(Plan!$C$6,88) | C94: =CHOOSE(Plan!$K$5,'Calc Smart'!AE100,'Calc Avalanche'!AE100,'Calc Snowball'!AE100,'Calc Cashflow'!AE100) | D94: =CHOOSE(Plan!$K$5,'Calc Smart'!AD100,'Calc Avalanche'!AD100,'Calc Snowball'!AD100,'Calc Cashflow'!AD100) | E94: =CHOOSE(Plan!$K$5,COUNTIF('Calc Smart'!C100:N100,">0"),COUNTIF('Calc Avalanche'!C100:N100,">0"),COUNTIF('Calc Snowball'!C100:N100,">0"),COUNTIF('Calc Cashflow'!C100:N100,">0")) | F94: =CHOOSE(Plan!$K$5,'Calc Smart'!C100,'Calc Avalanche'!C100,'Calc Snowball'!C100,'Calc Cashflow'!C100) | G94: =CHOOSE(Plan!$K$5,'Calc Smart'!D100,'Calc Avalanche'!D100,'Calc Snowball'!D100,'Calc Cashflow'!D100) | H94: =CHOOSE(Plan!$K$5,'Calc Smart'!E100,'Calc Avalanche'!E100,'Calc Snowball'!E100,'Calc Cashflow'!E100) | I94: =CHOOSE(Plan!$K$5,'Calc Smart'!F100,'Calc Avalanche'!F100,'Calc Snowball'!F100,'Calc Cashflow'!F100) | J94: =CHOOSE(Plan!$K$5,'Calc Smart'!G100,'Calc Avalanche'!G100,'Calc Snowball'!G100,'Calc Cashflow'!G100) | K94: =CHOOSE(Plan!$K$5,'Calc Smart'!H100,'Calc Avalanche'!H100,'Calc Snowball'!H100,'Calc Cashflow'!H100) | L94: =CHOOSE(Plan!$K$5,'Calc Smart'!I100,'Calc Avalanche'!I100,'Calc Snowball'!I100,'Calc Cashflow'!I100) | M94: =CHOOSE(Plan!$K$5,'Calc Smart'!J100,'Calc Avalanche'!J100,'Calc Snowball'!J100,'Calc Cashflow'!J100) | ... Q94: =CHOOSE(Plan!$K$5,'Calc Smart'!N100,'Calc Avalanche'!N100,'Calc Snowball'!N100,'Calc Cashflow'!N100)
B95: =EDATE(Plan!$C$6,89) | C95: =CHOOSE(Plan!$K$5,'Calc Smart'!AE101,'Calc Avalanche'!AE101,'Calc Snowball'!AE101,'Calc Cashflow'!AE101) | D95: =CHOOSE(Plan!$K$5,'Calc Smart'!AD101,'Calc Avalanche'!AD101,'Calc Snowball'!AD101,'Calc Cashflow'!AD101) | E95: =CHOOSE(Plan!$K$5,COUNTIF('Calc Smart'!C101:N101,">0"),COUNTIF('Calc Avalanche'!C101:N101,">0"),COUNTIF('Calc Snowball'!C101:N101,">0"),COUNTIF('Calc Cashflow'!C101:N101,">0")) | F95: =CHOOSE(Plan!$K$5,'Calc Smart'!C101,'Calc Avalanche'!C101,'Calc Snowball'!C101,'Calc Cashflow'!C101) | G95: =CHOOSE(Plan!$K$5,'Calc Smart'!D101,'Calc Avalanche'!D101,'Calc Snowball'!D101,'Calc Cashflow'!D101) | H95: =CHOOSE(Plan!$K$5,'Calc Smart'!E101,'Calc Avalanche'!E101,'Calc Snowball'!E101,'Calc Cashflow'!E101) | I95: =CHOOSE(Plan!$K$5,'Calc Smart'!F101,'Calc Avalanche'!F101,'Calc Snowball'!F101,'Calc Cashflow'!F101) | J95: =CHOOSE(Plan!$K$5,'Calc Smart'!G101,'Calc Avalanche'!G101,'Calc Snowball'!G101,'Calc Cashflow'!G101) | K95: =CHOOSE(Plan!$K$5,'Calc Smart'!H101,'Calc Avalanche'!H101,'Calc Snowball'!H101,'Calc Cashflow'!H101) | L95: =CHOOSE(Plan!$K$5,'Calc Smart'!I101,'Calc Avalanche'!I101,'Calc Snowball'!I101,'Calc Cashflow'!I101) | M95: =CHOOSE(Plan!$K$5,'Calc Smart'!J101,'Calc Avalanche'!J101,'Calc Snowball'!J101,'Calc Cashflow'!J101) | ... Q95: =CHOOSE(Plan!$K$5,'Calc Smart'!N101,'Calc Avalanche'!N101,'Calc Snowball'!N101,'Calc Cashflow'!N101)
B96: =EDATE(Plan!$C$6,90) | C96: =CHOOSE(Plan!$K$5,'Calc Smart'!AE102,'Calc Avalanche'!AE102,'Calc Snowball'!AE102,'Calc Cashflow'!AE102) | D96: =CHOOSE(Plan!$K$5,'Calc Smart'!AD102,'Calc Avalanche'!AD102,'Calc Snowball'!AD102,'Calc Cashflow'!AD102) | E96: =CHOOSE(Plan!$K$5,COUNTIF('Calc Smart'!C102:N102,">0"),COUNTIF('Calc Avalanche'!C102:N102,">0"),COUNTIF('Calc Snowball'!C102:N102,">0"),COUNTIF('Calc Cashflow'!C102:N102,">0")) | F96: =CHOOSE(Plan!$K$5,'Calc Smart'!C102,'Calc Avalanche'!C102,'Calc Snowball'!C102,'Calc Cashflow'!C102) | G96: =CHOOSE(Plan!$K$5,'Calc Smart'!D102,'Calc Avalanche'!D102,'Calc Snowball'!D102,'Calc Cashflow'!D102) | H96: =CHOOSE(Plan!$K$5,'Calc Smart'!E102,'Calc Avalanche'!E102,'Calc Snowball'!E102,'Calc Cashflow'!E102) | I96: =CHOOSE(Plan!$K$5,'Calc Smart'!F102,'Calc Avalanche'!F102,'Calc Snowball'!F102,'Calc Cashflow'!F102) | J96: =CHOOSE(Plan!$K$5,'Calc Smart'!G102,'Calc Avalanche'!G102,'Calc Snowball'!G102,'Calc Cashflow'!G102) | K96: =CHOOSE(Plan!$K$5,'Calc Smart'!H102,'Calc Avalanche'!H102,'Calc Snowball'!H102,'Calc Cashflow'!H102) | L96: =CHOOSE(Plan!$K$5,'Calc Smart'!I102,'Calc Avalanche'!I102,'Calc Snowball'!I102,'Calc Cashflow'!I102) | M96: =CHOOSE(Plan!$K$5,'Calc Smart'!J102,'Calc Avalanche'!J102,'Calc Snowball'!J102,'Calc Cashflow'!J102) | ... Q96: =CHOOSE(Plan!$K$5,'Calc Smart'!N102,'Calc Avalanche'!N102,'Calc Snowball'!N102,'Calc Cashflow'!N102)
B97: =EDATE(Plan!$C$6,91) | C97: =CHOOSE(Plan!$K$5,'Calc Smart'!AE103,'Calc Avalanche'!AE103,'Calc Snowball'!AE103,'Calc Cashflow'!AE103) | D97: =CHOOSE(Plan!$K$5,'Calc Smart'!AD103,'Calc Avalanche'!AD103,'Calc Snowball'!AD103,'Calc Cashflow'!AD103) | E97: =CHOOSE(Plan!$K$5,COUNTIF('Calc Smart'!C103:N103,">0"),COUNTIF('Calc Avalanche'!C103:N103,">0"),COUNTIF('Calc Snowball'!C103:N103,">0"),COUNTIF('Calc Cashflow'!C103:N103,">0")) | F97: =CHOOSE(Plan!$K$5,'Calc Smart'!C103,'Calc Avalanche'!C103,'Calc Snowball'!C103,'Calc Cashflow'!C103) | G97: =CHOOSE(Plan!$K$5,'Calc Smart'!D103,'Calc Avalanche'!D103,'Calc Snowball'!D103,'Calc Cashflow'!D103) | H97: =CHOOSE(Plan!$K$5,'Calc Smart'!E103,'Calc Avalanche'!E103,'Calc Snowball'!E103,'Calc Cashflow'!E103) | I97: =CHOOSE(Plan!$K$5,'Calc Smart'!F103,'Calc Avalanche'!F103,'Calc Snowball'!F103,'Calc Cashflow'!F103) | J97: =CHOOSE(Plan!$K$5,'Calc Smart'!G103,'Calc Avalanche'!G103,'Calc Snowball'!G103,'Calc Cashflow'!G103) | K97: =CHOOSE(Plan!$K$5,'Calc Smart'!H103,'Calc Avalanche'!H103,'Calc Snowball'!H103,'Calc Cashflow'!H103) | L97: =CHOOSE(Plan!$K$5,'Calc Smart'!I103,'Calc Avalanche'!I103,'Calc Snowball'!I103,'Calc Cashflow'!I103) | M97: =CHOOSE(Plan!$K$5,'Calc Smart'!J103,'Calc Avalanche'!J103,'Calc Snowball'!J103,'Calc Cashflow'!J103) | ... Q97: =CHOOSE(Plan!$K$5,'Calc Smart'!N103,'Calc Avalanche'!N103,'Calc Snowball'!N103,'Calc Cashflow'!N103)
B98: =EDATE(Plan!$C$6,92) | C98: =CHOOSE(Plan!$K$5,'Calc Smart'!AE104,'Calc Avalanche'!AE104,'Calc Snowball'!AE104,'Calc Cashflow'!AE104) | D98: =CHOOSE(Plan!$K$5,'Calc Smart'!AD104,'Calc Avalanche'!AD104,'Calc Snowball'!AD104,'Calc Cashflow'!AD104) | E98: =CHOOSE(Plan!$K$5,COUNTIF('Calc Smart'!C104:N104,">0"),COUNTIF('Calc Avalanche'!C104:N104,">0"),COUNTIF('Calc Snowball'!C104:N104,">0"),COUNTIF('Calc Cashflow'!C104:N104,">0")) | F98: =CHOOSE(Plan!$K$5,'Calc Smart'!C104,'Calc Avalanche'!C104,'Calc Snowball'!C104,'Calc Cashflow'!C104) | G98: =CHOOSE(Plan!$K$5,'Calc Smart'!D104,'Calc Avalanche'!D104,'Calc Snowball'!D104,'Calc Cashflow'!D104) | H98: =CHOOSE(Plan!$K$5,'Calc Smart'!E104,'Calc Avalanche'!E104,'Calc Snowball'!E104,'Calc Cashflow'!E104) | I98: =CHOOSE(Plan!$K$5,'Calc Smart'!F104,'Calc Avalanche'!F104,'Calc Snowball'!F104,'Calc Cashflow'!F104) | J98: =CHOOSE(Plan!$K$5,'Calc Smart'!G104,'Calc Avalanche'!G104,'Calc Snowball'!G104,'Calc Cashflow'!G104) | K98: =CHOOSE(Plan!$K$5,'Calc Smart'!H104,'Calc Avalanche'!H104,'Calc Snowball'!H104,'Calc Cashflow'!H104) | L98: =CHOOSE(Plan!$K$5,'Calc Smart'!I104,'Calc Avalanche'!I104,'Calc Snowball'!I104,'Calc Cashflow'!I104) | M98: =CHOOSE(Plan!$K$5,'Calc Smart'!J104,'Calc Avalanche'!J104,'Calc Snowball'!J104,'Calc Cashflow'!J104) | ... Q98: =CHOOSE(Plan!$K$5,'Calc Smart'!N104,'Calc Avalanche'!N104,'Calc Snowball'!N104,'Calc Cashflow'!N104)
B99: =EDATE(Plan!$C$6,93) | C99: =CHOOSE(Plan!$K$5,'Calc Smart'!AE105,'Calc Avalanche'!AE105,'Calc Snowball'!AE105,'Calc Cashflow'!AE105) | D99: =CHOOSE(Plan!$K$5,'Calc Smart'!AD105,'Calc Avalanche'!AD105,'Calc Snowball'!AD105,'Calc Cashflow'!AD105) | E99: =CHOOSE(Plan!$K$5,COUNTIF('Calc Smart'!C105:N105,">0"),COUNTIF('Calc Avalanche'!C105:N105,">0"),COUNTIF('Calc Snowball'!C105:N105,">0"),COUNTIF('Calc Cashflow'!C105:N105,">0")) | F99: =CHOOSE(Plan!$K$5,'Calc Smart'!C105,'Calc Avalanche'!C105,'Calc Snowball'!C105,'Calc Cashflow'!C105) | G99: =CHOOSE(Plan!$K$5,'Calc Smart'!D105,'Calc Avalanche'!D105,'Calc Snowball'!D105,'Calc Cashflow'!D105) | H99: =CHOOSE(Plan!$K$5,'Calc Smart'!E105,'Calc Avalanche'!E105,'Calc Snowball'!E105,'Calc Cashflow'!E105) | I99: =CHOOSE(Plan!$K$5,'Calc Smart'!F105,'Calc Avalanche'!F105,'Calc Snowball'!F105,'Calc Cashflow'!F105) | J99: =CHOOSE(Plan!$K$5,'Calc Smart'!G105,'Calc Avalanche'!G105,'Calc Snowball'!G105,'Calc Cashflow'!G105) | K99: =CHOOSE(Plan!$K$5,'Calc Smart'!H105,'Calc Avalanche'!H105,'Calc Snowball'!H105,'Calc Cashflow'!H105) | L99: =CHOOSE(Plan!$K$5,'Calc Smart'!I105,'Calc Avalanche'!I105,'Calc Snowball'!I105,'Calc Cashflow'!I105) | M99: =CHOOSE(Plan!$K$5,'Calc Smart'!J105,'Calc Avalanche'!J105,'Calc Snowball'!J105,'Calc Cashflow'!J105) | ... Q99: =CHOOSE(Plan!$K$5,'Calc Smart'!N105,'Calc Avalanche'!N105,'Calc Snowball'!N105,'Calc Cashflow'!N105)
B100: =EDATE(Plan!$C$6,94) | C100: =CHOOSE(Plan!$K$5,'Calc Smart'!AE106,'Calc Avalanche'!AE106,'Calc Snowball'!AE106,'Calc Cashflow'!AE106) | D100: =CHOOSE(Plan!$K$5,'Calc Smart'!AD106,'Calc Avalanche'!AD106,'Calc Snowball'!AD106,'Calc Cashflow'!AD106) | E100: =CHOOSE(Plan!$K$5,COUNTIF('Calc Smart'!C106:N106,">0"),COUNTIF('Calc Avalanche'!C106:N106,">0"),COUNTIF('Calc Snowball'!C106:N106,">0"),COUNTIF('Calc Cashflow'!C106:N106,">0")) | F100: =CHOOSE(Plan!$K$5,'Calc Smart'!C106,'Calc Avalanche'!C106,'Calc Snowball'!C106,'Calc Cashflow'!C106) | G100: =CHOOSE(Plan!$K$5,'Calc Smart'!D106,'Calc Avalanche'!D106,'Calc Snowball'!D106,'Calc Cashflow'!D106) | H100: =CHOOSE(Plan!$K$5,'Calc Smart'!E106,'Calc Avalanche'!E106,'Calc Snowball'!E106,'Calc Cashflow'!E106) | I100: =CHOOSE(Plan!$K$5,'Calc Smart'!F106,'Calc Avalanche'!F106,'Calc Snowball'!F106,'Calc Cashflow'!F106) | J100: =CHOOSE(Plan!$K$5,'Calc Smart'!G106,'Calc Avalanche'!G106,'Calc Snowball'!G106,'Calc Cashflow'!G106) | K100: =CHOOSE(Plan!$K$5,'Calc Smart'!H106,'Calc Avalanche'!H106,'Calc Snowball'!H106,'Calc Cashflow'!H106) | L100: =CHOOSE(Plan!$K$5,'Calc Smart'!I106,'Calc Avalanche'!I106,'Calc Snowball'!I106,'Calc Cashflow'!I106) | M100: =CHOOSE(Plan!$K$5,'Calc Smart'!J106,'Calc Avalanche'!J106,'Calc Snowball'!J106,'Calc Cashflow'!J106) | ... Q100: =CHOOSE(Plan!$K$5,'Calc Smart'!N106,'Calc Avalanche'!N106,'Calc Snowball'!N106,'Calc Cashflow'!N106)
B101: =EDATE(Plan!$C$6,95) | C101: =CHOOSE(Plan!$K$5,'Calc Smart'!AE107,'Calc Avalanche'!AE107,'Calc Snowball'!AE107,'Calc Cashflow'!AE107) | D101: =CHOOSE(Plan!$K$5,'Calc Smart'!AD107,'Calc Avalanche'!AD107,'Calc Snowball'!AD107,'Calc Cashflow'!AD107) | E101: =CHOOSE(Plan!$K$5,COUNTIF('Calc Smart'!C107:N107,">0"),COUNTIF('Calc Avalanche'!C107:N107,">0"),COUNTIF('Calc Snowball'!C107:N107,">0"),COUNTIF('Calc Cashflow'!C107:N107,">0")) | F101: =CHOOSE(Plan!$K$5,'Calc Smart'!C107,'Calc Avalanche'!C107,'Calc Snowball'!C107,'Calc Cashflow'!C107) | G101: =CHOOSE(Plan!$K$5,'Calc Smart'!D107,'Calc Avalanche'!D107,'Calc Snowball'!D107,'Calc Cashflow'!D107) | H101: =CHOOSE(Plan!$K$5,'Calc Smart'!E107,'Calc Avalanche'!E107,'Calc Snowball'!E107,'Calc Cashflow'!E107) | I101: =CHOOSE(Plan!$K$5,'Calc Smart'!F107,'Calc Avalanche'!F107,'Calc Snowball'!F107,'Calc Cashflow'!F107) | J101: =CHOOSE(Plan!$K$5,'Calc Smart'!G107,'Calc Avalanche'!G107,'Calc Snowball'!G107,'Calc Cashflow'!G107) | K101: =CHOOSE(Plan!$K$5,'Calc Smart'!H107,'Calc Avalanche'!H107,'Calc Snowball'!H107,'Calc Cashflow'!H107) | L101: =CHOOSE(Plan!$K$5,'Calc Smart'!I107,'Calc Avalanche'!I107,'Calc Snowball'!I107,'Calc Cashflow'!I107) | M101: =CHOOSE(Plan!$K$5,'Calc Smart'!J107,'Calc Avalanche'!J107,'Calc Snowball'!J107,'Calc Cashflow'!J107) | ... Q101: =CHOOSE(Plan!$K$5,'Calc Smart'!N107,'Calc Avalanche'!N107,'Calc Snowball'!N107,'Calc Cashflow'!N107)
...

Sheet Calc Smart
A1: row | C1: =IF(AND('My Debts'!$H$7="Allowed with a fee",N(+'My Debts'!$I$7)>0,ISNUMBER(C10)),IF(OR(N(+'My Debts'!$J$7)=0,C10<'My Debts'!$J$7),'My Debts'!$I$7,0),0) | D1: =IF(AND('My Debts'!$H$8="Allowed with a fee",N(+'My Debts'!$I$8)>0,ISNUMBER(D10)),IF(OR(N(+'My Debts'!$J$8)=0,D10<'My Debts'!$J$8),'My Debts'!$I$8,0),0) | E1: =IF(AND('My Debts'!$H$9="Allowed with a fee",N(+'My Debts'!$I$9)>0,ISNUMBER(E10)),IF(OR(N(+'My Debts'!$J$9)=0,E10<'My Debts'!$J$9),'My Debts'!$I$9,0),0) | F1: =IF(AND('My Debts'!$H$10="Allowed with a fee",N(+'My Debts'!$I$10)>0,ISNUMBER(F10)),IF(OR(N(+'My Debts'!$J$10)=0,F10<'My Debts'!$J$10),'My Debts'!$I$10,0),0) | G1: =IF(AND('My Debts'!$H$11="Allowed with a fee",N(+'My Debts'!$I$11)>0,ISNUMBER(G10)),IF(OR(N(+'My Debts'!$J$11)=0,G10<'My Debts'!$J$11),'My Debts'!$I$11,0),0) | H1: =IF(AND('My Debts'!$H$12="Allowed with a fee",N(+'My Debts'!$I$12)>0,ISNUMBER(H10)),IF(OR(N(+'My Debts'!$J$12)=0,H10<'My Debts'!$J$12),'My Debts'!$I$12,0),0) | I1: =IF(AND('My Debts'!$H$13="Allowed with a fee",N(+'My Debts'!$I$13)>0,ISNUMBER(I10)),IF(OR(N(+'My Debts'!$J$13)=0,I10<'My Debts'!$J$13),'My Debts'!$I$13,0),0) | J1: =IF(AND('My Debts'!$H$14="Allowed with a fee",N(+'My Debts'!$I$14)>0,ISNUMBER(J10)),IF(OR(N(+'My Debts'!$J$14)=0,J10<'My Debts'!$J$14),'My Debts'!$I$14,0),0) | K1: =IF(AND('My Debts'!$H$15="Allowed with a fee",N(+'My Debts'!$I$15)>0,ISNUMBER(K10)),IF(OR(N(+'My Debts'!$J$15)=0,K10<'My Debts'!$J$15),'My Debts'!$I$15,0),0) | L1: =IF(AND('My Debts'!$H$16="Allowed with a fee",N(+'My Debts'!$I$16)>0,ISNUMBER(L10)),IF(OR(N(+'My Debts'!$J$16)=0,L10<'My Debts'!$J$16),'My Debts'!$I$16,0),0) | M1: =IF(AND('My Debts'!$H$17="Allowed with a fee",N(+'My Debts'!$I$17)>0,ISNUMBER(M10)),IF(OR(N(+'My Debts'!$J$17)=0,M10<'My Debts'!$J$17),'My Debts'!$I$17,0),0) | N1: =IF(AND('My Debts'!$H$18="Allowed with a fee",N(+'My Debts'!$I$18)>0,ISNUMBER(N10)),IF(OR(N(+'My Debts'!$J$18)=0,N10<'My Debts'!$J$18),'My Debts'!$I$18,0),0)
A2: rank | C2: =IF('My Debts'!$AA$7="",999,'My Debts'!$AA$7) | D2: =IF('My Debts'!$AA$8="",999,'My Debts'!$AA$8) | E2: =IF('My Debts'!$AA$9="",999,'My Debts'!$AA$9) | F2: =IF('My Debts'!$AA$10="",999,'My Debts'!$AA$10) | G2: =IF('My Debts'!$AA$11="",999,'My Debts'!$AA$11) | H2: =IF('My Debts'!$AA$12="",999,'My Debts'!$AA$12) | I2: =IF('My Debts'!$AA$13="",999,'My Debts'!$AA$13) | J2: =IF('My Debts'!$AA$14="",999,'My Debts'!$AA$14) | K2: =IF('My Debts'!$AA$15="",999,'My Debts'!$AA$15) | L2: =IF('My Debts'!$AA$16="",999,'My Debts'!$AA$16) | M2: =IF('My Debts'!$AA$17="",999,'My Debts'!$AA$17) | N2: =IF('My Debts'!$AA$18="",999,'My Debts'!$AA$18)
A3: extra from | C3: =IF('My Debts'!$U$7="",DATE(2199,12,1),'My Debts'!$U$7) | D3: =IF('My Debts'!$U$8="",DATE(2199,12,1),'My Debts'!$U$8) | E3: =IF('My Debts'!$U$9="",DATE(2199,12,1),'My Debts'!$U$9) | F3: =IF('My Debts'!$U$10="",DATE(2199,12,1),'My Debts'!$U$10) | G3: =IF('My Debts'!$U$11="",DATE(2199,12,1),'My Debts'!$U$11) | H3: =IF('My Debts'!$U$12="",DATE(2199,12,1),'My Debts'!$U$12) | I3: =IF('My Debts'!$U$13="",DATE(2199,12,1),'My Debts'!$U$13) | J3: =IF('My Debts'!$U$14="",DATE(2199,12,1),'My Debts'!$U$14) | K3: =IF('My Debts'!$U$15="",DATE(2199,12,1),'My Debts'!$U$15) | L3: =IF('My Debts'!$U$16="",DATE(2199,12,1),'My Debts'!$U$16) | M3: =IF('My Debts'!$U$17="",DATE(2199,12,1),'My Debts'!$U$17) | N3: =IF('My Debts'!$U$18="",DATE(2199,12,1),'My Debts'!$U$18)
A4: APR now | C4: =N(+'My Debts'!$E$7) | D4: =N(+'My Debts'!$E$8) | E4: =N(+'My Debts'!$E$9) | F4: =N(+'My Debts'!$E$10) | G4: =N(+'My Debts'!$E$11) | H4: =N(+'My Debts'!$E$12) | I4: =N(+'My Debts'!$E$13) | J4: =N(+'My Debts'!$E$14) | K4: =N(+'My Debts'!$E$15) | L4: =N(+'My Debts'!$E$16) | M4: =N(+'My Debts'!$E$17) | N4: =N(+'My Debts'!$E$18)
A5: debt-free | B5: =IFERROR(INDEX($B$12:$B$371,MATCH(1,INDEX(($AD$12:$AD$371<=0.005)*1,0),0)),"-") | C5: =IF(N(+'My Debts'!$L$7)>0,'My Debts'!$L$7,C4) | D5: =IF(N(+'My Debts'!$L$8)>0,'My Debts'!$L$8,D4) | E5: =IF(N(+'My Debts'!$L$9)>0,'My Debts'!$L$9,E4) | F5: =IF(N(+'My Debts'!$L$10)>0,'My Debts'!$L$10,F4) | G5: =IF(N(+'My Debts'!$L$11)>0,'My Debts'!$L$11,G4) | H5: =IF(N(+'My Debts'!$L$12)>0,'My Debts'!$L$12,H4) | I5: =IF(N(+'My Debts'!$L$13)>0,'My Debts'!$L$13,I4) | J5: =IF(N(+'My Debts'!$L$14)>0,'My Debts'!$L$14,J4) | K5: =IF(N(+'My Debts'!$L$15)>0,'My Debts'!$L$15,K4) | L5: =IF(N(+'My Debts'!$L$16)>0,'My Debts'!$L$16,L4) | M5: =IF(N(+'My Debts'!$L$17)>0,'My Debts'!$L$17,M4) | N5: =IF(N(+'My Debts'!$L$18)>0,'My Debts'!$L$18,N4)
A6: months | B6: =IFERROR(MATCH(1,INDEX(($AD$12:$AD$371<=0.005)*1,0),0),"-") | C6: =N(+'My Debts'!$K$7) | D6: =N(+'My Debts'!$K$8) | E6: =N(+'My Debts'!$K$9) | F6: =N(+'My Debts'!$K$10) | G6: =N(+'My Debts'!$K$11) | H6: =N(+'My Debts'!$K$12) | I6: =N(+'My Debts'!$K$13) | J6: =N(+'My Debts'!$K$14) | K6: =N(+'My Debts'!$K$15) | L6: =N(+'My Debts'!$K$16) | M6: =N(+'My Debts'!$K$17) | N6: =N(+'My Debts'!$K$18)
A7: interest | B7: =SUM($O$12:$Z$371)-(SUM($C$8:$N$8)-SUM($C$371:$N$371)) | C7: =N(+'My Debts'!$F$7) | D7: =N(+'My Debts'!$F$8) | E7: =N(+'My Debts'!$F$9) | F7: =N(+'My Debts'!$F$10) | G7: =N(+'My Debts'!$F$11) | H7: =N(+'My Debts'!$F$12) | I7: =N(+'My Debts'!$F$13) | J7: =N(+'My Debts'!$F$14) | K7: =N(+'My Debts'!$F$15) | L7: =N(+'My Debts'!$F$16) | M7: =N(+'My Debts'!$F$17) | N7: =N(+'My Debts'!$F$18)
A8: fees | B8: =SUM($C$1:$N$1) | C8: =IF(AND(ISNUMBER('My Debts'!$D$7),'My Debts'!$D$7>0),'My Debts'!$D$7,0) | D8: =IF(AND(ISNUMBER('My Debts'!$D$8),'My Debts'!$D$8>0),'My Debts'!$D$8,0) | E8: =IF(AND(ISNUMBER('My Debts'!$D$9),'My Debts'!$D$9>0),'My Debts'!$D$9,0) | F8: =IF(AND(ISNUMBER('My Debts'!$D$10),'My Debts'!$D$10>0),'My Debts'!$D$10,0) | G8: =IF(AND(ISNUMBER('My Debts'!$D$11),'My Debts'!$D$11>0),'My Debts'!$D$11,0) | H8: =IF(AND(ISNUMBER('My Debts'!$D$12),'My Debts'!$D$12>0),'My Debts'!$D$12,0) | I8: =IF(AND(ISNUMBER('My Debts'!$D$13),'My Debts'!$D$13>0),'My Debts'!$D$13,0) | J8: =IF(AND(ISNUMBER('My Debts'!$D$14),'My Debts'!$D$14>0),'My Debts'!$D$14,0) | K8: =IF(AND(ISNUMBER('My Debts'!$D$15),'My Debts'!$D$15>0),'My Debts'!$D$15,0) | L8: =IF(AND(ISNUMBER('My Debts'!$D$16),'My Debts'!$D$16>0),'My Debts'!$D$16,0) | M8: =IF(AND(ISNUMBER('My Debts'!$D$17),'My Debts'!$D$17>0),'My Debts'!$D$17,0) | N8: =IF(AND(ISNUMBER('My Debts'!$D$18),'My Debts'!$D$18>0),'My Debts'!$D$18,0)
A9: first | B9: =IF(COUNT($C$10:$N$10)=0,"-",MIN($C$10:$N$10))
C10: =IF(C8<=0,"",IFERROR(INDEX($B$12:$B$371,MATCH(1,INDEX((C$12:C$371<=0.005)*1,0),0)),"")) | D10: =IF(D8<=0,"",IFERROR(INDEX($B$12:$B$371,MATCH(1,INDEX((D$12:D$371<=0.005)*1,0),0)),"")) | E10: =IF(E8<=0,"",IFERROR(INDEX($B$12:$B$371,MATCH(1,INDEX((E$12:E$371<=0.005)*1,0),0)),"")) | F10: =IF(F8<=0,"",IFERROR(INDEX($B$12:$B$371,MATCH(1,INDEX((F$12:F$371<=0.005)*1,0),0)),"")) | G10: =IF(G8<=0,"",IFERROR(INDEX($B$12:$B$371,MATCH(1,INDEX((G$12:G$371<=0.005)*1,0),0)),"")) | H10: =IF(H8<=0,"",IFERROR(INDEX($B$12:$B$371,MATCH(1,INDEX((H$12:H$371<=0.005)*1,0),0)),"")) | I10: =IF(I8<=0,"",IFERROR(INDEX($B$12:$B$371,MATCH(1,INDEX((I$12:I$371<=0.005)*1,0),0)),"")) | J10: =IF(J8<=0,"",IFERROR(INDEX($B$12:$B$371,MATCH(1,INDEX((J$12:J$371<=0.005)*1,0),0)),"")) | ... N10: =IF(N8<=0,"",IFERROR(INDEX($B$12:$B$371,MATCH(1,INDEX((N$12:N$371<=0.005)*1,0),0)),""))
B11: =EDATE(Plan!$C$6,-1) | C11: =C8 | D11: =D8 | E11: =E8 | F11: =F8 | G11: =G8 | H11: =H8 | I11: =I8 | J11: =J8 | ... N11: =N8 | AD11: =SUM(C11:N11)
A12: 1 | B12: =EDATE(Plan!$C$6,0) | C12: =IF(C11<=0,0,MAX(0,AH12-O12)) | D12: =IF(D11<=0,0,MAX(0,AI12-P12)) | E12: =IF(E11<=0,0,MAX(0,AJ12-Q12)) | F12: =IF(F11<=0,0,MAX(0,AK12-R12)) | G12: =IF(G11<=0,0,MAX(0,AL12-S12)) | H12: =IF(H11<=0,0,MAX(0,AM12-T12)) | I12: =IF(I11<=0,0,MAX(0,AN12-U12)) | J12: =IF(J11<=0,0,MAX(0,AO12-V12)) | ... N12: =IF(N11<=0,0,MAX(0,AS12-Z12)) | O12: =IF(C11<=0,0,MIN(AH12,C$7+IF(C$2=$AA12,$AC12,IF(C$2=$AF12,$AG12,0)))) | P12: =IF(D11<=0,0,MIN(AI12,D$7+IF(D$2=$AA12,$AC12,IF(D$2=$AF12,$AG12,0)))) | Q12: =IF(E11<=0,0,MIN(AJ12,E$7+IF(E$2=$AA12,$AC12,IF(E$2=$AF12,$AG12,0)))) | R12: =IF(F11<=0,0,MIN(AK12,F$7+IF(F$2=$AA12,$AC12,IF(F$2=$AF12,$AG12,0)))) | S12: =IF(G11<=0,0,MIN(AL12,G$7+IF(G$2=$AA12,$AC12,IF(G$2=$AF12,$AG12,0)))) | T12: =IF(H11<=0,0,MIN(AM12,H$7+IF(H$2=$AA12,$AC12,IF(H$2=$AF12,$AG12,0)))) | U12: =IF(I11<=0,0,MIN(AN12,I$7+IF(I$2=$AA12,$AC12,IF(I$2=$AF12,$AG12,0)))) | V12: =IF(J11<=0,0,MIN(AO12,J$7+IF(J$2=$AA12,$AC12,IF(J$2=$AF12,$AG12,0)))) | ... Z12: =IF(N11<=0,0,MIN(AS12,N$7+IF(N$2=$AA12,$AC12,IF(N$2=$AF12,$AG12,0)))) | AA12: =IFERROR(ROUND(1/SUMPRODUCT(MAX((C11:N11>0)*($C$3:$N$3<=B12)/$C$2:$N$2)),0),0) | AB12: =SUMPRODUCT((C11:N11>0)*$C$7:$N$7) | AC12: =MAX(0,Plan!$C$5-AB12)+IF(A12=Plan!$C$8,N(Plan!$C$7),0) | AD12: =SUM(C12:N12) | AE12: =SUM(O12:Z12) | AF12: =IFERROR(ROUND(1/SUMPRODUCT(MAX((C11:N11>0)*($C$3:$N$3<=B12)*($C$2:$N$2>AA12)/$C$2:$N$2)),0),0) | AG12: =MAX(0,AC12-MAX(0,SUMPRODUCT(($C$2:$N$2=AA12)*(AH12:AS12-$C$7:$N$7)))) | AH12: =IF(C11<=0,0,ROUND(C11*(1+IF(AND(C$6>0,$B12<C$6),C$4,C$5)/12),2)) | AI12: =IF(D11<=0,0,ROUND(D11*(1+IF(AND(D$6>0,$B12<D$6),D$4,D$5)/12),2)) | AJ12: =IF(E11<=0,0,ROUND(E11*(1+IF(AND(E$6>0,$B12<E$6),E$4,E$5)/12),2)) | AK12: =IF(F11<=0,0,ROUND(F11*(1+IF(AND(F$6>0,$B12<F$6),F$4,F$5)/12),2)) | AL12: =IF(G11<=0,0,ROUND(G11*(1+IF(AND(G$6>0,$B12<G$6),G$4,G$5)/12),2)) | AM12: =IF(H11<=0,0,ROUND(H11*(1+IF(AND(H$6>0,$B12<H$6),H$4,H$5)/12),2)) | AN12: =IF(I11<=0,0,ROUND(I11*(1+IF(AND(I$6>0,$B12<I$6),I$4,I$5)/12),2)) | AO12: =IF(J11<=0,0,ROUND(J11*(1+IF(AND(J$6>0,$B12<J$6),J$4,J$5)/12),2)) | ... AS12: =IF(N11<=0,0,ROUND(N11*(1+IF(AND(N$6>0,$B12<N$6),N$4,N$5)/12),2))
A13: 2 | B13: =EDATE(Plan!$C$6,1) | C13: =IF(C12<=0,0,MAX(0,AH13-O13)) | D13: =IF(D12<=0,0,MAX(0,AI13-P13)) | E13: =IF(E12<=0,0,MAX(0,AJ13-Q13)) | F13: =IF(F12<=0,0,MAX(0,AK13-R13)) | G13: =IF(G12<=0,0,MAX(0,AL13-S13)) | H13: =IF(H12<=0,0,MAX(0,AM13-T13)) | I13: =IF(I12<=0,0,MAX(0,AN13-U13)) | J13: =IF(J12<=0,0,MAX(0,AO13-V13)) | ... N13: =IF(N12<=0,0,MAX(0,AS13-Z13)) | O13: =IF(C12<=0,0,MIN(AH13,C$7+IF(C$2=$AA13,$AC13,IF(C$2=$AF13,$AG13,0)))) | P13: =IF(D12<=0,0,MIN(AI13,D$7+IF(D$2=$AA13,$AC13,IF(D$2=$AF13,$AG13,0)))) | Q13: =IF(E12<=0,0,MIN(AJ13,E$7+IF(E$2=$AA13,$AC13,IF(E$2=$AF13,$AG13,0)))) | R13: =IF(F12<=0,0,MIN(AK13,F$7+IF(F$2=$AA13,$AC13,IF(F$2=$AF13,$AG13,0)))) | S13: =IF(G12<=0,0,MIN(AL13,G$7+IF(G$2=$AA13,$AC13,IF(G$2=$AF13,$AG13,0)))) | T13: =IF(H12<=0,0,MIN(AM13,H$7+IF(H$2=$AA13,$AC13,IF(H$2=$AF13,$AG13,0)))) | U13: =IF(I12<=0,0,MIN(AN13,I$7+IF(I$2=$AA13,$AC13,IF(I$2=$AF13,$AG13,0)))) | V13: =IF(J12<=0,0,MIN(AO13,J$7+IF(J$2=$AA13,$AC13,IF(J$2=$AF13,$AG13,0)))) | ... Z13: =IF(N12<=0,0,MIN(AS13,N$7+IF(N$2=$AA13,$AC13,IF(N$2=$AF13,$AG13,0)))) | AA13: =IFERROR(ROUND(1/SUMPRODUCT(MAX((C12:N12>0)*($C$3:$N$3<=B13)/$C$2:$N$2)),0),0) | AB13: =SUMPRODUCT((C12:N12>0)*$C$7:$N$7) | AC13: =MAX(0,Plan!$C$5-AB13)+IF(A13=Plan!$C$8,N(Plan!$C$7),0) | AD13: =SUM(C13:N13) | AE13: =SUM(O13:Z13) | AF13: =IFERROR(ROUND(1/SUMPRODUCT(MAX((C12:N12>0)*($C$3:$N$3<=B13)*($C$2:$N$2>AA13)/$C$2:$N$2)),0),0) | AG13: =MAX(0,AC13-MAX(0,SUMPRODUCT(($C$2:$N$2=AA13)*(AH13:AS13-$C$7:$N$7)))) | AH13: =IF(C12<=0,0,ROUND(C12*(1+IF(AND(C$6>0,$B13<C$6),C$4,C$5)/12),2)) | AI13: =IF(D12<=0,0,ROUND(D12*(1+IF(AND(D$6>0,$B13<D$6),D$4,D$5)/12),2)) | AJ13: =IF(E12<=0,0,ROUND(E12*(1+IF(AND(E$6>0,$B13<E$6),E$4,E$5)/12),2)) | AK13: =IF(F12<=0,0,ROUND(F12*(1+IF(AND(F$6>0,$B13<F$6),F$4,F$5)/12),2)) | AL13: =IF(G12<=0,0,ROUND(G12*(1+IF(AND(G$6>0,$B13<G$6),G$4,G$5)/12),2)) | AM13: =IF(H12<=0,0,ROUND(H12*(1+IF(AND(H$6>0,$B13<H$6),H$4,H$5)/12),2)) | AN13: =IF(I12<=0,0,ROUND(I12*(1+IF(AND(I$6>0,$B13<I$6),I$4,I$5)/12),2)) | AO13: =IF(J12<=0,0,ROUND(J12*(1+IF(AND(J$6>0,$B13<J$6),J$4,J$5)/12),2)) | ... AS13: =IF(N12<=0,0,ROUND(N12*(1+IF(AND(N$6>0,$B13<N$6),N$4,N$5)/12),2))
